Workbook

Sheet BUDGET 2024-2025
B8: Financial Budget for Academic year 2024-2025
B9: September | C9: October | D9: November | E9: December | F9: January | G9: February | H9: March | I9: April | J9: May | K9: June | L9: July | M9: August | N9: GENERAL TOTAL
B10: TOTAL | C10: TOTAL | D10: TOTAL | E10: TOTAL | F10: TOTAL | G10: TOTAL | H10: TOTAL | I10: TOTAL | J10: TOTAL | K10: TOTAL | L10: TOTAL | M10: TOTAL | N10: TOTAL
A11: Budgeted Number of Students | N11: ='INCOME DETAILS'!Q121 -> 3997
A12: Revenue
A13: Tuition Fees
A14: Faculty of Catechesis and Religious Sciences | B14: =N14/12 -> 6041666.7 | C14: 6041666.7 | D14: 6041666.7 | E14: 6041666.7 | F14: 6041666.7 | G14: 6041666.7 | H14: 6041666.7 | I14: 6041666.7 | J14: 6041666.7 | K14: 6041666.7 | L14: 6041666.7 | M14: 6041666.7 | N14: ='INCOME DETAILS'!AB104 -> 72500000
A15: Faculty of Commerce | B15: =N15/12 -> 10250000 | C15: 12437500 | D15: 12437500 | E15: 12437500 | F15: 12437500 | G15: 12437500 | H15: 12437500 | I15: 12437500 | J15: 12437500 | K15: 12437500 | L15: 12437500 | M15: 12437500 | N15: ='INCOME DETAILS'!AB112 -> 123000000
A16: Faculty of Education -under graduates | B16: =N16/12 -> 41477500 | C16: 45802500 | D16: 45802500 | E16: 45802500 | F16: 45802500 | G16: 45802500 | H16: 45802500 | I16: 45802500 | J16: 45802500 | K16: 45802500 | L16: 45802500 | M16: 45802500 | N16: ='INCOME DETAILS'!AB62 -> 497730000
A17: Faculty of Education -PGD- Taba campus-Kibungo Learning Center | B17: =N17/12 -> 5160750 | C17: 7155750 | D17: 7155750 | E17: 7155750 | F17: 7155750 | G17: 7155750 | H17: 7155750 | I17: 7155750 | J17: 7155750 | K17: 7155750 | L17: 7155750 | M17: 7155750 | N17: ='INCOME DETAILS'!AB117 -> 61929000
A18: Faculty of Public Health and Human Nutrition | B18: =N18/12 -> 3428333.3 | C18: 9997083.3 | D18: 9997083.3 | E18: 9997083.3 | F18: 9997083.3 | G18: 9997083.3 | H18: 9997083.3 | I18: 9997083.3 | J18: 9997083.3 | K18: 9997083.3 | L18: 9997083.3 | M18: 9997083.3 | N18: ='INCOME DETAILS'!AB96 -> 41140000
A19: Faculty of Science and Technology | B19: =N19/12 -> 10931250 | C19: 12264583 | D19: 12264583 | E19: 12264583 | F19: 12264583 | G19: 12264583 | H19: 12264583 | I19: 12264583 | J19: 12264583 | K19: 12264583 | L19: 12264583 | M19: 12264583 | N19: ='INCOME DETAILS'!AB28 -> 131175000
A20: Faculty of Social Work | B20: =N20/12 -> 2770833.3 | C20: 2770833.3 | D20: 2770833.3 | E20: 2770833.3 | F20: 2770833.3 | G20: 2770833.3 | H20: 2770833.3 | I20: 2770833.3 | J20: 2770833.3 | K20: 2770833.3 | L20: 2770833.3 | M20: 2770833.3 | N20: ='INCOME DETAILS'!AB36 -> 33250000
A21: Expected New Masters Program fees | K21: =N21/3 -> 0 | L21: 0 | M21: 0 | N21: ='INCOME DETAILS'!AB120 -> 0
A22: Ministry of health sponsored student
A23: Existing Sponsored | B23: =N23/12 -> 23065417 | C23: 23065417 | D23: 23065417 | E23: 23065417 | F23: 23065417 | G23: 23065417 | H23: 23065417 | I23: 23065417 | J23: 23065417 | K23: 23065417 | L23: 23065417 | M23: 23065417 | N23: 276785000 | O23: =N23+N24+N25+N26-N24 -> 7.1875399e+08
A24: Projected Sponsored | K24: =N24/3 -> 24625000 | L24: 24625000 | M24: 24625000 | N24: ='INCOME DETAILS'!S124 -> 73875000
A25: Chancen Student Tuition fees | B25: =N25/12 -> 32324778 | C25: 32324778 | D25: 32324778 | E25: 32324778 | F25: 32324778 | G25: 32324778 | H25: 32324778 | I25: 32324778 | J25: 32324778 | K25: 32324778 | L25: 32324778 | M25: 32324778 | N25: ='INCOME DETAILS'!F133 -> 3.8789733e+08
A26: YWCA | F26: =N26/9 -> 6007962.2 | G26: 6007962.2 | H26: 6007962.2 | I26: 6007962.2 | J26: 6007962.2 | K26: 6007962.2 | L26: 6007962.2 | M26: 6007962.2 | N26: ='INCOME DETAILS'!E140 -> 54071660
A27: Total Tuition fees | B27: =SUM(B14:B26) -> 1.3545053e+08 | C27: =SUM(C14:C26) -> 1.5186011e+08 | D27: =SUM(D14:D26) -> 1.5186011e+08 | E27: =SUM(E14:E26) -> 1.5186011e+08 | F27: =SUM(F14:F26) -> 1.5786807e+08 | G27: =SUM(G14:G26) -> 1.5786807e+08 | H27: =SUM(H14:H26) -> 1.5786807e+08 | I27: =SUM(I14:I26) -> 1.5786807e+08 | ... N27: =SUM(N14:N26) -> 1.753353e+09
A28: Application fees | B28: =N28/12 -> 703333.33 | C28: 930416.67 | D28: 930416.67 | E28: 930416.67 | F28: 930416.67 | G28: 930416.67 | H28: 930416.67 | I28: 930416.67 | J28: 930416.67 | K28: 930416.67 | L28: 930416.67 | M28: 930416.67 | N28: ='INCOME DETAILS'!AD121 -> 8440000
A29: Internship fees | B29: =N29/12 -> 3187500 | C29: 2870833.3 | D29: 2870833.3 | E29: 2870833.3 | F29: 2870833.3 | G29: 2870833.3 | H29: 2870833.3 | I29: 2870833.3 | J29: 2870833.3 | K29: 2870833.3 | L29: 2870833.3 | M29: 2870833.3 | N29: ='INCOME DETAILS'!AE121 -> 38250000
A30: Research supervision fees | B30: =N30/12 -> 3837500 | C30: 3837500 | D30: 3837500 | E30: 3837500 | F30: 3837500 | G30: 3837500 | H30: 3837500 | I30: 3837500 | J30: 3837500 | K30: 3837500 | L30: 3837500 | M30: 3837500 | N30: ='INCOME DETAILS'!AF121 -> 46050000
A31: Graduation fees | J31: =N31 -> 13000000 | N31: =260*50000 -> 13000000
A32: Fines | B32: =N32/12 -> 50820 | C32: 50820 | D32: 50820 | E32: 50820 | F32: 50820 | G32: 50820 | H32: 50820 | I32: 50820 | J32: 50820 | K32: 50820 | L32: 50820 | M32: 50820 | N32: 609840
A33: Retake fees | B33: =N33/12 -> 33333.333 | C33: 33333.333 | D33: 33333.333 | E33: 33333.333 | F33: 33333.333 | G33: 33333.333 | H33: 33333.333 | I33: 33333.333 | J33: 33333.333 | K33: 33333.333 | L33: 33333.333 | M33: 33333.333 | N33: 400000
A34: Academic documents fees | B34: =N34/12 -> 232466.67 | C34: 232466.67 | D34: 232466.67 | E34: 232466.67 | F34: 232466.67 | G34: 232466.67 | H34: 232466.67 | I34: 232466.67 | J34: 232466.67 | K34: 232466.67 | L34: 232466.67 | M34: 232466.67 | N34: 2789600
A35: Total academic cost | B35: =SUM(B27:B34) -> 1.4349548e+08 | C35: =SUM(C27:C34) -> 1.5981548e+08 | D35: =SUM(D27:D34) -> 1.5981548e+08 | E35: =SUM(E27:E34) -> 1.5981548e+08 | F35: =SUM(F27:F34) -> 1.6582344e+08 | G35: =SUM(G27:G34) -> 1.6582344e+08 | H35: =SUM(H27:H34) -> 1.6582344e+08 | I35: =SUM(I27:I34) -> 1.6582344e+08 | ... N35: =SUM(N27:N34) -> 1.8628924e+09
A37: Other Income
A38: Accomodation fee | B38: =N38/12 -> 1309000 | C38: 109083.33 | D38: 109083.33 | E38: 109083.33 | F38: 109083.33 | G38: 109083.33 | H38: 109083.33 | I38: 109083.33 | J38: 109083.33 | K38: 109083.33 | L38: 109083.33 | M38: 109083.33 | N38: =187*7000*12 -> 15708000
A39: Other Income(Different IURA Projects) | F39: =N39/8 -> 12500000 | G39: 12500000 | H39: 12500000 | I39: 12500000 | J39: 12500000 | K39: 12500000 | L39: 12500000 | M39: 12500000 | N39: 100000000
A40: Total Income | B40: =B38+B39 -> 1309000 | C40: =C38+C39 -> 109083.33 | D40: =D38+D39 -> 109083.33 | E40: =E38+E39 -> 109083.33 | F40: =F38+F39 -> 12609083 | G40: =G38+G39 -> 12609083 | H40: =H38+H39 -> 12609083 | I40: =I38+I39 -> 12609083 | ... N40: =N38+N39 -> 115708000
A41: TOTAL REVENUE(A) | B41: =B40+B35 -> 1.4480448e+08 | C41: =C40+C35 -> 1.5992456e+08 | D41: =D40+D35 -> 1.5992456e+08 | E41: =E40+E35 -> 1.5992456e+08 | F41: =F40+F35 -> 1.7843253e+08 | G41: =G40+G35 -> 1.7843253e+08 | H41: =H40+H35 -> 1.7843253e+08 | I41: =I40+I35 -> 1.7843253e+08 | ... N41: =N40+N35 -> 1.9786004e+09
A42: OPERATING EXPENSES
A43: Staff Cost
A44: Full timeTeaching staff | B44: 32407582 | C44: 32407582 | D44: 32407582 | E44: 32407582 | F44: 32407582 | G44: 32407582 | H44: 32407582 | I44: 32407582 | J44: 32407582 | K44: 36319385 | L44: 36319385 | M44: 36319385 | N44: =SUM(B44:M44) -> 4.0062639e+08
A45: Part time teaching staff | B45: ='Part-time staff cost'!B13/12 -> 8044756.4 | C45: =B45 -> 8044756.4 | D45: =C45 -> 8044756.4 | E45: =D45 -> 8044756.4 | F45: =E45 -> 8044756.4 | G45: =F45 -> 8044756.4 | H45: =G45 -> 8044756.4 | I45: =H45 -> 8044756.4 | J45: =I45 -> 8044756.4 | ... M45: =L45 -> 8044756.4 | N45: =SUM(B45:M45) -> 96537077
A46: Administrative + Support staff | B46: 14887169 | C46: 14887169 | D46: 14887169 | E46: 14887169 | F46: 14887169 | G46: 14887169 | H46: 14887169 | I46: 14887169 | J46: 14887169 | K46: 17500450 | L46: 17500450 | M46: 17500450 | N46: =SUM(B46:M46) -> 1.8648587e+08
A47: Other payment(Consultancy fees) | B47: 2851511.5 | C47: 2851511.5 | D47: 2851511.5 | E47: 2851511.5 | F47: 2851511.5 | G47: 2851511.5 | H47: 2851511.5 | I47: 2851511.5 | J47: 2851511.5 | K47: 2851511.5 | L47: 2851511.5 | M47: 2851511.5 | N47: =SUM(B47:M47) -> 34218138
A48: CPA staff | B48: 1200000 | C48: 1200000 | D48: 1200000 | E48: 1200000 | F48: 1200000 | G48: 1200000 | H48: 1200000 | I48: 1200000 | J48: 1200000 | K48: 1200000 | L48: 1200000 | M48: 1200000 | N48: =SUM(B48:M48) -> 14400000
A49: Total Staff Cost | B49: =SUM(B44:B48) -> 59391019 | C49: =SUM(C44:C48) -> 59391019 | D49: =SUM(D44:D48) -> 59391019 | E49: =SUM(E44:E48) -> 59391019 | F49: =SUM(F44:F48) -> 59391019 | G49: =SUM(G44:G48) -> 59391019 | H49: =SUM(H44:H48) -> 59391019 | I49: =SUM(I44:I48) -> 59391019 | ... N49: =SUM(N44:N48) -> 7.3226748e+08
A50: Administrative Cost
A51: Communication | B51: 210000 | C51: 210000 | D51: 210000 | E51: 210000 | F51: 210000 | G51: 210000 | H51: 210000 | I51: 210000 | J51: 210000 | K51: 210000 | L51: 210000 | M51: 210000 | N51: =SUM(B51:M51) -> 2520000
A52: Security | B52: =720000+55000 -> 775000 | C52: =720000+55000 -> 775000 | D52: =720000+55000 -> 775000 | E52: =720000+55000 -> 775000 | F52: =720000+55000 -> 775000 | G52: =720000+55000 -> 775000 | H52: =720000+55000 -> 775000 | I52: =720000+55000 -> 775000 | ... M52: =720000+55000 -> 775000 | N52: =SUM(B52:M52) -> 9300000
A53: Water & Electricity | B53: 1342035 | C53: 1342035 | D53: 1342035 | E53: 1342035 | F53: 1342035 | G53: 1342035 | H53: 1342035 | I53: 1342035 | J53: 1342035 | K53: 1342035 | L53: 1342035 | M53: 1342035 | N53: =SUM(B53:M53) -> 16104420
A54: Medical insurance | B54: =N54/12 -> 1280603.4 | C54: 1280603.4 | D54: 1280603.4 | E54: 1280603.4 | F54: 1280603.4 | G54: 1280603.4 | H54: 1280603.4 | I54: 1280603.4 | J54: 1280603.4 | K54: 1280603.4 | L54: 1280603.4 | M54: 1280603.4 | N54: =(12234658+571376)*120% -> 15367241
A55: Rent ISR | B55: 800000 | C55: 800000 | D55: 800000 | E55: 800000 | F55: 800000 | G55: 800000 | H55: 800000 | I55: 800000 | J55: 800000 | K55: 800000 | L55: 800000 | M55: 800000 | N55: =SUM(B55:M55) -> 9600000
A56: Carburant/fuel | B56: 2020000 | C56: 2020000 | D56: 2020000 | E56: 2020000 | F56: 2020000 | G56: 2020000 | H56: 2020000 | I56: 2020000 | J56: 2020000 | K56: 2020000 | L56: 2020000 | M56: 2020000 | N56: =SUM(B56:M56) -> 24240000
A57: Supplies & office materials | B57: 3999855 | C57: 3999855 | D57: 3999855 | E57: 3999855 | F57: 3999855 | G57: 3999855 | H57: 3999855 | I57: 3999855 | J57: 3999855 | K57: 3999855 | L57: 3999855 | M57: 3999855 | N57: =SUM(B57:M57) -> 47998260
A58: Bank Charges | B58: =N58/12 -> 99705.6 | C58: 99705.6 | D58: 99705.6 | E58: 99705.6 | F58: 99705.6 | G58: 99705.6 | H58: 99705.6 | I58: 99705.6 | J58: 99705.6 | K58: 99705.6 | L58: 99705.6 | M58: 99705.6 | N58: =997056*120% -> 1196467.2
A59: Postal Charge | B59: =N59/12 -> 14640 | C59: 14640 | D59: 14640 | E59: 14640 | F59: 14640 | G59: 14640 | H59: 14640 | I59: 14640 | J59: 14640 | K59: 14640 | L59: 14640 | M59: 14640 | N59: =146400*120% -> 175680
A60: Interneship Supervision fees | B60: 3294272.8 | C60: 3294272.8 | D60: 3294272.8 | E60: 3294272.8 | F60: 3294272.8 | G60: 3294272.8 | H60: 3294272.8 | I60: 3294272.8 | J60: 3294272.8 | K60: 3294272.8 | L60: 3294272.8 | M60: 3294272.8 | N60: 39531274
A61: Maintenainance and repair | B61: 1172273.3 | C61: 1172273.3 | D61: 1172273.3 | E61: 1172273.3 | F61: 1172273.3 | G61: 1172273.3 | H61: 1172273.3 | I61: 1172273.3 | J61: 1172273.3 | K61: 1172273.3 | L61: 1172273.3 | M61: 1172273.3 | N61: =SUM(B61:M61) -> 14067279
A62: Marketing and Publicity | B62: =500000+400000+50000 -> 950000 | C62: =500000+400000+50000 -> 950000 | D62: =500000+400000+50000 -> 950000 | E62: =500000+400000+50000 -> 950000 | F62: =500000+400000+50000 -> 950000 | G62: =500000+400000+50000 -> 950000 | H62: =500000+400000+50000 -> 950000 | I62: =500000+400000+50000 -> 950000 | ... M62: =500000+400000+50000 -> 950000 | N62: =SUM(B62:M62) -> 11400000
A63: Marketing Agents Expenses fee | B63: 1038333.3 | C63: 1038333.3 | D63: 1038333.3 | E63: 1038333.3 | F63: 1038333.3 | G63: 1038333.3 | H63: 1038333.3 | I63: 1038333.3 | J63: 1038333.3 | K63: 1038333.3 | L63: 1038333.3 | M63: 1038333.3 | N63: ='INCOME DETAILS'!X124 -> 12460000
A64: Graduation expenses | B64: =N64/12 -> 833333.33 | C64: 833333.33 | D64: 833333.33 | E64: 833333.33 | F64: 833333.33 | G64: 833333.33 | H64: 833333.33 | I64: 833333.33 | J64: 833333.33 | K64: 833333.33 | L64: 833333.33 | M64: 833333.33 | N64: 10000000
A65: Vehicle Insurance | B65: =N65/12 -> 229814.67 | C65: 229814.67 | D65: 229814.67 | E65: 229814.67 | F65: 229814.67 | G65: 229814.67 | H65: 229814.67 | I65: 229814.67 | J65: 229814.67 | K65: 229814.67 | L65: 229814.67 | M65: 229814.67 | N65: 2757776
A66: Building Insurance | B66: =N66/12 -> 195082.08 | C66: 195082.08 | D66: 195082.08 | E66: 195082.08 | F66: 195082.08 | G66: 195082.08 | H66: 195082.08 | I66: 195082.08 | J66: 195082.08 | K66: 195082.08 | L66: 195082.08 | M66: 195082.08 | N66: 2340985
A67: Employees Capacity Building | B67: =N67/12 -> 333333.33 | C67: 333333.33 | D67: 333333.33 | E67: 333333.33 | F67: 333333.33 | G67: 333333.33 | H67: 333333.33 | I67: 333333.33 | J67: 333333.33 | K67: 333333.33 | L67: 333333.33 | M67: 333333.33 | N67: 4000000
A68: Accueil et reception | B68: =N68/12 -> 410922.75 | C68: 410922.75 | D68: 410922.75 | E68: 410922.75 | F68: 410922.75 | G68: 410922.75 | H68: 410922.75 | I68: 410922.75 | J68: 410922.75 | K68: 410922.75 | L68: 410922.75 | M68: 410922.75 | N68: 4931073
A69: Mission Fees | B69: =N69/12 -> 486777.08 | C69: 486777.08 | D69: 486777.08 | E69: 486777.08 | F69: 486777.08 | G69: 486777.08 | H69: 486777.08 | I69: 486777.08 | J69: 486777.08 | K69: 486777.08 | L69: 486777.08 | M69: 486777.08 | N69: 5841325
A70: Contribution in other Organism | B70: =N70/12 -> 250000 | C70: 250000 | D70: 250000 | E70: 250000 | F70: 250000 | G70: 250000 | H70: 250000 | I70: 250000 | J70: 250000 | K70: 250000 | L70: 250000 | M70: 250000 | N70: 3000000
A71: External Audit fee | B71: =N71/12 -> 250000 | C71: 250000 | D71: 250000 | E71: 250000 | F71: 250000 | G71: 250000 | H71: 250000 | I71: 250000 | J71: 250000 | K71: 250000 | L71: 250000 | M71: 250000 | N71: 3000000
A72: Public Relation | B72: =N72/12 -> 416666.67 | C72: 416666.67 | D72: 416666.67 | E72: 416666.67 | F72: 416666.67 | G72: 416666.67 | H72: 416666.67 | I72: 416666.67 | J72: 416666.67 | K72: 416666.67 | L72: 416666.67 | M72: 416666.67 | N72: 5000000
A73: Kibungo L.Center rental cost. | B73: 400000 | C73: 400000 | D73: 400000 | E73: 400000 | F73: 400000 | G73: 400000 | H73: 400000 | I73: 400000 | J73: 400000 | K73: 400000 | L73: 400000 | M73: 400000 | N73: =SUM(B73:M73) -> 4800000
A74: Partnership fees | B74: 3024380 | C74: 3024380 | D74: 3024380 | E74: 3024380 | F74: 3024380 | G74: 3024380 | H74: 3024380 | I74: 3024380 | J74: 3024380 | K74: 3024380 | L74: 3024380 | M74: 3024380 | N74: =SUM(B74:M74) -> 36292560
A75: Unforseen expenses | B75: 5000000 | C75: 5000000 | D75: 5000000 | E75: 5000000 | F75: 5000000 | G75: 5000000 | H75: 5000000 | I75: 5000000 | J75: 5000000 | K75: 5000000 | L75: 5000000 | M75: 5000000 | N75: =SUM(B75:M75) -> 60000000
A76: Total Admnistrative Cost | B76: =SUM(B51:B75) -> 28827028 | C76: =SUM(C51:C75) -> 28827028 | D76: =SUM(D51:D75) -> 28827028 | E76: =SUM(E51:E75) -> 28827028 | F76: =SUM(F51:F75) -> 28827028 | G76: =SUM(G51:G75) -> 28827028 | H76: =SUM(H51:H75) -> 28827028 | I76: =SUM(I51:I75) -> 28827028 | ... N76: =SUM(N51:N75) -> 3.4592434e+08
A77: Academic cost
A78: Research | B78: 1250000 | C78: 1250000 | D78: 1250000 | E78: 1250000 | F78: 1250000 | G78: 1250000 | H78: 1250000 | I78: 1250000 | J78: 1250000 | K78: 1250000 | L78: 1250000 | M78: 1250000 | N78: 15000000
A79: Seminars and conferences | B79: 170000 | C79: 170000 | D79: 170000 | E79: 170000 | F79: 170000 | G79: 170000 | H79: 170000 | I79: 170000 | J79: 170000 | K79: 170000 | L79: 170000 | M79: 170000 | N79: =SUM(B79:M79) -> 2040000
A80: Laboratory Consumables | B80: 1080208.3 | C80: 1080208.3 | D80: 1080208.3 | E80: 1080208.3 | F80: 1080208.3 | G80: 1080208.3 | H80: 1080208.3 | I80: 1080208.3 | J80: 1080208.3 | K80: 1080208.3 | L80: 1080208.3 | M80: 1080208.3 | N80: 12962500
A81: Designing and launching new programs | B81: 1084000 | C81: 1084000 | D81: 1084000 | E81: 1084000 | F81: 1084000 | G81: 1084000 | H81: 1084000 | I81: 1084000 | J81: 1084000 | K81: 1084000 | L81: 1084000 | M81: 1084000 | N81: =SUM(B81:M81) -> 13008000
A82: Other academic activities (field visit,community services..) | B82: 300000 | C82: 300000 | D82: 300000 | E82: 300000 | F82: 300000 | G82: 300000 | H82: 300000 | I82: 300000 | J82: 300000 | K82: 300000 | L82: 300000 | M82: 300000 | N82: =SUM(B82:M82) -> 3600000
A83: Responsability allowance | B83: 3600000 | C83: 3600000 | D83: 3600000 | E83: 3600000 | F83: 3600000 | G83: 3600000 | H83: 3600000 | I83: 3600000 | J83: 3600000 | K83: 3600000 | L83: 3600000 | M83: 3600000 | N83: =SUM(B83:M83) -> 43200000
A84: Panel fees | B84: =N84/12 -> 758333.33 | C84: 758333.33 | D84: 758333.33 | E84: 758333.33 | F84: 758333.33 | G84: 758333.33 | H84: 758333.33 | I84: 758333.33 | J84: 758333.33 | K84: 758333.33 | L84: 758333.33 | M84: 758333.33 | N84: 9100000
A85: Total Academic Cost | B85: =SUM(B78:B84) -> 8242541.7 | C85: =SUM(C78:C84) -> 8242541.7 | D85: =SUM(D78:D84) -> 8242541.7 | E85: =SUM(E78:E84) -> 8242541.7 | F85: =SUM(F78:F84) -> 8242541.7 | G85: =SUM(G78:G84) -> 8242541.7 | H85: =SUM(H78:H84) -> 8242541.7 | I85: =SUM(I78:I84) -> 8242541.7 | ... N85: =SUM(N78:N84) -> 98910500
A86: ICT COST
A87: Subscription to anti plagiarism software | B87: =N87/12 -> 73333.333 | C87: 73333.333 | D87: 73333.333 | E87: 73333.333 | F87: 73333.333 | G87: 73333.333 | H87: 73333.333 | I87: 73333.333 | J87: 73333.333 | K87: 73333.333 | L87: 73333.333 | M87: 73333.333 | N87: 880000
A88: Kaspesky (Antivirus ) | B88: =N88/12 -> 125000 | C88: 125000 | D88: 125000 | E88: 125000 | F88: 125000 | G88: 125000 | H88: 125000 | I88: 125000 | J88: 125000 | K88: 125000 | L88: 125000 | M88: 125000 | N88: 1500000
A89: Maintenance of IT equipment | B89: 431112.5 | C89: 431112.5 | D89: 431112.5 | E89: 431112.5 | F89: 431112.5 | G89: 431112.5 | H89: 431112.5 | I89: 431112.5 | J89: 431112.5 | K89: 431112.5 | L89: 431112.5 | M89: 431112.5 | N89: 5173350
A90: Website hosting+Elearning platform hosting + MIS Hosting | B90: 250000 | C90: 250000 | D90: 250000 | E90: 250000 | F90: 250000 | G90: 250000 | H90: 250000 | I90: 250000 | J90: 250000 | K90: 250000 | L90: 250000 | M90: 250000 | N90: 5173350
A91: School gear fees | B91: 666166.67 | C91: 666166.67 | D91: 666166.67 | E91: 666166.67 | F91: 666166.67 | G91: 666166.67 | H91: 666166.67 | I91: 666166.67 | J91: 666166.67 | K91: 666166.67 | L91: 666166.67 | M91: 666166.67 | N91: =N11*2000 -> 7994000
A92: Supplying softwares(library& registry) | B92: =N92/12 -> 166666.67 | C92: 166666.67 | D92: 166666.67 | E92: 166666.67 | F92: 166666.67 | G92: 166666.67 | H92: 166666.67 | I92: 166666.67 | J92: 166666.67 | K92: 166666.67 | L92: 166666.67 | M92: 166666.67 | N92: 2000000
A93: Subsription to online meeting software like webex, Ms team, Zoom | B93: =N93/12 -> 166666.67 | C93: 83333.333 | D93: 83333.333 | E93: 83333.333 | F93: 83333.333 | G93: 83333.333 | H93: 83333.333 | I93: 83333.333 | J93: 83333.333 | K93: 83333.333 | L93: 83333.333 | M93: 83333.333 | N93: 2000000
A94: Configuration of CUR Server room | B94: =N94/12 -> 250000 | C94: 250000 | D94: 250000 | E94: 250000 | F94: 250000 | G94: 250000 | H94: 250000 | I94: 250000 | J94: 250000 | K94: 250000 | L94: 250000 | M94: 250000 | N94: 3000000
A95: Annual Internet connection subscriptionn:(Taba and Save) | B95: 1274400 | C95: 1274400 | D95: 1890528 | E95: 1890528 | F95: 1890528 | G95: 1890528 | H95: 1890528 | I95: 1890528 | J95: 1890528 | K95: 1890528 | L95: 1890528 | M95: 1890528 | N95: =SUM(B95:M95) -> 21454080
A96: Total ICT COST | B96: =SUM(B87:B95) -> 3403345.8 | C96: =SUM(C87:C95) -> 3320012.5 | D96: =SUM(D87:D95) -> 3936140.5 | E96: =SUM(E87:E95) -> 3936140.5 | F96: =SUM(F87:F95) -> 3936140.5 | G96: =SUM(G87:G95) -> 3936140.5 | H96: =SUM(H87:H95) -> 3936140.5 | I96: =SUM(I87:I95) -> 3936140.5 | ... N96: =SUM(N87:N95) -> 49174780
A97: Finance Cost
A98: Cogebanque loan Interest | B98: =N98/12 -> 6131602.8 | C98: 6131602.8 | D98: 6131602.8 | E98: 6131602.8 | F98: 6131602.8 | G98: 6131602.8 | H98: 6131602.8 | I98: 6131602.8 | J98: 6131602.8 | K98: 6131602.8 | L98: 6131602.8 | M98: 6131602.8 | N98: 73579234
A99: Missio Invest Interest | B99: =N99/12 -> 6663195 | C99: 6663195 | D99: 6663195 | E99: 6663195 | F99: 6663195 | G99: 6663195 | H99: 6663195 | I99: 6663195 | J99: 6663195 | K99: 6663195 | L99: 6663195 | M99: 6663195 | N99: 79958340
A100: Total finance cost | B100: =B98+B99 -> 12794798 | C100: =C98+C99 -> 12794798 | D100: =D98+D99 -> 12794798 | E100: =E98+E99 -> 12794798 | F100: =F98+F99 -> 12794798 | G100: =G98+G99 -> 12794798 | H100: =H98+H99 -> 12794798 | I100: =I98+I99 -> 12794798 | ... N100: =N98+N99 -> 153537574
A101: TOTAL OPERATING EXPENSES(B) | B101: =B100+B96+B85+B76+B49 -> 1.1265873e+08 | C101: =C100+C96+C85+C76+C49 -> 1.125754e+08 | D101: =D100+D96+D85+D76+D49 -> 1.1319153e+08 | E101: =E100+E96+E85+E76+E49 -> 1.1319153e+08 | F101: =F100+F96+F85+F76+F49 -> 1.1319153e+08 | G101: =G100+G96+G85+G76+G49 -> 1.1319153e+08 | H101: =H100+H96+H85+H76+H49 -> 1.1319153e+08 | I101: =I100+I96+I85+I76+I49 -> 1.1319153e+08 | ... N101: =N100+N96+N85+N76+N49 -> 1.3798147e+09
A102: SURPLUS /DEFICIT FOR PERIOD(A-B) | B102: =B41-B101 -> 32145748 | C102: =C41-C101 -> 47349165 | D102: =D41-D101 -> 46733037 | E102: =E41-E101 -> 46733037 | F102: =F41-F101 -> 65240999 | G102: =G41-G101 -> 65240999 | H102: =H41-H101 -> 65240999 | I102: =I41-I101 -> 65240999 | ... N102: =N41-N101 -> 5.9878576e+08
A103: CASH FLOW
A104: CAPITAL EXPENDITURE
A105: Other Equipment | B105: =N105/12 -> 833333.33 | C105: 833333.33 | D105: 833333.33 | E105: 833333.33 | F105: 833333.33 | G105: 833333.33 | H105: 833333.33 | I105: 833333.33 | J105: 833333.33 | K105: 833333.33 | L105: 833333.33 | M105: 833333.33 | N105: 10000000
A106: Purchase of Additional books (Education and Nursing&Midwifrey) | B106: =N106/12 -> 1666666.7 | C106: 1666666.7 | D106: 1666666.7 | E106: 1666666.7 | F106: 1666666.7 | G106: 1666666.7 | H106: 1666666.7 | I106: 1666666.7 | J106: 1666666.7 | K106: 1666666.7 | L106: 1666666.7 | M106: 1666666.7 | N106: 20000000
A107: Purchase Remaining Equipment for New laboratories and renovation of existing Laboratory | B107: 33719661 | C107: 33719661 | D107: 33719661 | E107: 33719661 | N107: =SUM(B107:M107) -> 134878643
A108: Building & Rehabilitation | B108: =N108/12 -> 4166666.7 | C108: 4166666.7 | D108: 4166666.7 | E108: 4166666.7 | F108: 4166666.7 | G108: 4166666.7 | H108: 4166666.7 | I108: 4166666.7 | J108: 4166666.7 | K108: 4166666.7 | L108: 4166666.7 | M108: 4166666.7 | N108: 50000000
...

Sheet Execution of the budget
A1: BUDGET EXECUTION FOR ACADEMIC YEAR 2024-2025
N3: Number of students | O3: % Increase
A4: Number of student at start of 2024-2025 | N4: 2492
A5: Number of student at end of 2024-2025 | N5: 3442
A6: Increase in number of student at year end | B6: Financial Budget for Academic year 2024-2025 | N6: =N5-N4 -> 950 | O6: =N6/N4 -> 0.3812199
A8: PARTICULARS | B8: September | C8: October | D8: November | E8: December | F8: January | G8: February | H8: March | I8: April | J8: May | K8: June | L8: July | M8: August | N8: BUDGET 2024-2025 | O8: BUDGET EXECUTION 2024-2025 | P8: Variance | Q8: % of realisation
B9: TOTAL | C9: TOTAL | D9: TOTAL | E9: TOTAL | F9: TOTAL | G9: TOTAL | H9: TOTAL | I9: TOTAL | J9: TOTAL | K9: TOTAL | L9: TOTAL | M9: TOTAL | N9: TOTAL | O9: TOTAL
A10: Budgeted Number of Students | N10: ='INCOME DETAILS'!Q121 -> 3997 | O10: 3442 | P10: =O10-N10 -> -555 | Q10: =O10/N10 -> 0.86114586
A11: Revenue
A12: Tuition Fees
A13: Faculty of Catechesis and Religious Sciences | B13: =N13/12 -> 6041666.7 | C13: 6041666.7 | D13: 6041666.7 | E13: 6041666.7 | F13: 6041666.7 | G13: 6041666.7 | H13: 6041666.7 | I13: 6041666.7 | J13: 6041666.7 | K13: 6041666.7 | L13: 6041666.7 | M13: 6041666.7 | N13: ='INCOME DETAILS'!AB104 -> 72500000
A14: Faculty of Commerce | B14: =N14/12 -> 10250000 | C14: 12437500 | D14: 12437500 | E14: 12437500 | F14: 12437500 | G14: 12437500 | H14: 12437500 | I14: 12437500 | J14: 12437500 | K14: 12437500 | L14: 12437500 | M14: 12437500 | N14: ='INCOME DETAILS'!AB112 -> 123000000
A15: Faculty of Education -under graduates | B15: =N15/12 -> 41477500 | C15: 45802500 | D15: 45802500 | E15: 45802500 | F15: 45802500 | G15: 45802500 | H15: 45802500 | I15: 45802500 | J15: 45802500 | K15: 45802500 | L15: 45802500 | M15: 45802500 | N15: ='INCOME DETAILS'!AB62 -> 497730000
A16: Faculty of Education -PGD- Taba campus-Kibungo Learning Center | B16: =N16/12 -> 5160750 | C16: 7155750 | D16: 7155750 | E16: 7155750 | F16: 7155750 | G16: 7155750 | H16: 7155750 | I16: 7155750 | J16: 7155750 | K16: 7155750 | L16: 7155750 | M16: 7155750 | N16: ='INCOME DETAILS'!AB117 -> 61929000
A17: Faculty of Public Health and Human Nutrition | B17: =N17/12 -> 3428333.3 | C17: 9997083.3 | D17: 9997083.3 | E17: 9997083.3 | F17: 9997083.3 | G17: 9997083.3 | H17: 9997083.3 | I17: 9997083.3 | J17: 9997083.3 | K17: 9997083.3 | L17: 9997083.3 | M17: 9997083.3 | N17: ='INCOME DETAILS'!AB96 -> 41140000
A18: Faculty of Science and Technology | B18: =N18/12 -> 10931250 | C18: 12264583 | D18: 12264583 | E18: 12264583 | F18: 12264583 | G18: 12264583 | H18: 12264583 | I18: 12264583 | J18: 12264583 | K18: 12264583 | L18: 12264583 | M18: 12264583 | N18: ='INCOME DETAILS'!AB28 -> 131175000
A19: Faculty of Social Work | B19: =N19/12 -> 2770833.3 | C19: 2770833.3 | D19: 2770833.3 | E19: 2770833.3 | F19: 2770833.3 | G19: 2770833.3 | H19: 2770833.3 | I19: 2770833.3 | J19: 2770833.3 | K19: 2770833.3 | L19: 2770833.3 | M19: 2770833.3 | N19: ='INCOME DETAILS'!AB36 -> 33250000
A20: Expected New Masters Program fees | K20: =N20/3 -> 0 | L20: 0 | M20: 0 | N20: ='INCOME DETAILS'!AB120 -> 0
A21: Ministry of health sponsored student
A22: Existing Sponsored | B22: =N22/12 -> 23065417 | C22: 23065417 | D22: 23065417 | E22: 23065417 | F22: 23065417 | G22: 23065417 | H22: 23065417 | I22: 23065417 | J22: 23065417 | K22: 23065417 | L22: 23065417 | M22: 23065417 | N22: 276785000
A23: Projected Sponsored | K23: =N23/3 -> 24625000 | L23: 24625000 | M23: 24625000 | N23: ='INCOME DETAILS'!S124 -> 73875000
A24: Chancen Student Tuition fees | B24: =N24/12 -> 32324778 | C24: 32324778 | D24: 32324778 | E24: 32324778 | F24: 32324778 | G24: 32324778 | H24: 32324778 | I24: 32324778 | J24: 32324778 | K24: 32324778 | L24: 32324778 | M24: 32324778 | N24: ='INCOME DETAILS'!F133 -> 3.8789733e+08
A25: YWCA | F25: =N25/9 -> 6007962.2 | G25: 6007962.2 | H25: 6007962.2 | I25: 6007962.2 | J25: 6007962.2 | K25: 6007962.2 | L25: 6007962.2 | M25: 6007962.2 | N25: ='INCOME DETAILS'!E140 -> 54071660
A26: Income fromTuition fees | B26: =SUM(B13:B25) -> 1.3545053e+08 | C26: =SUM(C13:C25) -> 1.5186011e+08 | D26: =SUM(D13:D25) -> 1.5186011e+08 | E26: =SUM(E13:E25) -> 1.5186011e+08 | F26: =SUM(F13:F25) -> 1.5786807e+08 | G26: =SUM(G13:G25) -> 1.5786807e+08 | H26: =SUM(H13:H25) -> 1.5786807e+08 | I26: =SUM(I13:I25) -> 1.5786807e+08 | ... N26: =SUM(N13:N25) -> 1.753353e+09 | O26: 1088767000 | P26: =O26-N26 -> -6.6458599e+08 | Q26: =O26/N26 -> 0.62096281
A27: Application fees | B27: =N27/12 -> 703333.33 | C27: 930416.67 | D27: 930416.67 | E27: 930416.67 | F27: 930416.67 | G27: 930416.67 | H27: 930416.67 | I27: 930416.67 | J27: 930416.67 | K27: 930416.67 | L27: 930416.67 | M27: 930416.67 | N27: ='INCOME DETAILS'!AD121 -> 8440000 | O27: 9970000 | P27: =O27-N27 -> 1530000 | Q27: =O27/N27 -> 1.1812796
A28: Internship fees | B28: =N28/12 -> 3187500 | C28: 2870833.3 | D28: 2870833.3 | E28: 2870833.3 | F28: 2870833.3 | G28: 2870833.3 | H28: 2870833.3 | I28: 2870833.3 | J28: 2870833.3 | K28: 2870833.3 | L28: 2870833.3 | M28: 2870833.3 | N28: ='INCOME DETAILS'!AE121 -> 38250000 | O28: 33980000 | P28: =O28-N28 -> -4270000 | Q28: =O28/N28 -> 0.88836601
A29: Research supervision fees | B29: =N29/12 -> 3837500 | C29: 3837500 | D29: 3837500 | E29: 3837500 | F29: 3837500 | G29: 3837500 | H29: 3837500 | I29: 3837500 | J29: 3837500 | K29: 3837500 | L29: 3837500 | M29: 3837500 | N29: ='INCOME DETAILS'!AF121 -> 46050000 | O29: 63450000 | P29: =O29-N29 -> 17400000 | Q29: =O29/N29 -> 1.3778502
A30: Graduation fees | J30: =N30 -> 13000000 | N30: =260*50000 -> 13000000 | O30: 12730000 | P30: =O30-N30 -> -270000 | Q30: =O30/N30 -> 0.97923077
A31: Fines | B31: =N31/12 -> 50820 | C31: 50820 | D31: 50820 | E31: 50820 | F31: 50820 | G31: 50820 | H31: 50820 | I31: 50820 | J31: 50820 | K31: 50820 | L31: 50820 | M31: 50820 | N31: 609840 | O31: 0 | P31: =O31-N31 -> -609840 | Q31: =O31/N31 -> 0
A32: Retake fees | B32: =N32/12 -> 33333.333 | C32: 33333.333 | D32: 33333.333 | E32: 33333.333 | F32: 33333.333 | G32: 33333.333 | H32: 33333.333 | I32: 33333.333 | J32: 33333.333 | K32: 33333.333 | L32: 33333.333 | M32: 33333.333 | N32: 400000 | O32: 0 | P32: =O32-N32 -> -400000 | Q32: =O32/N32 -> 0
A33: Academic documents fees | B33: =N33/12 -> 232466.67 | C33: 232466.67 | D33: 232466.67 | E33: 232466.67 | F33: 232466.67 | G33: 232466.67 | H33: 232466.67 | I33: 232466.67 | J33: 232466.67 | K33: 232466.67 | L33: 232466.67 | M33: 232466.67 | N33: 2789600 | O33: 1905000 | P33: =O33-N33 -> -884600 | Q33: =O33/N33 -> 0.6828936
A34: Total academic cost | B34: =SUM(B26:B33) -> 1.4349548e+08 | C34: =SUM(C26:C33) -> 1.5981548e+08 | D34: =SUM(D26:D33) -> 1.5981548e+08 | E34: =SUM(E26:E33) -> 1.5981548e+08 | F34: =SUM(F26:F33) -> 1.6582344e+08 | G34: =SUM(G26:G33) -> 1.6582344e+08 | H34: =SUM(H26:H33) -> 1.6582344e+08 | I34: =SUM(I26:I33) -> 1.6582344e+08 | ... O34: =SUM(O26:O33) -> 1210802000 | Q34: =O34/N34 -> 0.64995809
A35: Other Income
A36: Accomodation fee | B36: =N36/12 -> 1309000 | C36: 109083.33 | D36: 109083.33 | E36: 109083.33 | F36: 109083.33 | G36: 109083.33 | H36: 109083.33 | I36: 109083.33 | J36: 109083.33 | K36: 109083.33 | L36: 109083.33 | M36: 109083.33 | N36: =187*7000*12 -> 15708000 | O36: 7345500 | P36: =O36-N36 -> -8362500 | Q36: =O36/N36 -> 0.46762796
A37: Other Income(Different IURA Projects) | F37: =N37/8 -> 12500000 | G37: 12500000 | H37: 12500000 | I37: 12500000 | J37: 12500000 | K37: 12500000 | L37: 12500000 | M37: 12500000 | N37: 100000000 | O37: 1.4241223e+08 | P37: =O37-N37 -> 42412233 | Q37: =O37/N37 -> 1.4241223
A38: Total Other Income | B38: =B36+B37 -> 1309000 | C38: =C36+C37 -> 109083.33 | D38: =D36+D37 -> 109083.33 | E38: =E36+E37 -> 109083.33 | F38: =F36+F37 -> 12609083 | G38: =G36+G37 -> 12609083 | H38: =H36+H37 -> 12609083 | I38: =I36+I37 -> 12609083 | ... O38: =O36+O37 -> 1.4975773e+08 | P38: =N38-O38 -> -34049733 | Q38: =O38/N38 -> 1.2942729
A39: TOTAL REVENUE(A) | B39: =B38+B34 -> 1.4480448e+08 | C39: =C38+C34 -> 1.5992456e+08 | D39: =D38+D34 -> 1.5992456e+08 | E39: =E38+E34 -> 1.5992456e+08 | F39: =F38+F34 -> 1.7843253e+08 | G39: =G38+G34 -> 1.7843253e+08 | H39: =H38+H34 -> 1.7843253e+08 | I39: =I38+I34 -> 1.7843253e+08 | ... O39: =O38+O34 -> 1.3605597e+09 | P39: =N39-O39 -> 6.180407e+08 | Q39: =O39/N39 -> 0.68763744
A40: OPERATING EXPENSES
A41: Staff Cost
A42: Full timeTeaching staff | B42: 32407582 | C42: 32407582 | D42: 32407582 | E42: 32407582 | F42: 32407582 | G42: 32407582 | H42: 32407582 | I42: 32407582 | J42: 32407582 | K42: 36319385 | L42: 36319385 | M42: 36319385 | N42: =SUM(B42:M42) -> 4.0062639e+08 | O42: 3.785134e+08 | P42: =O42-N42 -> -22112990 | Q42: =O42/N42 -> 0.94480396
A43: Part time teaching staff | B43: ='Part-time staff cost'!B13/12 -> 8044756.4 | C43: =B43 -> 8044756.4 | D43: =C43 -> 8044756.4 | E43: =D43 -> 8044756.4 | F43: =E43 -> 8044756.4 | G43: =F43 -> 8044756.4 | H43: =G43 -> 8044756.4 | I43: =H43 -> 8044756.4 | J43: =I43 -> 8044756.4 | ... M43: =L43 -> 8044756.4 | N43: =SUM(B43:M43) -> 96537077 | O43: 93960978 | P43: =O43-N43 -> -2576098.5 | Q43: =O43/N43 -> 0.97331493
A44: Administrative + Support staff | B44: 14887169 | C44: 14887169 | D44: 14887169 | E44: 14887169 | F44: 14887169 | G44: 14887169 | H44: 14887169 | I44: 14887169 | J44: 14887169 | K44: 17500450 | L44: 17500450 | M44: 17500450 | N44: =SUM(B44:M44) -> 1.8648587e+08 | O44: 1.7387885e+08 | P44: =O44-N44 -> -12607025 | Q44: =O44/N44 -> 0.93239689
A45: Other payment(Consultancy fees) | B45: 2851511.5 | C45: 2851511.5 | D45: 2851511.5 | E45: 2851511.5 | F45: 2851511.5 | G45: 2851511.5 | H45: 2851511.5 | I45: 2851511.5 | J45: 2851511.5 | K45: 2851511.5 | L45: 2851511.5 | M45: 2851511.5 | N45: =SUM(B45:M45) -> 34218138 | O45: 33305024 | P45: =O45-N45 -> -913113.34 | Q45: =O45/N45 -> 0.97331493
A46: CPA staff | B46: 1200000 | C46: 1200000 | D46: 1200000 | E46: 1200000 | F46: 1200000 | G46: 1200000 | H46: 1200000 | I46: 1200000 | J46: 1200000 | K46: 1200000 | L46: 1200000 | M46: 1200000 | N46: =SUM(B46:M46) -> 14400000 | O46: 14015735 | P46: =O46-N46 -> -384264.98 | Q46: =O46/N46 -> 0.97331493
A47: Total Staff Cost | B47: =SUM(B42:B46) -> 59391019 | C47: =SUM(C42:C46) -> 59391019 | D47: =SUM(D42:D46) -> 59391019 | E47: =SUM(E42:E46) -> 59391019 | F47: =SUM(F42:F46) -> 59391019 | G47: =SUM(G42:G46) -> 59391019 | H47: =SUM(H42:H46) -> 59391019 | I47: =SUM(I42:I46) -> 59391019 | ... N47: =SUM(N42:N46) -> 7.3226748e+08 | O47: 693673989 | P47: =N47-O47 -> 38593492 | Q47: =O47/N47 -> 0.94729591
A48: Administrative Cost
A49: Communication | B49: 210000 | C49: 210000 | D49: 210000 | E49: 210000 | F49: 210000 | G49: 210000 | H49: 210000 | I49: 210000 | J49: 210000 | K49: 210000 | L49: 210000 | M49: 210000 | N49: =SUM(B49:M49) -> 2520000 | O49: 2656500 | P49: =N49-O49 -> -136500 | Q49: =O49/N49 -> 1.0541667
A50: Hygiene and Sanitation | N50: =O50 -> 15791800 | O50: 15791800 | P50: =N50-O50 -> 0 | Q50: =O50/N50 -> 1
A51: Security | B51: =720000+55000 -> 775000 | C51: =720000+55000 -> 775000 | D51: =720000+55000 -> 775000 | E51: =720000+55000 -> 775000 | F51: =720000+55000 -> 775000 | G51: =720000+55000 -> 775000 | H51: =720000+55000 -> 775000 | I51: =720000+55000 -> 775000 | ... M51: =720000+55000 -> 775000 | N51: =SUM(B51:M51) -> 9300000 | O51: 8327000 | P51: =N51-O51 -> 973000 | Q51: =O51/N51 -> 0.89537634
A52: Water & Electricity | B52: 1342035 | C52: 1342035 | D52: 1342035 | E52: 1342035 | F52: 1342035 | G52: 1342035 | H52: 1342035 | I52: 1342035 | J52: 1342035 | K52: 1342035 | L52: 1342035 | M52: 1342035 | N52: =SUM(B52:M52) -> 16104420 | O52: 25442145 | P52: =N52-O52 -> -9337725 | Q52: =O52/N52 -> 1.5798237
A53: Medical insurance | B53: =N53/12 -> 1280603.4 | C53: 1280603.4 | D53: 1280603.4 | E53: 1280603.4 | F53: 1280603.4 | G53: 1280603.4 | H53: 1280603.4 | I53: 1280603.4 | J53: 1280603.4 | K53: 1280603.4 | L53: 1280603.4 | M53: 1280603.4 | N53: =(12234658+571376)*120% -> 15367241 | O53: 10367241 | P53: =N53-O53 -> 5000000 | Q53: =O53/N53 -> 0.67463255
A54: Rent ISR | B54: 800000 | C54: 800000 | D54: 800000 | E54: 800000 | F54: 800000 | G54: 800000 | H54: 800000 | I54: 800000 | J54: 800000 | K54: 800000 | L54: 800000 | M54: 800000 | N54: =SUM(B54:M54) -> 9600000 | O54: =N54 -> 9600000 | P54: =N54-O54 -> 0 | Q54: =O54/N54 -> 1
A55: Carburant/fuel | B55: 2020000 | C55: 2020000 | D55: 2020000 | E55: 2020000 | F55: 2020000 | G55: 2020000 | H55: 2020000 | I55: 2020000 | J55: 2020000 | K55: 2020000 | L55: 2020000 | M55: 2020000 | N55: =SUM(B55:M55) -> 24240000 | O55: 14620000 | P55: =N55-O55 -> 9620000 | Q55: =O55/N55 -> 0.60313531
A56: Supplies & office materials | B56: 3999855 | C56: 3999855 | D56: 3999855 | E56: 3999855 | F56: 3999855 | G56: 3999855 | H56: 3999855 | I56: 3999855 | J56: 3999855 | K56: 3999855 | L56: 3999855 | M56: 3999855 | N56: =SUM(B56:M56) -> 47998260 | O56: 25843708 | P56: =N56-O56 -> 22154552 | Q56: =O56/N56 -> 0.5384301
A57: Bank Charges | B57: =N57/12 -> 99705.6 | C57: 99705.6 | D57: 99705.6 | E57: 99705.6 | F57: 99705.6 | G57: 99705.6 | H57: 99705.6 | I57: 99705.6 | J57: 99705.6 | K57: 99705.6 | L57: 99705.6 | M57: 99705.6 | N57: =997056*120% -> 1196467.2 | O57: 755381 | P57: =N57-O57 -> 441086.2 | Q57: =O57/N57 -> 0.63134284
A58: Postal Charge | B58: =N58/12 -> 14640 | C58: 14640 | D58: 14640 | E58: 14640 | F58: 14640 | G58: 14640 | H58: 14640 | I58: 14640 | J58: 14640 | K58: 14640 | L58: 14640 | M58: 14640 | N58: =146400*120% -> 175680 | O58: =N58 -> 175680 | P58: =N58-O58 -> 0 | Q58: =O58/N58 -> 1
A59: Interneship Supervision fees | B59: 3294272.8 | C59: 3294272.8 | D59: 3294272.8 | E59: 3294272.8 | F59: 3294272.8 | G59: 3294272.8 | H59: 3294272.8 | I59: 3294272.8 | J59: 3294272.8 | K59: 3294272.8 | L59: 3294272.8 | M59: 3294272.8 | N59: 39531274 | O59: 27024847 | P59: =N59-O59 -> 12506427 | Q59: =O59/N59 -> 0.68363208
A60: Maintenainance and repair | B60: 1172273.3 | C60: 1172273.3 | D60: 1172273.3 | E60: 1172273.3 | F60: 1172273.3 | G60: 1172273.3 | H60: 1172273.3 | I60: 1172273.3 | J60: 1172273.3 | K60: 1172273.3 | L60: 1172273.3 | M60: 1172273.3 | N60: =SUM(B60:M60) -> 14067279 | O60: 13218820 | P60: =N60-O60 -> 848459.1 | Q60: =O60/N60 -> 0.93968563
A61: Marketing and Publicity | B61: =500000+400000+50000 -> 950000 | C61: =500000+400000+50000 -> 950000 | D61: =500000+400000+50000 -> 950000 | E61: =500000+400000+50000 -> 950000 | F61: =500000+400000+50000 -> 950000 | G61: =500000+400000+50000 -> 950000 | H61: =500000+400000+50000 -> 950000 | I61: =500000+400000+50000 -> 950000 | ... M61: =500000+400000+50000 -> 950000 | N61: =SUM(B61:M61) -> 11400000 | O61: 5803000 | P61: =N61-O61 -> 5597000 | Q61: =O61/N61 -> 0.50903509
A62: Marketing Agents Expenses fee | B62: 1038333.3 | C62: 1038333.3 | D62: 1038333.3 | E62: 1038333.3 | F62: 1038333.3 | G62: 1038333.3 | H62: 1038333.3 | I62: 1038333.3 | J62: 1038333.3 | K62: 1038333.3 | L62: 1038333.3 | M62: 1038333.3 | N62: ='INCOME DETAILS'!X124 -> 12460000 | O62: 6460000 | P62: =N62-O62 -> 6000000 | Q62: =O62/N62 -> 0.51845907
A63: Graduation expenses | B63: =N63/12 -> 833333.33 | C63: 833333.33 | D63: 833333.33 | E63: 833333.33 | F63: 833333.33 | G63: 833333.33 | H63: 833333.33 | I63: 833333.33 | J63: 833333.33 | K63: 833333.33 | L63: 833333.33 | M63: 833333.33 | N63: 10000000 | O63: 9000000 | P63: =N63-O63 -> 1000000 | Q63: =O63/N63 -> 0.9
A64: Vehicle Insurance | B64: =N64/12 -> 229814.67 | C64: 229814.67 | D64: 229814.67 | E64: 229814.67 | F64: 229814.67 | G64: 229814.67 | H64: 229814.67 | I64: 229814.67 | J64: 229814.67 | K64: 229814.67 | L64: 229814.67 | M64: 229814.67 | N64: 2757776 | O64: =N64 -> 2757776 | P64: =N64-O64 -> 0 | Q64: =O64/N64 -> 1
A65: Building Insurance | B65: =N65/12 -> 195082.08 | C65: 195082.08 | D65: 195082.08 | E65: 195082.08 | F65: 195082.08 | G65: 195082.08 | H65: 195082.08 | I65: 195082.08 | J65: 195082.08 | K65: 195082.08 | L65: 195082.08 | M65: 195082.08 | N65: 2340985 | O65: 1148195 | P65: =N65-O65 -> 1192790 | Q65: =O65/N65 -> 0.49047516
A66: Employees Capacity Building | B66: =N66/12 -> 333333.33 | C66: 333333.33 | D66: 333333.33 | E66: 333333.33 | F66: 333333.33 | G66: 333333.33 | H66: 333333.33 | I66: 333333.33 | J66: 333333.33 | K66: 333333.33 | L66: 333333.33 | M66: 333333.33 | N66: 4000000 | O66: 1000000 | P66: =N66-O66 -> 3000000 | Q66: =O66/N66 -> 0.25
A67: Accueil et reception | B67: =N67/12 -> 410922.75 | C67: 410922.75 | D67: 410922.75 | E67: 410922.75 | F67: 410922.75 | G67: 410922.75 | H67: 410922.75 | I67: 410922.75 | J67: 410922.75 | K67: 410922.75 | L67: 410922.75 | M67: 410922.75 | N67: 4931073 | O67: 9533200 | P67: =N67-O67 -> -4602127 | Q67: =O67/N67 -> 1.9332912
A68: Mission Fees | B68: =N68/12 -> 486777.08 | C68: 486777.08 | D68: 486777.08 | E68: 486777.08 | F68: 486777.08 | G68: 486777.08 | H68: 486777.08 | I68: 486777.08 | J68: 486777.08 | K68: 486777.08 | L68: 486777.08 | M68: 486777.08 | N68: 5841325 | O68: =13936530 -> 13936530 | P68: =N68-O68 -> -8095205 | Q68: =O68/N68 -> 2.3858508
A69: Contribution in other Organism | B69: =N69/12 -> 250000 | C69: 250000 | D69: 250000 | E69: 250000 | F69: 250000 | G69: 250000 | H69: 250000 | I69: 250000 | J69: 250000 | K69: 250000 | L69: 250000 | M69: 250000 | N69: 3000000 | O69: 0 | P69: =N69-O69 -> 3000000 | Q69: =O69/N69 -> 0
A70: External Audit fee | B70: =N70/12 -> 250000 | C70: 250000 | D70: 250000 | E70: 250000 | F70: 250000 | G70: 250000 | H70: 250000 | I70: 250000 | J70: 250000 | K70: 250000 | L70: 250000 | M70: 250000 | N70: 3000000 | O70: =N70 -> 3000000 | P70: =N70-O70 -> 0 | Q70: =O70/N70 -> 1
A71: Public Relation | B71: =N71/12 -> 416666.67 | C71: 416666.67 | D71: 416666.67 | E71: 416666.67 | F71: 416666.67 | G71: 416666.67 | H71: 416666.67 | I71: 416666.67 | J71: 416666.67 | K71: 416666.67 | L71: 416666.67 | M71: 416666.67 | N71: 5000000 | O71: 4968500 | P71: =N71-O71 -> 31500 | Q71: =O71/N71 -> 0.9937
A72: Kibungo L.Center rental cost. | B72: 400000 | C72: 400000 | D72: 400000 | E72: 400000 | F72: 400000 | G72: 400000 | H72: 400000 | I72: 400000 | J72: 400000 | K72: 400000 | L72: 400000 | M72: 400000 | N72: =SUM(B72:M72) -> 4800000 | O72: =N72 -> 4800000 | P72: =N72-O72 -> 0 | Q72: =O72/N72 -> 1
A73: Partnership fees | B73: 3024380 | C73: 3024380 | D73: 3024380 | E73: 3024380 | F73: 3024380 | G73: 3024380 | H73: 3024380 | I73: 3024380 | J73: 3024380 | K73: 3024380 | L73: 3024380 | M73: 3024380 | N73: =SUM(B73:M73) -> 36292560 | O73: 36292560 | P73: =N73-O73 -> 0 | Q73: =O73/N73 -> 1
A74: Unforseen expenses | B74: 5000000 | C74: 5000000 | D74: 5000000 | E74: 5000000 | F74: 5000000 | G74: 5000000 | H74: 5000000 | I74: 5000000 | J74: 5000000 | K74: 5000000 | L74: 5000000 | M74: 5000000 | N74: =SUM(B74:M74) -> 60000000 | O74: 38666806 | P74: =N74-O74 -> 21333194 | Q74: =O74/N74 -> 0.64444677
A75: Total Admnistrative Cost | B75: =SUM(B49:B74) -> 28827028 | C75: =SUM(C49:C74) -> 28827028 | D75: =SUM(D49:D74) -> 28827028 | E75: =SUM(E49:E74) -> 28827028 | F75: =SUM(F49:F74) -> 28827028 | G75: =SUM(G49:G74) -> 28827028 | H75: =SUM(H49:H74) -> 28827028 | I75: =SUM(I49:I74) -> 28827028 | ... P75: =SUM(P49:P74) -> 70526451 | Q75: =O75/N75 -> 0.80502266
A76: Academic cost
A77: Research | B77: 1250000 | C77: 1250000 | D77: 1250000 | E77: 1250000 | F77: 1250000 | G77: 1250000 | H77: 1250000 | I77: 1250000 | J77: 1250000 | K77: 1250000 | L77: 1250000 | M77: 1250000 | N77: 15000000 | O77: =12732204+1030000 -> 13762204 | P77: =N77-O77 -> 1237796 | Q77: =O77/N77 -> 0.91748027
A78: Seminars and conferences | B78: 170000 | C78: 170000 | D78: 170000 | E78: 170000 | F78: 170000 | G78: 170000 | H78: 170000 | I78: 170000 | J78: 170000 | K78: 170000 | L78: 170000 | M78: 170000 | N78: =SUM(B78:M78) -> 2040000 | O78: =N78 -> 2040000 | P78: =N78-O78 -> 0 | Q78: =O78/N78 -> 1
A79: Laboratory Consumables | B79: 1080208.3 | C79: 1080208.3 | D79: 1080208.3 | E79: 1080208.3 | F79: 1080208.3 | G79: 1080208.3 | H79: 1080208.3 | I79: 1080208.3 | J79: 1080208.3 | K79: 1080208.3 | L79: 1080208.3 | M79: 1080208.3 | N79: 12962500 | O79: 17371600 | P79: =N79-O79 -> -4409100 | Q79: =O79/N79 -> 1.3401427
A80: Designing and launching new programs | B80: 1084000 | C80: 1084000 | D80: 1084000 | E80: 1084000 | F80: 1084000 | G80: 1084000 | H80: 1084000 | I80: 1084000 | J80: 1084000 | K80: 1084000 | L80: 1084000 | M80: 1084000 | N80: =SUM(B80:M80) -> 13008000 | O80: 16432170 | P80: =N80-O80 -> -3424170 | Q80: =O80/N80 -> 1.2632357
A81: Other academic activities (field visit,community services..) | B81: 300000 | C81: 300000 | D81: 300000 | E81: 300000 | F81: 300000 | G81: 300000 | H81: 300000 | I81: 300000 | J81: 300000 | K81: 300000 | L81: 300000 | M81: 300000 | N81: =SUM(B81:M81) -> 3600000 | O81: 5058925 | P81: =N81-O81 -> -1458925 | Q81: =O81/N81 -> 1.4052569
A82: Responsability allowance | B82: 3600000 | C82: 3600000 | D82: 3600000 | E82: 3600000 | F82: 3600000 | G82: 3600000 | H82: 3600000 | I82: 3600000 | J82: 3600000 | K82: 3600000 | L82: 3600000 | M82: 3600000 | N82: =SUM(B82:M82) -> 43200000 | O82: =12000000 -> 12000000 | P82: =N82-O82 -> 31200000 | Q82: =O82/N82 -> 0.27777778
A83: Panel fees | B83: =N83/12 -> 758333.33 | C83: 758333.33 | D83: 758333.33 | E83: 758333.33 | F83: 758333.33 | G83: 758333.33 | H83: 758333.33 | I83: 758333.33 | J83: 758333.33 | K83: 758333.33 | L83: 758333.33 | M83: 758333.33 | N83: 9100000 | O83: 0 | P83: =N83-O83 -> 9100000 | Q83: =O83/N83 -> 0
A84: Total Academic Cost | B84: =SUM(B77:B83) -> 8242541.7 | C84: =SUM(C77:C83) -> 8242541.7 | D84: =SUM(D77:D83) -> 8242541.7 | E84: =SUM(E77:E83) -> 8242541.7 | F84: =SUM(F77:F83) -> 8242541.7 | G84: =SUM(G77:G83) -> 8242541.7 | H84: =SUM(H77:H83) -> 8242541.7 | I84: =SUM(I77:I83) -> 8242541.7 | ... P84: =SUM(P77:P83) -> 32245601 | Q84: =O84/N84 -> 0.67399213
A85: ICT COST
A86: Subscription to anti plagiarism software | B86: =N86/12 -> 73333.333 | C86: 73333.333 | D86: 73333.333 | E86: 73333.333 | F86: 73333.333 | G86: 73333.333 | H86: 73333.333 | I86: 73333.333 | J86: 73333.333 | K86: 73333.333 | L86: 73333.333 | M86: 73333.333 | N86: 880000 | O86: 0 | P86: =N86-O86 -> 880000 | Q86: =O86/N86 -> 0
A87: Kaspesky (Antivirus ) | B87: =N87/12 -> 125000 | C87: 125000 | D87: 125000 | E87: 125000 | F87: 125000 | G87: 125000 | H87: 125000 | I87: 125000 | J87: 125000 | K87: 125000 | L87: 125000 | M87: 125000 | N87: 1500000 | O87: 1000000 | P87: =N87-O87 -> 500000 | Q87: =O87/N87 -> 0.66666667
A88: Maintenance of IT equipment | B88: 431112.5 | C88: 431112.5 | D88: 431112.5 | E88: 431112.5 | F88: 431112.5 | G88: 431112.5 | H88: 431112.5 | I88: 431112.5 | J88: 431112.5 | K88: 431112.5 | L88: 431112.5 | M88: 431112.5 | N88: 5173350 | O88: 5563400 | P88: =N88-O88 -> -390050 | Q88: =O88/N88 -> 1.075396
A89: Website hosting+Elearning platform hosting + MIS Hosting | B89: 250000 | C89: 250000 | D89: 250000 | E89: 250000 | F89: 250000 | G89: 250000 | H89: 250000 | I89: 250000 | J89: 250000 | K89: 250000 | L89: 250000 | M89: 250000 | N89: 5173350 | O89: =N89 -> 5173350 | P89: =N89-O89 -> 0 | Q89: =O89/N89 -> 1
A90: School gear fees | B90: 666166.67 | C90: 666166.67 | D90: 666166.67 | E90: 666166.67 | F90: 666166.67 | G90: 666166.67 | H90: 666166.67 | I90: 666166.67 | J90: 666166.67 | K90: 666166.67 | L90: 666166.67 | M90: 666166.67 | N90: =N10*2000 -> 7994000 | O90: 5994000 | P90: =N90-O90 -> 2000000 | Q90: =O90/N90 -> 0.74981236
A91: Supplying softwares(library& registry) | B91: =N91/12 -> 166666.67 | C91: 166666.67 | D91: 166666.67 | E91: 166666.67 | F91: 166666.67 | G91: 166666.67 | H91: 166666.67 | I91: 166666.67 | J91: 166666.67 | K91: 166666.67 | L91: 166666.67 | M91: 166666.67 | N91: 2000000 | O91: 0 | P91: =N91-O91 -> 2000000 | Q91: =O91/N91 -> 0
A92: Subsription to online meeting software like webex, Ms team, Zoom | B92: =N92/12 -> 166666.67 | C92: 83333.333 | D92: 83333.333 | E92: 83333.333 | F92: 83333.333 | G92: 83333.333 | H92: 83333.333 | I92: 83333.333 | J92: 83333.333 | K92: 83333.333 | L92: 83333.333 | M92: 83333.333 | N92: 2000000 | O92: 1000000 | P92: =N92-O92 -> 1000000 | Q92: =O92/N92 -> 0.5
A93: Configuration of CUR Server room | B93: =N93/12 -> 250000 | C93: 250000 | D93: 250000 | E93: 250000 | F93: 250000 | G93: 250000 | H93: 250000 | I93: 250000 | J93: 250000 | K93: 250000 | L93: 250000 | M93: 250000 | N93: 3000000 | O93: 0 | P93: =N93-O93 -> 3000000 | Q93: =O93/N93 -> 0
A94: Annual Internet connection subscriptionn:(Taba and Save) | B94: 1274400 | C94: 1274400 | D94: 1890528 | E94: 1890528 | F94: 1890528 | G94: 1890528 | H94: 1890528 | I94: 1890528 | J94: 1890528 | K94: 1890528 | L94: 1890528 | M94: 1890528 | N94: =SUM(B94:M94) -> 21454080 | O94: 23739699 | P94: =N94-O94 -> -2285619 | Q94: =O94/N94 -> 1.1065354
A95: Total ICT COST | B95: =SUM(B86:B94) -> 3403345.8 | C95: =SUM(C86:C94) -> 3320012.5 | D95: =SUM(D86:D94) -> 3936140.5 | E95: =SUM(E86:E94) -> 3936140.5 | F95: =SUM(F86:F94) -> 3936140.5 | G95: =SUM(G86:G94) -> 3936140.5 | H95: =SUM(H86:H94) -> 3936140.5 | I95: =SUM(I86:I94) -> 3936140.5 | ... P95: =SUM(P86:P94) -> 6704331 | Q95: =O95/N95 -> 0.86366322
A96: Finance Cost
A97: Cogebanque loan Interest | B97: =N97/12 -> 6131602.8 | C97: 6131602.8 | D97: 6131602.8 | E97: 6131602.8 | F97: 6131602.8 | G97: 6131602.8 | H97: 6131602.8 | I97: 6131602.8 | J97: 6131602.8 | K97: 6131602.8 | L97: 6131602.8 | M97: 6131602.8 | N97: 73579234 | O97: 73579234 | P97: =N97-O97 -> 0 | Q97: =O97/N97 -> 1
A98: Missio Invest Interest | B98: =N98/12 -> 6663195 | C98: 6663195 | D98: 6663195 | E98: 6663195 | F98: 6663195 | G98: 6663195 | H98: 6663195 | I98: 6663195 | J98: 6663195 | K98: 6663195 | L98: 6663195 | M98: 6663195 | N98: 79958340 | O98: =O99-O97 -> 87057743 | P98: =N98-O98 -> -7099403 | Q98: =O98/N98 -> 1.0887888
A99: Total finance cost | B99: =B97+B98 -> 12794798 | C99: =C97+C98 -> 12794798 | D99: =D97+D98 -> 12794798 | E99: =E97+E98 -> 12794798 | F99: =F97+F98 -> 12794798 | G99: =G97+G98 -> 12794798 | H99: =H97+H98 -> 12794798 | I99: =I97+I98 -> 12794798 | ... N99: =N97+N98 -> 153537574 | O99: 160636977 | P99: =N99-O99 -> -7099403 | Q99: =O99/N99 -> 1.0462389
A100: TOTAL OPERATING EXPENSES(B) | B100: =B99+B95+B84+B75+B47 -> 1.1265873e+08 | C100: =C99+C95+C84+C75+C47 -> 1.125754e+08 | D100: =D99+D95+D84+D75+D47 -> 1.1319153e+08 | E100: =E99+E95+E84+E75+E47 -> 1.1319153e+08 | F100: =F99+F95+F84+F75+F47 -> 1.1319153e+08 | G100: =G99+G95+G84+G75+G47 -> 1.1319153e+08 | H100: =H99+H95+H84+H75+H47 -> 1.1319153e+08 | I100: =I99+I95+I84+I75+I47 -> 1.1319153e+08 | ... O100: =O99+O95+O84+O75+O47 -> 1.254636e+09 | P100: =N100-O100 -> 1.4097047e+08 | Q100: =O100/N100 -> 0.89898981
A101: SURPLUS /DEFICIT FOR PERIOD(A-B) | B101: =B39-B100 -> 32145748 | C101: =C39-C100 -> 47349165 | D101: =D39-D100 -> 46733037 | E101: =E39-E100 -> 46733037 | F101: =F39-F100 -> 65240999 | G101: =G39-G100 -> 65240999 | H101: =H39-H100 -> 65240999 | I101: =I39-I100 -> 65240999 | ... O101: =O39-O100 -> 1.0592373e+08 | P101: =N101-O101 -> 4.7707023e+08 | Q101: =O101/N101 -> 0.18168924
A102: CASH FLOW
...

Sheet INCOME DETAILS
C1: Current Student | G1: Projected New student
G2: September 2024 Intake | J2: March 2025 Intake | M2: June 2025 Intake
C3: Day program | D3: Weekend Program | E3: Holiday Program | F3: Total Existing | G3: Day program | H3: Weekend Program | I3: Holiday Program | J3: Day program | K3: Weekend Program | L3: Holiday Program | M3: Day program | N3: Weekend Program | O3: Holiday Program | P3: Total Projected | Q3: Total Student Budgeted 2024-2025 | R3: Sponsored Student | AB3: Tuition fees | AC3: Registration fees+Technology fees | AD3: Application fees | AE3: Internship fees | AF3: Final project fees | AG3: Total
R4: Minisante | T4: Chancen | V4: YWCA | W4: Private student | X4: Existing private student | Y4: Projected Private
R5: Existing | S5: Projected | T5: Existing | U5: Projected | V5: Projected | Y5: Sept int | Z5: March In | AA5: June int
B6: 1.Faculty of science and technology
B7: 1.1 Department Biomedical Laboratory science
B8: L8 S1&2 | C8: 22 | D8: 0 | E8: 0 | F8: =SUM(C8:E8) -> 22 | H8: 0 | I8: 0 | J8: 15 | K8: 0 | L8: 0 | N8: 0 | O8: 0 | P8: =SUM(G8:O8) -> 15 | Q8: =F8+P8 -> 37 | R8: 14 | U8: 10 | V8: 5 | W8: =Q8-SUM(R8:V8) -> 8 | X8: =F8-R8-T8 -> 8 | AB8: =((X8*600000)+(Y8*600000)+(Z8*450000)+(AA8*300000)) -> 4800000 | AC8: =W8*33000 -> 264000 | AD8: =W8*5000 -> 40000 | AG8: =SUM(AB8:AD8) -> 5104000
B9: L8 S3&4 | C9: 26 | D9: 0 | E9: 0 | F9: =SUM(C9:E9) -> 26 | G9: 0 | H9: 0 | I9: 0 | J9: 0 | K9: 0 | L9: 0 | M9: 0 | N9: 0 | O9: 0 | P9: =SUM(G9:O9) -> 0 | Q9: =F9+P9 -> 26 | R9: 0 | W9: =Q9-SUM(R9:V9) -> 26 | X9: =F9-R9-T9 -> 26 | AB9: =((X9*600000)+(Y9*600000)+(Z9*450000)+(AA9*300000)) -> 15600000 | AC9: =W9*33000 -> 858000 | AE9: =(X9-Y9-Z9-AA9)*160000 -> 4160000 | AG9: =SUM(AB9:AD9) -> 16458000
B10: L8 S5&6 | C10: 76 | D10: 0 | E10: 0 | F10: =SUM(C10:E10) -> 76 | G10: 10 | H10: 0 | I10: 0 | K10: 0 | L10: 0 | M10: 20 | N10: 0 | O10: 0 | P10: =SUM(G10:O10) -> 30 | Q10: =F10+P10 -> 106 | R10: 0 | U10: 30 | W10: =Q10-SUM(R10:V10) -> 76 | X10: =F10-R10-T10 -> 76 | Y10: 0 | AA10: 0 | AB10: =((X10*600000)+(Y10*600000)+(Z10*450000)+(AA10*300000)) -> 45600000 | AC10: =W10*33000 -> 2508000 | AE10: =(X10-Y10-Z10-AA10)*160000 -> 12160000 | AG10: =SUM(AB10:AD10) -> 48108000
B11: L8 S7&8 | C11: 18 | D11: 0 | E11: 0 | F11: =SUM(C11:E11) -> 18 | G11: 0 | H11: 0 | I11: 0 | J11: 0 | K11: 0 | L11: 0 | M11: 0 | N11: 0 | O11: 0 | P11: =SUM(G11:O11) -> 0 | Q11: =F11+P11 -> 18 | R11: 0 | W11: =Q11-SUM(R11:V11) -> 18 | X11: =F11-R11-T11 -> 18 | AB11: =((X11*600000)+(Y11*600000)+(Z11*450000)+(AA11*300000)) -> 10800000 | AC11: =W11*33000 -> 594000 | AE11: =(X11-Y11-Z11-AA11)*160000 -> 2880000 | AG11: =SUM(AB11:AD11) -> 11394000
B12: Graduands | D12: 0 | E12: 0 | F12: =SUM(C12:E12) -> 0 | G12: 0 | H12: 0 | I12: 0 | J12: 0 | K12: 0 | L12: 0 | M12: 0 | N12: 0 | O12: 0 | P12: =SUM(G12:O12) -> 0 | Q12: =F12+P12 -> 0 | X12: =F12-R12-T12 -> 0
B13: Total students in BLS | F13: =SUM(F8:F12) -> 142 | G13: =SUM(G8:G12) -> 10 | H13: =SUM(H8:H12) -> 0 | I13: =SUM(I8:I12) -> 0 | J13: =SUM(J8:J12) -> 15 | K13: =SUM(K8:K12) -> 0 | L13: =SUM(L8:L12) -> 0 | M13: =SUM(M8:M12) -> 20 | ... AG13: =SUM(AG8:AG12) -> 81064000
B14: 1.2 Department of computer science
B15: L8 S1&2 | C15: =35+4 -> 39 | D15: 23 | F15: =SUM(C15:E15) -> 62 | G15: 10 | H15: 20 | I15: 0 | J15: 30 | K15: 10 | L15: 0 | M15: 10 | N15: 20 | O15: 0 | P15: =SUM(G15:O15) -> 100 | Q15: =F15+P15 -> 162 | T15: =21 -> 21 | U15: 50 | V15: 40 | W15: =Q15-SUM(R15:V15) -> 51 | X15: =F15-R15-T15 -> 41 | Z15: 10 | AB15: =((X15*375000)+(Y15*375000)+(Z15*250000)+(AA15*125000)) -> 17875000 | AC15: =W15*33000 -> 1683000 | AD15: =W15*5000 -> 255000 | AG15: =SUM(AB15:AD15) -> 19813000
B16: L8 S3&4 | C16: 63 | F16: =SUM(C16:E16) -> 63 | G16: 0 | H16: 0 | I16: 0 | J16: 0 | K16: 0 | L16: 0 | M16: 0 | N16: 0 | O16: 0 | P16: =SUM(G16:O16) -> 0 | Q16: =F16+P16 -> 63 | T16: 66 | W16: =Q16-SUM(R16:V16) -> -3 | X16: =F16-R16-T16 -> -3 | AG16: =SUM(AB16:AD16) -> 0
B17: L8 S5&6 | C17: 8 | D17: 20 | F17: =SUM(C17:E17) -> 28 | G17: 0 | H17: 10 | I17: 0 | J17: 0 | L17: 0 | M17: 0 | N17: 10 | O17: 0 | P17: =SUM(G17:O17) -> 20 | Q17: =F17+P17 -> 48 | W17: =Q17-SUM(R17:V17) -> 48 | X17: =F17-R17-T17 -> 28 | Z17: 10 | AA17: 10 | AB17: =((X17*375000)+(Y17*375000)+(Z17*250000)+(AA17*125000)) -> 14250000 | AC17: =W17*33000 -> 1584000 | AG17: =SUM(AB17:AD17) -> 15834000
B18: L8 S7&8 | C18: 17 | D18: 19 | F18: =SUM(C18:E18) -> 36 | G18: 0 | H18: 0 | I18: 0 | J18: 0 | K18: 0 | L18: 0 | M18: 0 | N18: 0 | O18: 0 | P18: =SUM(G18:O18) -> 0 | Q18: =F18+P18 -> 36 | W18: =Q18-SUM(R18:V18) -> 36 | X18: =F18-R18-T18 -> 36 | AB18: =((X18*375000)+(Y18*375000)+(Z18*250000)+(AA18*125000)) -> 13500000 | AC18: =W18*33000 -> 1188000 | AE18: =W18*30000 -> 1080000 | AF18: =W18*150000 -> 5400000 | AG18: =SUM(AB18:AD18) -> 14688000
B19: Graduands | F19: =SUM(C19:E19) -> 0 | G19: 0 | H19: 0 | I19: 0 | J19: 0 | K19: 0 | L19: 0 | M19: 0 | N19: 0 | O19: 0 | P19: =SUM(G19:O19) -> 0 | Q19: =F19+P19 -> 0 | X19: =F19-R19-T19 -> 0 | AB19: =((X19*375000)+(Y19*375000)+(Z19*250000)+(AA19*125000)) -> 0 | AC19: =W19*33000 -> 0
B20: Total Students in CS | C20: =SUM(C15:C19) -> 127 | D20: =SUM(D15:D19) -> 62 | F20: =SUM(F15:F19) -> 189 | G20: =SUM(G15:G19) -> 10 | H20: =SUM(H15:H19) -> 30 | I20: =SUM(I15:I19) -> 0 | J20: =SUM(J15:J19) -> 30 | K20: =SUM(K15:K19) -> 10 | L20: =SUM(L15:L19) -> 0 | M20: =SUM(M15:M19) -> 10 | ... O20: =SUM(O15:O19) -> 0 | Q20: =SUM(Q15:Q19) -> 309 | R20: =SUM(R15:R19) -> 0 | S20: =SUM(S15:S19) -> 0 | T20: =SUM(T15:T19) -> 87 | U20: =SUM(U15:U19) -> 50 | V20: =SUM(V15:V19) -> 40 | W20: =SUM(W15:W19) -> 132 | X20: =SUM(X15:X19) -> 102 | ... AG20: =SUM(AG15:AG19) -> 50335000
B21: 1.3 Food processing Department
B22: L8 S1&2 | C22: 0 | D22: 0 | E22: 0 | F22: =SUM(C22:E22) -> 0 | G22: 0 | H22: 0 | I22: 0 | J22: 0 | K22: 0 | L22: 0 | M22: 50 | N22: 20 | P22: =SUM(G22:O22) -> 70 | Q22: =F22+P22 -> 70 | W22: =Q22-SUM(R22:V22) -> 70 | X22: =F22-R22-T22 -> 0 | AA22: 70 | AB22: =((X22*375000)+(Y22*375000)+(Z22*250000)+(AA22*125000)) -> 8750000 | AC22: =W22*33000 -> 2310000 | AD22: =W22*5000 -> 350000 | AG22: =SUM(AB22:AD22) -> 11410000
B23: L8 S3&4 | C23: 0 | D23: 0 | E23: 0 | F23: =SUM(C23:E23) -> 0 | G23: 0 | H23: 0 | I23: 0 | J23: 0 | K23: 0 | L23: 0 | M23: 0 | N23: 0 | O23: 0 | P23: =SUM(G23:O23) -> 0 | Q23: =F23+P23 -> 0 | W23: =Q23-SUM(R23:V23) -> 0 | X23: =F23-R23-T23 -> 0 | AC23: =W23*33000 -> 0 | AD23: =W23*5000 -> 0 | AE23: 0 | AF23: 0 | AG23: =SUM(AB23:AD23) -> 0
B24: L8 S5&6 | C24: 0 | D24: 0 | E24: 0 | F24: =SUM(C24:E24) -> 0 | G24: 0 | H24: 0 | I24: 0 | J24: 0 | K24: 0 | L24: 0 | M24: 0 | N24: 0 | O24: 0 | P24: =SUM(G24:O24) -> 0 | Q24: =F24+P24 -> 0 | W24: =Q24-SUM(R24:V24) -> 0 | X24: =F24-R24-T24 -> 0 | AC24: =W24*33000 -> 0 | AD24: =W24*5000 -> 0 | AE24: 0 | AF24: 0 | AG24: =SUM(AB24:AD24) -> 0
B25: L8 S7&8 | C25: 0 | D25: 0 | E25: 0 | F25: =SUM(C25:E25) -> 0 | G25: 0 | H25: 0 | I25: 0 | J25: 0 | K25: 0 | L25: 0 | M25: 0 | N25: 0 | O25: 0 | P25: =SUM(G25:O25) -> 0 | Q25: =F25+P25 -> 0 | W25: =Q25-SUM(R25:V25) -> 0 | X25: =F25-R25-T25 -> 0 | AC25: =W25*33000 -> 0 | AD25: =W25*5000 -> 0 | AE25: 0 | AF25: 0 | AG25: =SUM(AB25:AD25) -> 0
B26: Graduands | C26: 0 | D26: 0 | E26: 0 | F26: =SUM(C26:E26) -> 0 | G26: 0 | H26: 0 | I26: 0 | J26: 0 | K26: 0 | L26: 0 | M26: 0 | N26: 0 | O26: 0 | P26: =SUM(G26:O26) -> 0 | Q26: =F26+P26 -> 0 | W26: =Q26-SUM(R26:V26) -> 0 | X26: =F26-R26-T26 -> 0 | AC26: =W26*33000 -> 0 | AD26: =W26*5000 -> 0 | AE26: 0 | AF26: 0 | AG26: =SUM(AB26:AD26) -> 0
B27: Total Students in FP | C27: =SUM(C22:C26) -> 0 | D27: =SUM(D22:D26) -> 0 | E27: =SUM(E22:E26) -> 0 | F27: =SUM(F22:F26) -> 0 | G27: =SUM(G22:G26) -> 0 | H27: =SUM(H22:H26) -> 0 | I27: =SUM(I22:I26) -> 0 | J27: =SUM(J22:J26) -> 0 | ... AG27: =SUM(AG22:AG26) -> 11410000
B28: 1.Total Students in faculty of Science and technology | F28: =F13+F20+F27 -> 331 | G28: =G13+G20+G27 -> 20 | H28: =H13+H20+H27 -> 30 | I28: =I13+I20+I27 -> 0 | J28: =J13+J20+J27 -> 45 | K28: =K13+K20+K27 -> 10 | L28: =L13+L20+L27 -> 0 | M28: =M13+M20+M27 -> 80 | ... AG28: =AG13+AG20+AG27 -> 142809000
B29: 2.Faculty of social work | P29: =SUM(G29:O29) -> 0 | X29: =F29-R29-T29 -> 0
B30: L8 S1&2 | C30: 0 | D30: 34 | F30: =SUM(C30:E30) -> 34 | H30: 10 | K30: 20 | N30: 10 | P30: =SUM(G30:O30) -> 40 | Q30: =F30+P30 -> 74 | W30: =Q30-SUM(R30:V30) -> 74 | X30: =F30-R30-T30 -> 34 | Y30: 10 | Z30: 20 | AA30: 10 | AB30: =((X30*375000)+(Y30*375000)+(Z30*250000)+(AA30*125000)) -> 22750000 | AC30: =W30*33000 -> 2442000 | AD30: =W30*5000 -> 370000 | AG30: =SUM(AB30:AD30) -> 25562000
B31: L8 S3&4 | C31: 0 | D31: 0 | F31: =SUM(C31:E31) -> 0 | P31: =SUM(G31:O31) -> 0 | Q31: =F31+P31 -> 0 | W31: =Q31-SUM(R31:V31) -> 0 | X31: =F31-R31-T31 -> 0 | AB31: =((X31*375000)+(Y31*375000)+(Z31*250000)+(AA31*125000)) -> 0 | AC31: =W31*33000 -> 0 | AG31: =SUM(AB31:AD31) -> 0
B32: L8 S5&6 | C32: 0 | D32: 14 | F32: =SUM(C32:E32) -> 14 | P32: =SUM(G32:O32) -> 0 | Q32: =F32+P32 -> 14 | W32: =Q32-SUM(R32:V32) -> 14 | X32: =F32-R32-T32 -> 14 | AB32: =((X32*375000)+(Y32*375000)+(Z32*250000)+(AA32*125000)) -> 5250000 | AC32: =W32*33000 -> 462000 | AG32: =SUM(AB32:AD32) -> 5712000
B33: L8 S7&8 | C33: 0 | D33: 14 | F33: =SUM(C33:E33) -> 14 | P33: =SUM(G33:O33) -> 0 | Q33: =F33+P33 -> 14 | W33: =Q33-SUM(R33:V33) -> 14 | X33: =F33-R33-T33 -> 14 | AB33: =((X33*375000)+(Y33*375000)+(Z33*250000)+(AA33*125000)) -> 5250000 | AC33: =W33*33000 -> 462000 | AE33: =W33*30000 -> 420000 | AF33: =W33*150000 -> 2100000 | AG33: =SUM(AB33:AD33) -> 5712000
B34: Graduands | F34: =SUM(C34:E34) -> 0 | P34: =SUM(G34:O34) -> 0 | Q34: =F34+P34 -> 0 | W34: =Q34-SUM(R34:V34) -> 0 | X34: =F34-R34-T34 -> 0 | AB34: =((X34*375000)+(Y34*375000)+(Z34*250000)+(AA34*125000)) -> 0 | AC34: =W34*33000 -> 0 | AG34: =SUM(AB34:AD34) -> 0
B35: Partime | C35: 0 | D35: 0 | F35: =SUM(C35:E35) -> 0 | P35: =SUM(G35:O35) -> 0 | Q35: =F35+P35 -> 0 | W35: =Q35-SUM(R35:V35) -> 0 | X35: =F35-R35-T35 -> 0 | AB35: =((X35*375000)+(Y35*375000)+(Z35*250000)+(AA35*125000)) -> 0 | AC35: =W35*33000 -> 0 | AG35: =SUM(AB35:AD35) -> 0
B36: 2.Total students Faculty of social work | C36: 0 | D36: =SUM(D30:D35) -> 62 | F36: =SUM(F30:F35) -> 62 | G36: =SUM(G30:G35) -> 0 | H36: =SUM(H30:H35) -> 10 | I36: =SUM(I30:I35) -> 0 | J36: =SUM(J30:J35) -> 0 | K36: =SUM(K30:K35) -> 20 | L36: =SUM(L30:L35) -> 0 | M36: =SUM(M30:M35) -> 0 | ... AG36: =SUM(AG30:AG35) -> 36986000
B37: 3.Faculty of Education
B38: 3.1 Educational Management and planning | P38: =SUM(G38:O38) -> 0 | Q38: =F38+P38 -> 0 | X38: =F38-R38-T38 -> 0
B39: L8 S1&2 | C39: 0 | D39: 0 | F39: =SUM(C39:E39) -> 0 | P39: =SUM(G39:O39) -> 0 | Q39: =F39+P39 -> 0 | W39: =Q39-SUM(R39:V39) -> 0 | X39: =F39-R39-T39 -> 0 | AB39: =((X39*375000)+(Y39*375000)+(Z39*250000)+(AA39*125000)) -> 0 | AC39: =W39*33000 -> 0 | AD39: =W39*5000 -> 0 | AG39: =SUM(AB39:AD39) -> 0
B40: L8 S3&4 | C40: 0 | D40: 0 | F40: =SUM(C40:E40) -> 0 | P40: =SUM(G40:O40) -> 0 | Q40: =F40+P40 -> 0 | W40: =Q40-SUM(R40:V40) -> 0 | X40: =F40-R40-T40 -> 0 | AB40: =((X40*375000)+(Y40*375000)+(Z40*250000)+(AA40*125000)) -> 0 | AC40: =W40*33000 -> 0 | AG40: =SUM(AB40:AD40) -> 0
B41: L8 S5&6 | C41: 0 | D41: 0 | F41: =SUM(C41:E41) -> 0 | P41: =SUM(G41:O41) -> 0 | Q41: =F41+P41 -> 0 | W41: =Q41-SUM(R41:V41) -> 0 | X41: =F41-R41-T41 -> 0 | AB41: =((X41*375000)+(Y41*375000)+(Z41*250000)+(AA41*125000)) -> 0 | AC41: =W41*33000 -> 0 | AG41: =SUM(AB41:AD41) -> 0
B42: L8 S7&8 | C42: 0 | D42: 0 | F42: =SUM(C42:E42) -> 0 | P42: =SUM(G42:O42) -> 0 | Q42: =F42+P42 -> 0 | W42: =Q42-SUM(R42:V42) -> 0 | X42: =F42-R42-T42 -> 0 | AB42: =((X42*375000)+(Y42*375000)+(Z42*250000)+(AA42*125000)) -> 0 | AC42: =W42*33000 -> 0 | AE42: =W42*30000 -> 0 | AF42: =W42*150000 -> 0 | AG42: =SUM(AB42:AD42) -> 0
B43: Graduands | C43: 0 | D43: 0 | F43: =SUM(C43:E43) -> 0 | P43: =SUM(G43:O43) -> 0 | Q43: =F43+P43 -> 0 | W43: =Q43-SUM(R43:V43) -> 0 | X43: =F43-R43-T43 -> 0 | AB43: =((X43*375000)+(Y43*375000)+(Z43*250000)+(AA43*125000)) -> 0 | AC43: =W43*33000 -> 0 | AG43: =SUM(AB43:AD43) -> 0
B44: Partime | C44: 0 | D44: 0 | F44: =SUM(C44:E44) -> 0 | P44: =SUM(G44:O44) -> 0 | Q44: =F44+P44 -> 0 | W44: =Q44-SUM(R44:V44) -> 0 | X44: =F44-R44-T44 -> 0 | AB44: =((X44*375000)+(Y44*375000)+(Z44*250000)+(AA44*125000)) -> 0 | AC44: =W44*33000 -> 0 | AG44: =SUM(AB44:AD44) -> 0
B45: Total students | F45: =SUM(F39:F44) -> 0 | G45: =SUM(G39:G44) -> 0 | H45: =SUM(H39:H44) -> 0 | I45: =SUM(I39:I44) -> 0 | J45: =SUM(J39:J44) -> 0 | K45: =SUM(K39:K44) -> 0 | L45: =SUM(L39:L44) -> 0 | M45: =SUM(M39:M44) -> 0 | ... AG45: =SUM(AG39:AG44) -> 0
B46: 3.2 Department of art and social science
B47: L8 S1&2 | C47: 38 | D47: 63 | E47: 140 | F47: =SUM(C47:E47) -> 241 | G47: 10 | H47: 20 | I47: 60 | J47: 10 | K47: 20 | L47: 40 | M47: 10 | N47: 20 | O47: 60 | P47: =SUM(G47:O47) -> 250 | Q47: =F47+P47 -> 491 | T47: 25 | W47: =Q47-SUM(R47:V47) -> 466 | X47: =F47-R47-T47 -> 216 | Y47: 90 | Z47: 70 | AA47: 90 | AB47: =(((E47*330000)+(I47*330000)+(L47*220000)+(O47*110000))+((C47-T47)*500000)+(D47*375000)+(G47*500000)+(H47*375000)+((J47-U47)*375000)+(K47*250000)+(M47*250000)+(N47*125000)) -> 137775000 | AC47: =W47*33000 -> 15378000 | AD47: =W47*5000 -> 2330000 | AG47: =SUM(AB47:AD47) -> 155483000
B48: L8 S3&4 | C48: 98 | D48: 17 | F48: =SUM(C48:E48) -> 115 | G48: 0 | H48: 0 | I48: 0 | J48: 0 | K48: 0 | L48: 0 | M48: 0 | N48: 0 | O48: 0 | P48: =SUM(G48:O48) -> 0 | Q48: =F48+P48 -> 115 | W48: =Q48-SUM(R48:V48) -> 115 | X48: =F48-R48-T48 -> 115 | Y48: =W48-X48 -> 0 | AB48: =(((E48*330000)+(I48*330000)+(L48*220000)+(O48*110000))+((C48-T48)*500000)+(D48*375000)+(G48*500000)+(H48*375000)+((J48-U48)*375000)+(K48*250000)+(M48*250000)+(N48*125000)) -> 55375000 | AC48: =W48*33000 -> 3795000 | AG48: =SUM(AB48:AD48) -> 59170000
B49: L8 S5&6 | D49: 16 | E49: 5 | F49: =SUM(C49:E49) -> 21 | G49: 0 | H49: 10 | I49: 20 | J49: 0 | K49: 10 | L49: 20 | M49: 0 | O49: 30 | P49: =SUM(G49:O49) -> 90 | Q49: =F49+P49 -> 111 | W49: =Q49-SUM(R49:V49) -> 111 | X49: =F49-R49-T49 -> 21 | Y49: 30 | Z49: 30 | AA49: 30 | AB49: =(((E49*330000)+(I49*330000)+(L49*220000)+(O49*110000))+((C49-T49)*500000)+(D49*375000)+(G49*500000)+(H49*375000)+((J49-U49)*375000)+(K49*250000)+(M49*250000)+(N49*125000)) -> 28200000 | AC49: =W49*33000 -> 3663000 | AD49: =(Y49+Z49+AA49)*5000 -> 450000 | AG49: =SUM(AB49:AD49) -> 32313000
B50: L8 S7&8 | D50: 12 | E50: 8 | F50: =SUM(C50:E50) -> 20 | G50: 0 | H50: 0 | I50: 0 | J50: 0 | K50: 0 | L50: 0 | M50: 0 | N50: 0 | O50: 0 | P50: =SUM(G50:O50) -> 0 | Q50: =F50+P50 -> 20 | W50: =Q50-SUM(R50:V50) -> 20 | X50: =F50-R50-T50 -> 20 | AB50: =(((E50*330000)+(I50*330000)+(L50*220000)+(O50*110000))+((C50-T50)*500000)+(D50*375000)+(G50*500000)+(H50*375000)+((J50-U50)*375000)+(K50*250000)+(M50*250000)+(N50*125000)) -> 7140000 | AC50: =W50*33000 -> 660000 | AE50: =W50*30000 -> 600000 | AG50: =SUM(AB50:AD50) -> 7800000
B51: Graduands | D51: 12 | E51: 8 | F51: =SUM(C51:E51) -> 20 | G51: 0 | H51: 0 | I51: 0 | J51: 0 | K51: 0 | L51: 0 | M51: 0 | N51: 0 | O51: 0 | P51: =SUM(G51:O51) -> 0 | Q51: =F51+P51 -> 20 | W51: =Q51-SUM(R51:V51) -> 20 | X51: =F51-R51-T51 -> 20 | AB51: =(((E51*330000)+(I51*330000)+(L51*220000)+(O51*110000))+((C51-T51)*500000)+(D51*375000)+(G51*500000)+(H51*375000)+((J51-U51)*375000)+(K51*250000)+(M51*250000)+(N51*125000)) -> 7140000 | AC51: =W51*33000 -> 660000 | AF51: =W51*150000 -> 3000000 | AG51: =SUM(AB51:AD51) -> 7800000
B52: Partime | F52: =SUM(C52:E52) -> 0 | G52: 0 | H52: 0 | I52: 0 | J52: 0 | K52: 0 | L52: 0 | M52: 0 | N52: 0 | O52: 0 | P52: =SUM(G52:O52) -> 0 | Q52: =F52+P52 -> 0 | W52: =Q52-SUM(R52:V52) -> 0 | X52: =F52-R52-T52 -> 0 | AB52: =(((E52*330000)+(I52*330000)+(L52*220000)+(O52*110000))+((C52-T52)*500000)+(D52*375000)+(G52*500000)+(H52*375000)+((J52-U52)*375000)+(K52*250000)+(M52*250000)+(N52*125000)) -> 0 | AC52: =W52*33000 -> 0 | AG52: =SUM(AB52:AD52) -> 0
B53: Total students | C53: 136 | D53: 120 | F53: =SUM(F47:F52) -> 417 | G53: =SUM(G47:G52) -> 10 | H53: =SUM(H47:H52) -> 30 | I53: =SUM(I47:I52) -> 80 | J53: =SUM(J47:J52) -> 10 | K53: =SUM(K47:K52) -> 30 | L53: =SUM(L47:L52) -> 60 | M53: =SUM(M47:M52) -> 10 | ... AG53: =SUM(AG47:AG52) -> 262566000
B54: 3.3 Department of Science | X54: =F54-R54-T54 -> 0
B55: L8 S1&2 | C55: 54 | D55: 16 | E55: 137 | F55: =SUM(C55:E55) -> 207 | H55: 20 | I55: 40 | J55: 10 | K55: 10 | L55: 40 | N55: 20 | O55: 40 | P55: =SUM(G55:O55) -> 180 | Q55: =F55+P55 -> 387 | W55: =Q55-SUM(R55:V55) -> 387 | X55: =F55-R55-T55 -> 207 | Y55: 60 | Z55: 60 | AA55: 60 | AB55: =(((E55*330000)+(I55*330000)+(L55*220000)+(O55*110000))+((C55-T55)*500000)+(D55*375000)+(G55*500000)+(H55*375000)+((J55-U55)*375000)+(K55*250000)+(M55*250000)+(N55*125000)) -> 120860000 | AC55: =W55*33000 -> 12771000 | AD55: =W55*5000 -> 1935000 | AG55: =SUM(AB55:AD55) -> 135566000
B56: L8 S3&4 | C56: 113 | D56: 48 | F56: =SUM(C56:E56) -> 161 | P56: =SUM(G56:O56) -> 0 | Q56: =F56+P56 -> 161 | T56: 112 | W56: =Q56-SUM(R56:V56) -> 49 | X56: =F56-R56-T56 -> 49 | AB56: =(((E56*330000)+(I56*330000)+(L56*220000)+(O56*110000))+((C56-T56)*500000)+(D56*375000)+(G56*500000)+(H56*375000)+((J56-U56)*375000)+(K56*250000)+(M56*250000)+(N56*125000)) -> 18500000 | AC56: =W56*33000 -> 1617000 | AG56: =SUM(AB56:AD56) -> 20117000
B57: L8 S5&6 | D57: 56 | E57: 69 | F57: =SUM(C57:E57) -> 125 | H57: 10 | I57: 20 | K57: 15 | L57: 20 | N57: 20 | O57: 20 | P57: =SUM(G57:O57) -> 105 | Q57: =F57+P57 -> 230 | W57: =Q57-SUM(R57:V57) -> 230 | X57: =F57-R57-T57 -> 125 | Y57: 30 | Z57: 35 | AA57: 40 | AB57: =(((E57*330000)+(I57*330000)+(L57*220000)+(O57*110000))+((C57-T57)*500000)+(D57*375000)+(G57*500000)+(H57*375000)+((J57-U57)*375000)+(K57*250000)+(M57*250000)+(N57*125000)) -> 66970000 | AC57: =W57*33000 -> 7590000 | AD57: =(Y57+Z57+AA57)*5000 -> 525000 | AG57: =SUM(AB57:AD57) -> 75085000
B58: L8 S7&8 | D58: 33 | E58: 47 | F58: =SUM(C58:E58) -> 80 | P58: =SUM(G58:O58) -> 0 | Q58: =F58+P58 -> 80 | W58: =Q58-SUM(R58:V58) -> 80 | X58: =F58-R58-T58 -> 80 | AB58: =(((E58*330000)+(I58*330000)+(L58*220000)+(O58*110000))+((C58-T58)*500000)+(D58*375000)+(G58*500000)+(H58*375000)+((J58-U58)*375000)+(K58*250000)+(M58*250000)+(N58*125000)) -> 27885000 | AC58: =W58*33000 -> 2640000 | AE58: =W58*30000 -> 2400000 | AG58: =SUM(AB58:AD58) -> 30525000
B59: Graduands | D59: 33 | E59: 47 | F59: =SUM(C59:E59) -> 80 | P59: =SUM(G59:O59) -> 0 | Q59: =F59+P59 -> 80 | W59: =Q59-SUM(R59:V59) -> 80 | X59: =F59-R59-T59 -> 80 | AB59: =(((E59*330000)+(I59*330000)+(L59*220000)+(O59*110000))+((C59-T59)*500000)+(D59*375000)+(G59*500000)+(H59*375000)+((J59-U59)*375000)+(K59*250000)+(M59*250000)+(N59*125000)) -> 27885000 | AC59: =W59*33000 -> 2640000 | AF59: =W59*150000 -> 12000000 | AG59: =SUM(AB59:AD59) -> 30525000
B60: Partime | F60: =SUM(C60:E60) -> 0 | P60: =SUM(G60:O60) -> 0 | Q60: =F60+P60 -> 0 | W60: =Q60-SUM(R60:V60) -> 0 | X60: =F60-R60-T60 -> 0 | AB60: =(((E60*330000)+(I60*330000)+(L60*220000)+(O60*110000))+((C60-T60)*500000)+(D60*375000)+(G60*500000)+(H60*375000)+((J60-U60)*375000)+(K60*250000)+(M60*250000)+(N60*125000)) -> 0 | AC60: =W60*33000 -> 0
B61: Total students | C61: 167 | D61: 186 | F61: =SUM(F55:F60) -> 653 | G61: =SUM(G55:G60) -> 0 | H61: =SUM(H55:H60) -> 30 | I61: =SUM(I55:I60) -> 60 | J61: =SUM(J55:J60) -> 10 | K61: =SUM(K55:K60) -> 25 | L61: =SUM(L55:L60) -> 60 | M61: =SUM(M55:M60) -> 0 | ... AG61: =SUM(AG55:AG60) -> 291818000
B62: 3. Total students in faculty of Education | C62: =C61+C53+C45 -> 303 | D62: =D61+D53+D45 -> 306 | E62: =E61+E53+E45 -> 0 | F62: =F61+F53+F45 -> 1070 | G62: =G61+G53+G45 -> 10 | H62: =H61+H53+H45 -> 60 | I62: =I61+I53+I45 -> 140 | J62: =J61+J53+J45 -> 20 | ... AG62: =AG61+AG53+AG45 -> 554384000
B63: 4.Faculty of Public Health and Human Nutrition | X63: =W62-X62 -> 625
B64: 4.1 Public Health | P64: =SUM(G64:O64) -> 0 | Q64: =F64+P64 -> 0
B65: L8 S1&2 | F65: =SUM(C65:E65) -> 0 | M65: 15 | P65: =SUM(G65:O65) -> 15 | Q65: =F65+P65 -> 15 | W65: =Q65-SUM(R65:V65) -> 15 | X65: =F65-R65-T65 -> 0 | Z65: 10 | AA65: 5 | AB65: =((X65*440000)+(Y65*440000)+(Z65*295000)+(AA65*150000)) -> 3700000 | AC65: =W65*33000 -> 495000 | AD65: =W65*5000 -> 75000 | AG65: =SUM(AB65:AD65) -> 4270000
B66: L8 S3&4 | F66: =SUM(C66:E66) -> 0 | P66: =SUM(G66:O66) -> 0 | Q66: =F66+P66 -> 0 | W66: =Q66-SUM(R66:V66) -> 0 | X66: =F66-R66-T66 -> 0 | AB66: =((X66*440000)+(Y66*440000)+(Z66*295000)+(AA66*150000)) -> 0 | AC66: =W66*33000 -> 0 | AG66: =SUM(AB66:AD66) -> 0
B67: L8 S5&6 | C67: 16 | F67: =SUM(C67:E67) -> 16 | J67: 20 | M67: 30 | P67: =SUM(G67:O67) -> 50 | Q67: =F67+P67 -> 66 | U67: 50 | W67: =Q67-SUM(R67:V67) -> 16 | X67: =F67-R67-T67 -> 16 | Z67: 0 | AA67: 0 | AB67: =((X67*440000)+(Y67*440000)+(Z67*295000)+(AA67*150000)) -> 7040000 | AC67: =W67*33000 -> 528000 | AD67: =(Y67+Z67+AA67)*5000 -> 0 | AG67: =SUM(AB67:AD67) -> 7568000
B68: L8 S7&8 | C68: 45 | F68: =SUM(C68:E68) -> 45 | P68: =SUM(G68:O68) -> 0 | Q68: =F68+P68 -> 45 | W68: =Q68-SUM(R68:V68) -> 45 | X68: =F68-R68-T68 -> 45 | AB68: =((X68*440000)+(Y68*440000)+(Z68*295000)+(AA68*150000)) -> 19800000 | AC68: =W68*33000 -> 1485000 | AE68: =W68*30000 -> 1350000 | AF68: =W68*150000 -> 6750000 | AG68: =SUM(AB68:AD68) -> 21285000
B69: Graduands | F69: =SUM(C69:E69) -> 0 | P69: =SUM(G69:O69) -> 0 | Q69: =F69+P69 -> 0 | W69: =Q69-SUM(R69:V69) -> 0 | X69: =F69-R69-T69 -> 0 | AB69: =((X69*440000)+(Y69*440000)+(Z69*295000)+(AA69*150000)) -> 0 | AC69: =W69*33000 -> 0 | AE69: =W69*30000 -> 0 | AF69: =W69*150000 -> 0 | AG69: =SUM(AB69:AD69) -> 0
B70: Partime | F70: =SUM(C70:E70) -> 0 | P70: =SUM(G70:O70) -> 0 | Q70: =F70+P70 -> 0 | W70: =Q70-SUM(R70:V70) -> 0 | X70: =F70-R70-T70 -> 0 | AB70: =((X70*440000)+(Y70*440000)+(Z70*295000)+(AA70*150000)) -> 0
B71: Total students | C71: =SUM(C65:C70) -> 61 | D71: =SUM(D65:D70) -> 0 | F71: =SUM(F65:F70) -> 61 | G71: =SUM(G65:G70) -> 0 | H71: =SUM(H65:H70) -> 0 | I71: =SUM(I65:I70) -> 0 | J71: =SUM(J65:J70) -> 20 | K71: =SUM(K65:K70) -> 0 | L71: =SUM(L65:L70) -> 0 | M71: =SUM(M65:M70) -> 45 | ... AG71: =SUM(AG65:AG70) -> 33123000
B72: 4.2 Human Nutrition | X72: =F72-R72-T72 -> 0
B73: L8 S1&2 | F73: =SUM(C73:E73) -> 0 | M73: 10 | P73: =SUM(G73:O73) -> 10 | Q73: =F73+P73 -> 10 | U73: 10 | V73: 0 | W73: =Q73-SUM(R73:V73) -> 0 | X73: =F73-R73-T73 -> 0 | AA73: 0 | AB73: =((X73*500000)+(Y73*500000)+(Z73*340000)+(AA73*170000)) -> 0 | AC73: =W73*33000 -> 0 | AD73: =W73*5000 -> 0 | AG73: =SUM(AB73:AD73) -> 0
B74: L8 S3&4 | C74: 5 | F74: =SUM(C74:E74) -> 5 | P74: =SUM(G74:O74) -> 0 | Q74: =F74+P74 -> 5 | R74: 5 | W74: =Q74-SUM(R74:V74) -> 0 | X74: =F74-R74-T74 -> 0 | AB74: =((X74*500000)+(Y74*500000)+(Z74*340000)+(AA74*170000)) -> 0 | AC74: =W74*33000 -> 0 | AG74: =SUM(AB74:AD74) -> 0
B75: L8 S5&6 | F75: =SUM(C75:E75) -> 0 | M75: 20 | P75: =SUM(G75:O75) -> 20 | Q75: =F75+P75 -> 20 | U75: 20 | W75: =Q75-SUM(R75:V75) -> 0 | X75: =F75-R75-T75 -> 0 | AA75: 0 | AB75: =((X75*500000)+(Y75*500000)+(Z75*340000)+(AA75*170000)) -> 0 | AC75: =W75*33000 -> 0 | AD75: =(Y75+Z75+AA75)*5000 -> 0 | AG75: =SUM(AB75:AD75) -> 0
B76: L8 S7&8 | F76: =SUM(C76:E76) -> 0 | P76: =SUM(G76:O76) -> 0 | Q76: =F76+P76 -> 0 | W76: =Q76-SUM(R76:V76) -> 0 | X76: =F76-R76-T76 -> 0 | AB76: =((X76*500000)+(Y76*500000)+(Z76*340000)+(AA76*170000)) -> 0 | AC76: =W76*33000 -> 0 | AE76: =W76*30000 -> 0 | AF76: =W76*150000 -> 0 | AG76: =SUM(AB76:AD76) -> 0
B77: Graduands | F77: =SUM(C77:E77) -> 0 | P77: =SUM(G77:O77) -> 0 | Q77: =F77+P77 -> 0 | W77: =Q77-SUM(R77:V77) -> 0 | X77: =F77-R77-T77 -> 0 | AB77: =((X77*500000)+(Y77*500000)+(Z77*340000)+(AA77*170000)) -> 0 | AC77: =W77*33000 -> 0 | AG77: =SUM(AB77:AD77) -> 0
B78: Partime | F78: =SUM(C78:E78) -> 0 | P78: =SUM(G78:O78) -> 0 | Q78: =F78+P78 -> 0 | W78: =Q78-SUM(R78:V78) -> 0 | X78: =F78-R78-T78 -> 0
B79: Total students | C79: =SUM(C73:C78) -> 5 | D79: =SUM(D73:D78) -> 0 | F79: =SUM(F73:F78) -> 5 | G79: =SUM(G73:G78) -> 0 | H79: =SUM(H73:H78) -> 0 | I79: =SUM(I73:I78) -> 0 | J79: =SUM(J73:J78) -> 0 | K79: =SUM(K73:K78) -> 0 | L79: =SUM(L73:L78) -> 0 | M79: =SUM(M73:M78) -> 30 | ... AG79: =SUM(AG73:AG78) -> 0
B80: 4.3 Nursing
B81: L8 S1&2 | C81: =43+40 -> 83 | F81: =SUM(C81:E81) -> 83 | J81: 60 | M81: 10 | P81: =SUM(G81:O81) -> 70 | Q81: =F81+P81 -> 153 | R81: 81 | S81: 50 | U81: 20 | W81: =Q81-SUM(R81:V81) -> 2 | X81: =F81-R81-T81 -> 2 | AA81: 0 | AB81: =((X81*800000)+(Y81*800000)+(Z81*600000)+(AA81*400000)) -> 1600000 | AC81: =W81*33000 -> 66000 | AD81: =W81*5000 -> 10000 | AG81: =SUM(AB81:AD81) -> 1676000
B82: L8 S3&4 | F82: =SUM(C82:E82) -> 0 | P82: =SUM(G82:O82) -> 0 | Q82: =F82+P82 -> 0 | W82: =Q82-SUM(R82:V82) -> 0 | X82: =F82-R82-T82 -> 0 | AB82: =((X82*800000)+(Y82*800000)+(Z82*600000)+(AA82*400000)) -> 0 | AC82: =W82*33000 -> 0 | AD82: =W82*5000 -> 0 | AG82: =SUM(AB82:AD82) -> 0
B83: L8 S5&6 | F83: =SUM(C83:E83) -> 0 | P83: =SUM(G83:O83) -> 0 | Q83: =F83+P83 -> 0 | W83: =Q83-SUM(R83:V83) -> 0 | X83: =F83-R83-T83 -> 0 | AB83: =((X83*800000)+(Y83*800000)+(Z83*600000)+(AA83*400000)) -> 0 | AC83: =W83*33000 -> 0 | AD83: =(Y83+Z83+AA83)*5000 -> 0 | AG83: =SUM(AB83:AD83) -> 0
B84: L8 S7&8 | F84: =SUM(C84:E84) -> 0 | P84: =SUM(G84:O84) -> 0 | Q84: =F84+P84 -> 0 | W84: =Q84-SUM(R84:V84) -> 0 | X84: =F84-R84-T84 -> 0 | AB84: =((X84*800000)+(Y84*800000)+(Z84*600000)+(AA84*400000)) -> 0 | AC84: =W84*33000 -> 0 | AG84: =SUM(AB84:AD84) -> 0
B85: Graduands | F85: =SUM(C85:E85) -> 0 | P85: =SUM(G85:O85) -> 0 | Q85: =F85+P85 -> 0 | W85: =Q85-SUM(R85:V85) -> 0 | X85: =F85-R85-T85 -> 0 | AB85: =((X85*800000)+(Y85*800000)+(Z85*600000)+(AA85*400000)) -> 0 | AC85: =W85*33000 -> 0 | AE85: =W85*30000 -> 0 | AF85: =W85*150000 -> 0 | AG85: =SUM(AB85:AD85) -> 0
B86: Partime | F86: =SUM(C86:E86) -> 0 | P86: =SUM(G86:O86) -> 0 | Q86: =F86+P86 -> 0 | W86: =Q86-SUM(R86:V86) -> 0 | X86: =F86-R86-T86 -> 0
B87: Total students | C87: =SUM(C81:C86) -> 83 | D87: =SUM(D81:D86) -> 0 | F87: =SUM(F81:F86) -> 83 | G87: =SUM(G81:G86) -> 0 | H87: =SUM(H81:H86) -> 0 | I87: =SUM(I81:I86) -> 0 | J87: =SUM(J81:J86) -> 60 | K87: =SUM(K81:K86) -> 0 | L87: =SUM(L81:L86) -> 0 | M87: =SUM(M81:M86) -> 10 | ... AG87: =SUM(AG81:AG86) -> 1676000
B88: 4.4Midwifery
B89: L8 S1&2 | C89: =100+100 -> 200 | F89: =SUM(C89:E89) -> 200 | J89: =120+10 -> 130 | M89: 10 | P89: =SUM(G89:O89) -> 140 | Q89: =F89+P89 -> 340 | R89: 200 | S89: 100 | U89: 40 | W89: =Q89-SUM(R89:V89) -> 0 | X89: =F89-R89-T89 -> 0 | AB89: =((X89*720000)+(Y89*720000)+(Z89*540000)+(AA89*360000)) -> 0 | AC89: =W89*33000 -> 0 | AG89: =SUM(AB89:AD89) -> 0
B90: L8 S3&4 | F90: =SUM(C90:E90) -> 0 | P90: =SUM(G90:O90) -> 0 | Q90: =F90+P90 -> 0 | W90: =Q90-SUM(R90:V90) -> 0 | X90: =F90-R90-T90 -> 0 | AB90: =((X90*720000)+(Y90*720000)+(Z90*540000)+(AA90*360000)) -> 0 | AC90: =W90*33000 -> 0 | AG90: =SUM(AB90:AD90) -> 0
B91: L8 S5&6 | F91: =SUM(C91:E91) -> 0 | P91: =SUM(G91:O91) -> 0 | Q91: =F91+P91 -> 0 | W91: =Q91-SUM(R91:V91) -> 0 | X91: =F91-R91-T91 -> 0 | Z91: 10 | AA91: 10 | AB91: =((X91*720000)+(Y91*720000)+(Z91*540000)+(AA91*360000)) -> 9000000 | AC91: =W91*33000 -> 0 | AD91: =(Y91+Z91+AA91)*5000 -> 100000 | AG91: =SUM(AB91:AD91) -> 9100000
B92: L8 S7&8 | F92: =SUM(C92:E92) -> 0 | P92: =SUM(G92:O92) -> 0 | Q92: =F92+P92 -> 0 | W92: =Q92-SUM(R92:V92) -> 0 | X92: =F92-R92-T92 -> 0 | AB92: =((X92*720000)+(Y92*720000)+(Z92*540000)+(AA92*360000)) -> 0 | AC92: =W92*33000 -> 0 | AG92: =SUM(AB92:AD92) -> 0
B93: Graduands | F93: =SUM(C93:E93) -> 0 | P93: =SUM(G93:O93) -> 0 | Q93: =F93+P93 -> 0 | W93: =Q93-SUM(R93:V93) -> 0 | X93: =F93-R93-T93 -> 0 | AB93: =((X93*720000)+(Y93*720000)+(Z93*540000)+(AA93*360000)) -> 0 | AC93: =W93*33000 -> 0 | AE93: =W93*30000 -> 0 | AF93: =W93*150000 -> 0 | AG93: =SUM(AB93:AD93) -> 0
B94: Partime | F94: =SUM(C94:E94) -> 0 | P94: =SUM(G94:O94) -> 0 | Q94: =F94+P94 -> 0 | W94: =Q94-SUM(R94:V94) -> 0 | X94: =F94-R94-T94 -> 0 | AB94: =((X94*720000)+(Y94*720000)+(Z94*540000)+(AA94*360000)) -> 0 | AC94: =W94*33000 -> 0 | AG94: =SUM(AB94:AD94) -> 0
B95: Total students | C95: =SUM(C89:C94) -> 200 | D95: =SUM(D89:D94) -> 0 | F95: =SUM(F89:F94) -> 200 | G95: =SUM(G89:G94) -> 0 | H95: =SUM(H89:H94) -> 0 | I95: =SUM(I89:I94) -> 0 | J95: =SUM(J89:J94) -> 130 | K95: =SUM(K89:K94) -> 0 | L95: =SUM(L89:L94) -> 0 | M95: =SUM(M89:M94) -> 10 | ... AG95: =SUM(AG89:AG94) -> 9100000
B96: 4. Total Faculty of public health and human nutrition | F96: =F95+F87+F79+F71 -> 349 | G96: =G95+G87+G79+G71 -> 0 | H96: =H95+H87+H79+H71 -> 0 | I96: =I95+I87+I79+I71 -> 0 | J96: =J95+J87+J79+J71 -> 210 | K96: =K95+K87+K79+K71 -> 0 | L96: =L95+L87+L79+L71 -> 0 | M96: =M95+M87+M79+M71 -> 95 | ... AG96: =AG95+AG87+AG79+AG71 -> 43899000
B97: 5. Faculty of Catechesis | X97: =F97-R97-T97 -> 0
B98: L8 S1&2 | C98: 57 | D98: 0 | F98: =SUM(C98:E98) -> 57 | J98: 20 | M98: 20 | P98: =SUM(G98:O98) -> 40 | Q98: =F98+P98 -> 97 | W98: =Q98-SUM(R98:V98) -> 97 | X98: =F98-R98-T98 -> 57 | Z98: 20 | AA98: 20 | AB98: =((X98*500000)+(Y98*500000)+(Z98*375000)+(AA98*250000)) -> 41000000 | AC98: =W98*33000 -> 3201000 | AD98: =W98*5000 -> 485000 | AG98: =SUM(AB98:AD98) -> 44686000
B99: L8 S3&4 | C99: 0 | D99: 0 | F99: =SUM(C99:E99) -> 0 | P99: =SUM(G99:O99) -> 0 | Q99: =F99+P99 -> 0 | W99: =Q99-SUM(R99:V99) -> 0 | X99: =F99-R99-T99 -> 0 | AB99: =((X99*500000)+(Y99*500000)+(Z99*375000)+(AA99*250000)) -> 0 | AC99: =W99*33000 -> 0 | AG99: =SUM(AB99:AD99) -> 0
B100: L8 S5&6 | C100: 30 | D100: 0 | F100: =SUM(C100:E100) -> 30 | P100: =SUM(G100:O100) -> 0 | Q100: =F100+P100 -> 30 | W100: =Q100-SUM(R100:V100) -> 30 | X100: =F100-R100-T100 -> 30 | AB100: =((X100*500000)+(Y100*500000)+(Z100*375000)+(AA100*250000)) -> 15000000 | AC100: =W100*33000 -> 990000 | AD100: =(Y100+Z100+AA100)*5000 -> 0 | AG100: =SUM(AB100:AD100) -> 15990000
...

Sheet INCOME EXECUTION 2024-2025
C3: Income in Details Number of students
C4: Budgeted number of students
D5: Budgeted | E5: Execution | F5: Variance | G5: % completion | H5: Rank
B6: 6 | C6: FCOM | D6: 653 | E6: 717 | F6: =E6-D6 -> 64 | G6: =E6/D6*100 -> 109.80092 | H6: 1
B7: 2 | C7: FSW | D7: 102 | E7: 105 | F7: =E7-D7 -> 3 | G7: =E7/D7*100 -> 102.94118 | H7: 2
B8: 3 | C8: FED | D8: 1695 | E8: 1536 | F8: =E8-D8 -> -159 | G8: =E8/D8*100 -> 90.619469 | H8: 3
B9: 4 | C9: FHS | D9: 841 | E9: 671 | F9: =E9-D9 -> -170 | G9: =E9/D9*100 -> 79.785969 | H9: 4
B10: 1 | C10: FST | D10: 379 | E10: 279 | F10: =E10-D10 -> -100 | G10: =E10/D10*100 -> 73.614776 | H10: 5
B11: 5 | C11: FCRS | D11: 160 | E11: 100 | F11: =E11-D11 -> -60 | G11: =E11/D11*100 -> 62.5 | H11: 6
B12: 7 | C12: PGDE | D12: 167 | E12: 34 | F12: =E12-D12 -> -133 | G12: =E12/D12*100 -> 20.359281 | H12: 7
C13: Total University | D13: =SUM(D6:D12) -> 3997 | E13: =SUM(E6:E12) -> 3442 | F13: =E13-D13 -> -555 | G13: =E13/D13*100 -> 86.114586
C14: Exisiting | E14: 2492 | F14: =E14-E13 -> -950
C15: % Increase in Number of student | E15: =(E13-E14)/E14 -> 0.3812199
E16: =D13*(1+E15) -> 5520.736
D18: =E13+950 -> 4392
C34: PROJECTS FEES
C35: Date | D35: 1470.780686
B36: Nishati Project | C36: 27.02.2025 | D36: 43786 | E36: =D36*D35 -> 64399603
B37: Fun learning consultation | C37: 27.08.2025 | D37: 3416.25 | E37: =D37*D38 -> 5735435.7
B38: Irrigation project | D38: 1678.868854 | E38: 72277194
B39: Grant Income | E39: =SUM(E36:E38) -> 1.4241223e+08

Sheet DETAILED Number of students
C2: L8 S1&2 | D2: L8 S3&4 | E2: L8 S5&6 | F2: L8 S7&8 | G2: L9 | H2: Graduands | I2: Partime | J2: Total students
A3: 1.Faculty of science and technology
A5: Department Biomedical Laboratory science | B5: Day program | C5: 22 | D5: 26 | E5: 76 | F5: 18 | I5: 0 | J5: =SUM(C5:I5) -> 142
B6: Weekend Program | C6: 0 | D6: 0 | E6: 0 | F6: 0 | I6: 0 | J6: =SUM(C6:I6) -> 0
A7: Department of computer science | B7: Day program | C7: =35+4 -> 39 | D7: 63 | E7: 8 | F7: 17 | J7: =SUM(C7:I7) -> 127
B8: Weekend Program | C8: 23 | E8: 20 | F8: 19 | J8: =SUM(C8:I8) -> 62
J9: =SUM(J5:J8) -> 331
A10: 2.Faculty of social work | B10: Day program | C10: 0 | D10: 0 | E10: 0 | F10: 0 | I10: 0 | J10: 0
B11: Weekend Program | C11: 34 | D11: 0 | E11: 14 | F11: 14 | I11: 0 | J11: =SUM(C11:I11) -> 62 | K11: =J11-'INCOME DETAILS'!#REF! -> #REF!
J12: =SUM(J10:J11) -> 62
A13: 3.Faculty of Education
A14: Educational Management and planning | B14: Day program | C14: 0 | D14: 0 | E14: 0 | F14: 0 | G14: 0 | H14: 0 | I14: 0
B15: Weekend Program | C15: 0 | D15: 0 | E15: 0 | F15: 0 | G15: 0 | H15: 0 | I15: 0
B16: Holiday program | C16: 0 | D16: 0 | E16: 0 | F16: 0 | G16: 0 | H16: 0 | I16: 0
A17: Department of art and social science | B17: Day program | C17: 38 | D17: 98 | J17: 136
B18: Weekend Program | C18: 63 | D18: 17 | E18: 16 | F18: 12 | H18: 12 | J18: 120
B19: Holiday program | C19: 140 | E19: 5 | F19: 8 | H19: 8 | J19: 161 | K19: 137
A20: Department of Science | B20: Day program | C20: 54 | D20: 113 | J20: 167 | K20: =J17+J20 -> 303
B21: Weekend Program | C21: 16 | D21: 48 | E21: 56 | F21: 33 | H21: 33 | J21: 186 | K21: =K20-K19 -> 166
B22: Holiday program | C22: 137 | E22: 69 | F22: 47 | H22: 47 | J22: 300
A23: 4.Faculty of public health and Human Nutrition | J23: =SUM(J14:J22) -> 1070
A24: Public Health | B24: Day program | E24: 16 | F24: 45 | J24: =SUM(C24:I24) -> 61
B25: Weekend Program | J25: =SUM(C25:I25) -> 0
A26: Human Nutrition | B26: Day program | D26: 5 | J26: =SUM(C26:I26) -> 5
B27: Weekend Program | J27: =SUM(C27:I27) -> 0
A28: Nursing | B28: Day program | C28: =43+40 -> 83 | J28: =SUM(C28:I28) -> 83
B29: Weekend Program | J29: =SUM(C29:I29) -> 0
A30: Midwifery | B30: Day program | C30: =100+100 -> 200 | J30: =SUM(C30:I30) -> 200
B31: Weekend Program | J31: =SUM(C31:I31) -> 0
J32: =SUM(J24:J31) -> 349
A33: 5. Faculty of Catechesis | B33: Day program | C33: 57 | D33: 0 | E33: 30 | F33: 32 | I33: 1 | J33: =SUM(C33:I33) -> 120
B34: Weekend Program | C34: 0 | D34: 0 | E34: 0 | F34: 0 | J34: =SUM(C34:I34) -> 0
J35: =SUM(J33:J34) -> 120
A36: 6.Faculty of commerce | B36: Day program | C36: 40 | D36: 113 | H36: 18 | J36: =SUM(C36:I36) -> 171
B37: Weekend Program | C37: 27 | D37: 101 | E37: 48 | F37: 74 | H37: 62 | J37: =SUM(C37:I37) -> 312
J38: =SUM(J36:J37) -> 483
A39: 7.Postgraduate students
B40: Huye campus | G40: 70 | J40: =SUM(G40:I40) -> 70
B41: Ngoma Learning center | G41: 7 | J41: =SUM(G41:I41) -> 7
J42: =SUM(J40:J41) -> 77
A43: Grand total number of students | H43: =SUM(H14:H42) -> 180 | I43: =I9+I12+I23+I32+I35+I38+I42 -> 0 | J43: =J9+J12+J23+J32+J35+J38+J42 -> 2492

Sheet Sheet1
C2: L8 S1&2 | D2: L8 S3&4 | E2: L8 S5&6 | F2: L8 S7&8 | G2: L9 | H2: Graduands | I2: Partime | J2: Total students
A3: 3.Faculty of Education
A4: Educational Management and planning | B4: Day program | C4: 0 | D4: 0 | E4: 0 | F4: 0 | G4: 0 | H4: 0 | I4: 0
B5: Weekend Program | C5: 0 | D5: 0 | E5: 0 | F5: 0 | G5: 0 | H5: 0 | I5: 0
B6: Holiday program | C6: 0 | D6: 0 | E6: 0 | F6: 0 | G6: 0 | H6: 0 | I6: 0
A7: Department of art and social science | B7: Day program | C7: 38 | D7: 98 | J7: 136
B8: Weekend Program | C8: 63 | D8: 17 | E8: 16 | F8: 12 | H8: 12 | J8: 120
B9: Holiday program | C9: 140 | E9: 5 | F9: 8 | H9: 8 | J9: 161
A10: Department of Science | B10: Day program | C10: 54 | D10: 113 | J10: 167
B11: Weekend Program | C11: 16 | D11: 48 | E11: 56 | F11: 33 | H11: 33 | J11: 186
B12: Holiday program | C12: 137 | E12: 69 | F12: 47 | H12: 47 | J12: 300
D16: 3.Faculty of Education | E16: Educational Management and planning | H16: Department of art and social science | K16: Department of Science
E17: Day program | F17: Weekend Program | G17: Holiday program | H17: Day program | I17: Weekend Program | J17: Holiday program | K17: Day program | L17: Weekend Program | M17: Holiday program
C18: L8 S1&2 | E18: 0 | F18: 0 | G18: 0 | H18: 38 | I18: 63 | J18: 140 | K18: 54 | L18: 16 | M18: 137
C19: L8 S3&4 | E19: 0 | F19: 0 | G19: 0 | H19: 98 | I19: 17 | K19: 113 | L19: 48
C20: L8 S5&6 | E20: 0 | F20: 0 | G20: 0 | I20: 16 | J20: 5 | L20: 56 | M20: 69
C21: L8 S7&8 | E21: 0 | F21: 0 | G21: 0 | I21: 12 | J21: 8 | L21: 33 | M21: 47
C22: L9 | E22: 0 | F22: 0 | G22: 0
C23: Graduands | E23: 0 | F23: 0 | G23: 0 | I23: 12 | J23: 8 | L23: 33 | M23: 47
C24: Partime | E24: 0 | F24: 0 | G24: 0
C25: Total students | H25: 136 | I25: 120 | J25: 161 | K25: 167 | L25: 186 | M25: 300

Sheet Communication fees
A1: Communication fee Policy
A2: Rector | B2: =20000*2 -> 40000
A3: Vice-Rector | B3: 20000
A4: DAF | B4: 20000
A5: DOQ | B5: 15000
A6: Dean of FCRS | B6: 10000
A7: Dean of FED | B7: 10000
A8: Dean of FST | B8: 10000
A9: Dean of FCOM | B9: 10000
A10: Dean of FSW | B10: 10000
A11: Dean of FPHHN | B11: 10000
A12: Dean of students | B12: 10000
A13: Academic Registrar | B13: 10000
A14: Academic secretaries FCRS | B14: 10000
... A46: Driver 2 | B46: 3000
B47: =SUM(B2:B46) -> 466000

Sheet Responsability allowance
A1: Responsibility allowance
A2: Dean of FCRS | B2: 200000
A3: Dean of FED | B3: 200000
A4: Dean of FST | B4: 200000
A5: Dean of FCOM | B5: 200000
A6: Dean of FSW | B6: 200000
A7: Dean of FPHHN | B7: 200000
A8: Academic secretaries FCRS | B8: 150000
A9: Academic secretaries FED | B9: 150000
A10: Academic secretaries FST | B10: 150000
A11: Academic secretaries FCOM | B11: 150000
A12: Academic secretaries FSW | B12: 150000
A13: Academic secretaries FPHHN | B13: 150000
... A23: HOD HN&PH | B23: 150000
B24: =SUM(B2:B23) -> 3600000

Sheet Sheet5
A1: Panel fees
C2: Supervisor | D2: Panel members
A3: Number of graduates | B3: 260 | C3: =B3*15000 -> 3900000 | D3: =B3*2*10000 -> 5200000 | E3: =C3+D3 -> 9100000

Sheet Part-time staff cost
B4: Part-time
A5: FCRS | B5: 3574075
A6: FSW | B6: 3522960
A7: FST | B7: 2253360
A8: FPHHN | B8: 2419200
A9: FCOM | B9: 4094880
A10: FED | B10: 73274100
B11: 89138575
A12: 0.083 | B12: =B11*A12 -> 7398501.7
B13: =B11+B12 -> 96537077

Sheet STAFF COST DETAILS
A1: Proposed Salary structure | B1: Proposed new structure | C1: Existing structure | D1: Difference
A2: Senior Lecturer | B2: 1081433.7 | C2: 1029936.9 | D2: =B2-C2 -> 51496.843
A3: Lecturer | B3: 772600.95 | C3: 735810.43 | D3: =B3-C3 -> 36790.521
A4: Ass Lecturer | B4: 617402.25 | C4: 588002.14 | D4: =B4-C4 -> 29400.107
A5: Tutorial Ass | B5: 517495.5 | C5: 492853 | D5: =B5-C5 -> 24642.5
A7: This change of increase of 5% of basic salary will have overall impact which the following:
A8: Total staff cost will increase Monthly by:
A9: Academic staff | B9: =--893988.285714287 -> 893988.29
A10: Administratif staff | B10: 653976.13
A11: Total Monthly Increase | B11: =SUM(B9:B10) -> 1547964.4 | C11: 1547964.4
A12: Total annual increase in staff | B12: =B11*12 -> 18575573 | C12: 18575573
