Workbook

Sheet BUDGET 2025-2026
B8: Financial Budget for Academic year 2025-2026
B9: September | C9: October | D9: November | E9: December | F9: January | G9: February | H9: March | I9: April | J9: May | K9: June | L9: July | M9: August | N9: GENERAL TOTAL
B10: TOTAL | C10: TOTAL | D10: TOTAL | E10: TOTAL | F10: TOTAL | G10: TOTAL | H10: TOTAL | I10: TOTAL | J10: TOTAL | K10: TOTAL | L10: TOTAL | M10: TOTAL | N10: TOTAL
A11: Budgeted Number of Students | N11: ='INCOME DETAILS'!Q121 -> 4692
A12: Revenue
A13: Tuition Fees
A14: Faculty of Catechesis and Religious Sciences | B14: =N14/12 -> 5208333.3 | C14: 5208333.3 | D14: 5208333.3 | E14: 5208333.3 | F14: 5208333.3 | G14: 5208333.3 | H14: 5208333.3 | I14: 5208333.3 | J14: 5208333.3 | K14: 5208333.3 | L14: 5208333.3 | M14: 5208333.3 | N14: ='INCOME DETAILS'!AB104 -> 62500000
A15: Faculty of Commerce | B15: =N15/12 -> 17343750 | C15: 17343750 | D15: 17343750 | E15: 17343750 | F15: 17343750 | G15: 17343750 | H15: 17343750 | I15: 17343750 | J15: 17343750 | K15: 17343750 | L15: 17343750 | M15: 17343750 | N15: ='INCOME DETAILS'!AB112 -> 208125000
A16: Faculty of Education -under graduates | B16: =N16/12 -> 54873750 | C16: 54873750 | D16: 54873750 | E16: 54873750 | F16: 54873750 | G16: 54873750 | H16: 54873750 | I16: 54873750 | J16: 54873750 | K16: 54873750 | L16: 54873750 | M16: 54873750 | N16: ='INCOME DETAILS'!AB55 -> 658485000
A17: Faculty of Education -PGD- Taba campus-Kibungo Learning Center | B17: =N17/12 -> 2482666.7 | C17: 2482666.7 | D17: 2482666.7 | E17: 2482666.7 | F17: 2482666.7 | G17: 2482666.7 | H17: 2482666.7 | I17: 2482666.7 | J17: 2482666.7 | K17: 2482666.7 | L17: 2482666.7 | M17: 2482666.7 | N17: ='INCOME DETAILS'!AB117 -> 29792000
A18: Faculty of Public Health and Human Nutrition | B18: =N18/12 -> 17256667 | C18: 17256667 | D18: 17256667 | E18: 17256667 | F18: 17256667 | G18: 17256667 | H18: 17256667 | I18: 17256667 | J18: 17256667 | K18: 17256667 | L18: 17256667 | M18: 17256667 | N18: ='INCOME DETAILS'!AB96 -> 207080000
A19: Faculty of Science and Technology | B19: =N19/12 -> 7187500 | C19: 7187500 | D19: 7187500 | E19: 7187500 | F19: 7187500 | G19: 7187500 | H19: 7187500 | I19: 7187500 | J19: 7187500 | K19: 7187500 | L19: 7187500 | M19: 7187500 | N19: ='INCOME DETAILS'!AB21 -> 86250000
A20: Faculty of Social Work | B20: =N20/12 -> 4114583.3 | C20: 4114583.3 | D20: 4114583.3 | E20: 4114583.3 | F20: 4114583.3 | G20: 4114583.3 | H20: 4114583.3 | I20: 4114583.3 | J20: 4114583.3 | K20: 4114583.3 | L20: 4114583.3 | M20: 4114583.3 | N20: ='INCOME DETAILS'!AB29 -> 49375000
A21: Expected New Masters Program fees | K21: =N21/3 -> 5000000 | L21: 5000000 | M21: 5000000 | N21: ='INCOME DETAILS'!AB120 -> 15000000
A22: Ministry of health sponsored student
A23: Existing Sponsored | B23: =N23/12 -> 23065417 | C23: 23065417 | D23: 23065417 | E23: 23065417 | F23: 23065417 | G23: 23065417 | H23: 23065417 | I23: 23065417 | J23: 23065417 | K23: 23065417 | L23: 23065417 | M23: 23065417 | N23: 276785000
A24: Projected Sponsored | K24: =N24/3 -> 24625000 | L24: 24625000 | M24: 24625000 | N24: ='INCOME DETAILS'!S124 -> 73875000
A25: Chancen Student Tuition fees | B25: =N25/12 -> 32324778 | C25: 32324778 | D25: 32324778 | E25: 32324778 | F25: 32324778 | G25: 32324778 | H25: 32324778 | I25: 32324778 | J25: 32324778 | K25: 32324778 | L25: 32324778 | M25: 32324778 | N25: ='INCOME DETAILS'!F133 -> 3.8789733e+08
A26: YWCA | F26: =N26/9 -> 6007962.2 | G26: 6007962.2 | H26: 6007962.2 | I26: 6007962.2 | J26: 6007962.2 | K26: 6007962.2 | L26: 6007962.2 | M26: 6007962.2 | N26: ='INCOME DETAILS'!E140 -> 54071660
A27: Total Tuition fees | B27: =SUM(B14:B26) -> 1.6385744e+08 | C27: =SUM(C14:C26) -> 1.6385744e+08 | D27: =SUM(D14:D26) -> 1.6385744e+08 | E27: =SUM(E14:E26) -> 1.6385744e+08 | F27: =SUM(F14:F26) -> 1.6986541e+08 | G27: =SUM(G14:G26) -> 1.6986541e+08 | H27: =SUM(H14:H26) -> 1.6986541e+08 | I27: =SUM(I14:I26) -> 1.6986541e+08 | ... N27: =SUM(N14:N26) -> 2.109236e+09
A28: Application fees | B28: =N28/12 -> 795833.33 | C28: 795833.33 | D28: 795833.33 | E28: 795833.33 | F28: 795833.33 | G28: 795833.33 | H28: 795833.33 | I28: 795833.33 | J28: 795833.33 | K28: 795833.33 | L28: 795833.33 | M28: 795833.33 | N28: ='INCOME DETAILS'!AD121 -> 9550000
A29: Internship fees | B29: =N29/12 -> 2340000 | C29: 2340000 | D29: 2340000 | E29: 2340000 | F29: 2340000 | G29: 2340000 | H29: 2340000 | I29: 2340000 | J29: 2340000 | K29: 2340000 | L29: 2340000 | M29: 2340000 | N29: ='INCOME DETAILS'!AE121 -> 28080000
A30: Research supervision fees | B30: =N30/12 -> 2225000 | C30: 2225000 | D30: 2225000 | E30: 2225000 | F30: 2225000 | G30: 2225000 | H30: 2225000 | I30: 2225000 | J30: 2225000 | K30: 2225000 | L30: 2225000 | M30: 2225000 | N30: ='INCOME DETAILS'!AF121 -> 26700000
A31: Graduation fees | J31: =N31 -> 13000000 | N31: =260*50000 -> 13000000
A32: Fines | B32: =N32/12 -> 50820 | C32: 50820 | D32: 50820 | E32: 50820 | F32: 50820 | G32: 50820 | H32: 50820 | I32: 50820 | J32: 50820 | K32: 50820 | L32: 50820 | M32: 50820 | N32: 609840
A33: Retake fees | B33: =N33/12 -> 33333.333 | C33: 33333.333 | D33: 33333.333 | E33: 33333.333 | F33: 33333.333 | G33: 33333.333 | H33: 33333.333 | I33: 33333.333 | J33: 33333.333 | K33: 33333.333 | L33: 33333.333 | M33: 33333.333 | N33: 400000
A34: Academic documents fees | B34: =N34/12 -> 232466.67 | C34: 232466.67 | D34: 232466.67 | E34: 232466.67 | F34: 232466.67 | G34: 232466.67 | H34: 232466.67 | I34: 232466.67 | J34: 232466.67 | K34: 232466.67 | L34: 232466.67 | M34: 232466.67 | N34: 2789600
A35: Total academic cost | B35: =SUM(B27:B34) -> 1.695349e+08 | C35: =SUM(C27:C34) -> 1.695349e+08 | D35: =SUM(D27:D34) -> 1.695349e+08 | E35: =SUM(E27:E34) -> 1.695349e+08 | F35: =SUM(F27:F34) -> 1.7554286e+08 | G35: =SUM(G27:G34) -> 1.7554286e+08 | H35: =SUM(H27:H34) -> 1.7554286e+08 | I35: =SUM(I27:I34) -> 1.7554286e+08 | ... N35: =SUM(N27:N34) -> 2.1903654e+09
A37: Other Income
A38: Accomodation fee | B38: =N38/12 -> 1309000 | C38: 1309000 | D38: 1309000 | E38: 1309000 | F38: 1309000 | G38: 1309000 | H38: 1309000 | I38: 1309000 | J38: 1309000 | K38: 1309000 | L38: 1309000 | M38: 1309000 | N38: =187*7000*12 -> 15708000
A39: Other Income(Different IURA Projects) | F39: =N39/8 -> 12500000 | G39: 12500000 | H39: 12500000 | I39: 12500000 | J39: 12500000 | K39: 12500000 | L39: 12500000 | M39: 12500000 | N39: 100000000
A40: Total Income | B40: =B38+B39 -> 1309000 | C40: =C38+C39 -> 1309000 | D40: =D38+D39 -> 1309000 | E40: =E38+E39 -> 1309000 | F40: =F38+F39 -> 13809000 | G40: =G38+G39 -> 13809000 | H40: =H38+H39 -> 13809000 | I40: =I38+I39 -> 13809000 | ... N40: =N38+N39 -> 115708000
A41: TOTAL REVENUE(A) | B41: =B40+B35 -> 1.708439e+08 | C41: =C40+C35 -> 1.708439e+08 | D41: =D40+D35 -> 1.708439e+08 | E41: =E40+E35 -> 1.708439e+08 | F41: =F40+F35 -> 1.8935186e+08 | G41: =G40+G35 -> 1.8935186e+08 | H41: =H40+H35 -> 1.8935186e+08 | I41: =I40+I35 -> 1.8935186e+08 | ... N41: =N40+N35 -> 2.3060734e+09
A42: OPERATING EXPENSES
A43: Staff Cost
A44: Full timeTeaching staff | B44: =33807840.0605505*110% -> 37188624 | C44: =33807840.0605505*110% -> 37188624 | D44: =33807840.0605505*110% -> 37188624 | E44: =33807840.0605505*110% -> 37188624 | F44: =33807840.0605505*120% -> 40569408 | G44: =33807840.0605505*120% -> 40569408 | H44: =33807840.0605505*120% -> 40569408 | I44: =33807840.0605505*120% -> 40569408 | J44: =33807840.0605505*120% -> 40569408 | K44: =33807840.0605505*150% -> 50711760 | L44: =33807840.0605505*150% -> 50711760 | M44: =33807840.0605505*150% -> 50711760 | N44: =SUM(B44:M44) -> 5.0373682e+08
A45: Part time teaching staff | B45: =8392352.01821476*110% -> 9231587.2 | C45: =8392352.01821476*110% -> 9231587.2 | D45: =8392352.01821476*110% -> 9231587.2 | E45: =8392352.01821476*110% -> 9231587.2 | F45: =8392352.01821476*120% -> 10070822 | G45: =8392352.01821476*120% -> 10070822 | H45: =8392352.01821476*120% -> 10070822 | I45: =8392352.01821476*120% -> 10070822 | J45: =8392352.01821476*120% -> 10070822 | K45: =8392352.01821476*150% -> 12588528 | L45: =8392352.01821476*150% -> 12588528 | M45: =8392352.01821476*150% -> 12588528 | N45: =SUM(B45:M45) -> 1.2504605e+08
A46: Administrative + Support staff | B46: =15530409.8544533*110% -> 17083451 | C46: =15530409.8544533*110% -> 17083451 | D46: =15530409.8544533*110% -> 17083451 | E46: =15530409.8544533*110% -> 17083451 | F46: =15530409.8544533*120% -> 18636492 | G46: =15530409.8544533*120% -> 18636492 | H46: =15530409.8544533*120% -> 18636492 | I46: =15530409.8544533*120% -> 18636492 | J46: =15530409.8544533*120% -> 18636492 | K46: =15530409.8544533*150% -> 23295615 | L46: =15530409.8544533*150% -> 23295615 | M46: =15530409.8544533*150% -> 23295615 | N46: =SUM(B46:M46) -> 2.3140311e+08
A47: Other payment(Consultancy fees) | B47: =2974718.79640678*110% -> 3272190.7 | C47: =2974718.79640678*110% -> 3272190.7 | D47: =2974718.79640678*110% -> 3272190.7 | E47: =2974718.79640678*110% -> 3272190.7 | F47: =2974718.79640678*120% -> 3569662.6 | G47: =2974718.79640678*120% -> 3569662.6 | H47: =2974718.79640678*120% -> 3569662.6 | I47: =2974718.79640678*120% -> 3569662.6 | J47: =2974718.79640678*120% -> 3569662.6 | K47: =2974718.79640678*150% -> 4462078.2 | L47: =2974718.79640678*150% -> 4462078.2 | M47: =2974718.79640678*150% -> 4462078.2 | N47: =SUM(B47:M47) -> 44323310
A48: CPA staff | B48: =1251849.27037465*110% -> 1377034.2 | C48: =1251849.27037465*110% -> 1377034.2 | D48: =1251849.27037465*110% -> 1377034.2 | E48: =1251849.27037465*110% -> 1377034.2 | F48: =1251849.27037465*120% -> 1502219.1 | G48: =1251849.27037465*120% -> 1502219.1 | H48: =1251849.27037465*120% -> 1502219.1 | I48: =1251849.27037465*120% -> 1502219.1 | J48: =1251849.27037465*120% -> 1502219.1 | K48: =1251849.27037465*150% -> 1877773.9 | L48: =1251849.27037465*150% -> 1877773.9 | M48: =1251849.27037465*150% -> 1877773.9 | N48: =SUM(B48:M48) -> 18652554
A49: Total Staff Cost | B49: =SUM(B44:B48) -> 68152887 | C49: =SUM(C44:C48) -> 68152887 | D49: =SUM(D44:D48) -> 68152887 | E49: =SUM(E44:E48) -> 68152887 | F49: =SUM(F44:F48) -> 74348604 | G49: =SUM(G44:G48) -> 74348604 | H49: =SUM(H44:H48) -> 74348604 | I49: =SUM(I44:I48) -> 74348604 | ... N49: =SUM(N44:N48) -> 9.2316183e+08
A50: Administrative Cost
A51: Communication | B51: 210000 | C51: 210000 | D51: 210000 | E51: 210000 | F51: 210000 | G51: 210000 | H51: 210000 | I51: 210000 | J51: 210000 | K51: 210000 | L51: 210000 | M51: 210000 | N51: =SUM(B51:M51) -> 2520000
A52: Security | B52: =720000+55000 -> 775000 | C52: =720000+55000 -> 775000 | D52: =720000+55000 -> 775000 | E52: =720000+55000 -> 775000 | F52: =720000+55000 -> 775000 | G52: =720000+55000 -> 775000 | H52: =720000+55000 -> 775000 | I52: =720000+55000 -> 775000 | ... M52: =720000+55000 -> 775000 | N52: =SUM(B52:M52) -> 9300000
A53: Water & Electricity | B53: 1342035 | C53: 1342035 | D53: 1342035 | E53: 1342035 | F53: 1342035 | G53: 1342035 | H53: 1342035 | I53: 1342035 | J53: 1342035 | K53: 1342035 | L53: 1342035 | M53: 1342035 | N53: =SUM(B53:M53) -> 16104420
A54: Medical insurance | B54: =N54/12 -> 1280603.4 | C54: 1280603.4 | D54: 1280603.4 | E54: 1280603.4 | F54: 1280603.4 | G54: 1280603.4 | H54: 1280603.4 | I54: 1280603.4 | J54: 1280603.4 | K54: 1280603.4 | L54: 1280603.4 | M54: 1280603.4 | N54: =(12234658+571376)*120% -> 15367241
A55: Rent ISR | B55: 800000 | C55: 800000 | D55: 800000 | E55: 800000 | F55: 800000 | G55: 800000 | H55: 800000 | I55: 800000 | J55: 800000 | K55: 800000 | L55: 800000 | M55: 800000 | N55: =SUM(B55:M55) -> 9600000
A56: Carburant/fuel | B56: 2020000 | C56: 2020000 | D56: 2020000 | E56: 2020000 | F56: 2020000 | G56: 2020000 | H56: 2020000 | I56: 2020000 | J56: 2020000 | K56: 2020000 | L56: 2020000 | M56: 2020000 | N56: =SUM(B56:M56) -> 24240000
A57: Supplies & office materials | B57: 3999855 | C57: 3999855 | D57: 3999855 | E57: 3999855 | F57: 3999855 | G57: 3999855 | H57: 3999855 | I57: 3999855 | J57: 3999855 | K57: 3999855 | L57: 3999855 | M57: 3999855 | N57: =SUM(B57:M57) -> 47998260
A58: Bank Charges | B58: =N58/12 -> 99705.6 | C58: 99705.6 | D58: 99705.6 | E58: 99705.6 | F58: 99705.6 | G58: 99705.6 | H58: 99705.6 | I58: 99705.6 | J58: 99705.6 | K58: 99705.6 | L58: 99705.6 | M58: 99705.6 | N58: =997056*120% -> 1196467.2
A59: Postal Charge | B59: =N59/12 -> 14640 | C59: 14640 | D59: 14640 | E59: 14640 | F59: 14640 | G59: 14640 | H59: 14640 | I59: 14640 | J59: 14640 | K59: 14640 | L59: 14640 | M59: 14640 | N59: =146400*120% -> 175680
A60: Internship Supervision fees | B60: 3294272.8 | C60: 3294272.8 | D60: 3294272.8 | E60: 3294272.8 | F60: 3294272.8 | G60: 3294272.8 | H60: 3294272.8 | I60: 3294272.8 | J60: 3294272.8 | K60: 3294272.8 | L60: 3294272.8 | M60: 3294272.8 | N60: 39531274
A61: Maintenaince and repair | B61: 1172273.3 | C61: 1172273.3 | D61: 1172273.3 | E61: 1172273.3 | F61: 1172273.3 | G61: 1172273.3 | H61: 1172273.3 | I61: 1172273.3 | J61: 1172273.3 | K61: 1172273.3 | L61: 1172273.3 | M61: 1172273.3 | N61: =SUM(B61:M61) -> 14067279
A62: Marketing and Publicity | B62: =500000+400000+50000 -> 950000 | C62: =500000+400000+50000 -> 950000 | D62: =500000+400000+50000 -> 950000 | E62: =500000+400000+50000 -> 950000 | F62: =500000+400000+50000 -> 950000 | G62: =500000+400000+50000 -> 950000 | H62: =500000+400000+50000 -> 950000 | I62: =500000+400000+50000 -> 950000 | ... M62: =500000+400000+50000 -> 950000 | N62: =SUM(B62:M62) -> 11400000
A63: Marketing Agents Expenses fee | B63: 1038333.3 | C63: 1038333.3 | D63: 1038333.3 | E63: 1038333.3 | F63: 1038333.3 | G63: 1038333.3 | H63: 1038333.3 | I63: 1038333.3 | J63: 1038333.3 | K63: 1038333.3 | L63: 1038333.3 | M63: 1038333.3 | N63: ='INCOME DETAILS'!X124 -> 17210000
A64: Graduation expenses | B64: =N64/12 -> 833333.33 | C64: 833333.33 | D64: 833333.33 | E64: 833333.33 | F64: 833333.33 | G64: 833333.33 | H64: 833333.33 | I64: 833333.33 | J64: 833333.33 | K64: 833333.33 | L64: 833333.33 | M64: 833333.33 | N64: 10000000
A65: Vehicle Insurance | B65: =N65/12 -> 229814.67 | C65: 229814.67 | D65: 229814.67 | E65: 229814.67 | F65: 229814.67 | G65: 229814.67 | H65: 229814.67 | I65: 229814.67 | J65: 229814.67 | K65: 229814.67 | L65: 229814.67 | M65: 229814.67 | N65: 2757776
A66: Building Insurance | B66: =N66/12 -> 195082.08 | C66: 195082.08 | D66: 195082.08 | E66: 195082.08 | F66: 195082.08 | G66: 195082.08 | H66: 195082.08 | I66: 195082.08 | J66: 195082.08 | K66: 195082.08 | L66: 195082.08 | M66: 195082.08 | N66: 2340985
A67: Employees Capacity Building | B67: =N67/12 -> 333333.33 | C67: 333333.33 | D67: 333333.33 | E67: 333333.33 | F67: 333333.33 | G67: 333333.33 | H67: 333333.33 | I67: 333333.33 | J67: 333333.33 | K67: 333333.33 | L67: 333333.33 | M67: 333333.33 | N67: 4000000
A68: Accueil et reception | B68: =N68/12 -> 410922.75 | C68: 410922.75 | D68: 410922.75 | E68: 410922.75 | F68: 410922.75 | G68: 410922.75 | H68: 410922.75 | I68: 410922.75 | J68: 410922.75 | K68: 410922.75 | L68: 410922.75 | M68: 410922.75 | N68: 4931073
A69: Mission Fees | B69: =N69/12 -> 486777.08 | C69: 486777.08 | D69: 486777.08 | E69: 486777.08 | F69: 486777.08 | G69: 486777.08 | H69: 486777.08 | I69: 486777.08 | J69: 486777.08 | K69: 486777.08 | L69: 486777.08 | M69: 486777.08 | N69: 5841325
A70: Contribution in other Organism | B70: =N70/12 -> 250000 | C70: 250000 | D70: 250000 | E70: 250000 | F70: 250000 | G70: 250000 | H70: 250000 | I70: 250000 | J70: 250000 | K70: 250000 | L70: 250000 | M70: 250000 | N70: 3000000
A71: External Audit fee | B71: =N71/12 -> 250000 | C71: 250000 | D71: 250000 | E71: 250000 | F71: 250000 | G71: 250000 | H71: 250000 | I71: 250000 | J71: 250000 | K71: 250000 | L71: 250000 | M71: 250000 | N71: 3000000
A72: Public Relation | B72: =N72/12 -> 416666.67 | C72: 416666.67 | D72: 416666.67 | E72: 416666.67 | F72: 416666.67 | G72: 416666.67 | H72: 416666.67 | I72: 416666.67 | J72: 416666.67 | K72: 416666.67 | L72: 416666.67 | M72: 416666.67 | N72: 5000000
A73: Kibungo L.Center rental cost. | B73: 400000 | C73: 400000 | D73: 400000 | E73: 400000 | F73: 400000 | G73: 400000 | H73: 400000 | I73: 400000 | J73: 400000 | K73: 400000 | L73: 400000 | M73: 400000 | N73: =SUM(B73:M73) -> 4800000
A74: Partnership fees | B74: 3024380 | C74: 3024380 | D74: 3024380 | E74: 3024380 | F74: 3024380 | G74: 3024380 | H74: 3024380 | I74: 3024380 | J74: 3024380 | K74: 3024380 | L74: 3024380 | M74: 3024380 | N74: =SUM(B74:M74) -> 36292560
A75: Unforseen expenses | B75: 5000000 | C75: 5000000 | D75: 5000000 | E75: 5000000 | F75: 5000000 | G75: 5000000 | H75: 5000000 | I75: 5000000 | J75: 5000000 | K75: 5000000 | L75: 5000000 | M75: 5000000 | N75: =SUM(B75:M75) -> 60000000
A76: Total Administrative Cost | B76: =SUM(B51:B75) -> 28827028 | C76: =SUM(C51:C75) -> 28827028 | D76: =SUM(D51:D75) -> 28827028 | E76: =SUM(E51:E75) -> 28827028 | F76: =SUM(F51:F75) -> 28827028 | G76: =SUM(G51:G75) -> 28827028 | H76: =SUM(H51:H75) -> 28827028 | I76: =SUM(I51:I75) -> 28827028 | ... N76: =SUM(N51:N75) -> 3.5067434e+08
A77: Academic cost
A78: Research | B78: 1250000 | C78: 1250000 | D78: 1250000 | E78: 1250000 | F78: 1250000 | G78: 1250000 | H78: 1250000 | I78: 1250000 | J78: 1250000 | K78: 1250000 | L78: 1250000 | M78: 1250000 | N78: 15000000
A79: Seminars and conferences | B79: 170000 | C79: 170000 | D79: 170000 | E79: 170000 | F79: 170000 | G79: 170000 | H79: 170000 | I79: 170000 | J79: 170000 | K79: 170000 | L79: 170000 | M79: 170000 | N79: =SUM(B79:M79) -> 2040000
A80: Laboratory Consumables | B80: 1080208.3 | C80: 1080208.3 | D80: 1080208.3 | E80: 1080208.3 | F80: 1080208.3 | G80: 1080208.3 | H80: 1080208.3 | I80: 1080208.3 | J80: 1080208.3 | K80: 1080208.3 | L80: 1080208.3 | M80: 1080208.3 | N80: 12962500
A81: Designing and launching new programs | B81: 1084000 | C81: 1084000 | D81: 1084000 | E81: 1084000 | F81: 1084000 | G81: 1084000 | H81: 1084000 | I81: 1084000 | J81: 1084000 | K81: 1084000 | L81: 1084000 | M81: 1084000 | N81: =SUM(B81:M81) -> 13008000
A82: Other academic activities (field visit,community services..) | B82: 300000 | C82: 300000 | D82: 300000 | E82: 300000 | F82: 300000 | G82: 300000 | H82: 300000 | I82: 300000 | J82: 300000 | K82: 300000 | L82: 300000 | M82: 300000 | N82: =SUM(B82:M82) -> 3600000
A83: Responsability allowance | B83: 3600000 | C83: 3600000 | D83: 3600000 | E83: 3600000 | F83: 3600000 | G83: 3600000 | H83: 3600000 | I83: 3600000 | J83: 3600000 | K83: 3600000 | L83: 3600000 | M83: 3600000 | N83: =SUM(B83:M83) -> 43200000
A84: Panel fees | B84: =N84/12 -> 758333.33 | C84: 758333.33 | D84: 758333.33 | E84: 758333.33 | F84: 758333.33 | G84: 758333.33 | H84: 758333.33 | I84: 758333.33 | J84: 758333.33 | K84: 758333.33 | L84: 758333.33 | M84: 758333.33 | N84: 9100000
A85: Total Academic Cost | B85: =SUM(B78:B84) -> 8242541.7 | C85: =SUM(C78:C84) -> 8242541.7 | D85: =SUM(D78:D84) -> 8242541.7 | E85: =SUM(E78:E84) -> 8242541.7 | F85: =SUM(F78:F84) -> 8242541.7 | G85: =SUM(G78:G84) -> 8242541.7 | H85: =SUM(H78:H84) -> 8242541.7 | I85: =SUM(I78:I84) -> 8242541.7 | ... N85: =SUM(N78:N84) -> 98910500
A86: ICT COST
A87: Subscription to anti plagiarism software | B87: =N87/12 -> 73333.333 | C87: 73333.333 | D87: 73333.333 | E87: 73333.333 | F87: 73333.333 | G87: 73333.333 | H87: 73333.333 | I87: 73333.333 | J87: 73333.333 | K87: 73333.333 | L87: 73333.333 | M87: 73333.333 | N87: 880000
A88: Kaspesky (Antivirus ) | B88: =N88/12 -> 125000 | C88: 125000 | D88: 125000 | E88: 125000 | F88: 125000 | G88: 125000 | H88: 125000 | I88: 125000 | J88: 125000 | K88: 125000 | L88: 125000 | M88: 125000 | N88: 1500000
A89: Maintenance of IT equipment | B89: 431112.5 | C89: 431112.5 | D89: 431112.5 | E89: 431112.5 | F89: 431112.5 | G89: 431112.5 | H89: 431112.5 | I89: 431112.5 | J89: 431112.5 | K89: 431112.5 | L89: 431112.5 | M89: 431112.5 | N89: 5173350
A90: Website hosting+Elearning platform hosting + MIS Hosting | B90: 250000 | C90: 250000 | D90: 250000 | E90: 250000 | F90: 250000 | G90: 250000 | H90: 250000 | I90: 250000 | J90: 250000 | K90: 250000 | L90: 250000 | M90: 250000 | N90: 5173350
A91: School gear fees | B91: 666166.67 | C91: 666166.67 | D91: 666166.67 | E91: 666166.67 | F91: 666166.67 | G91: 666166.67 | H91: 666166.67 | I91: 666166.67 | J91: 666166.67 | K91: 666166.67 | L91: 666166.67 | M91: 666166.67 | N91: =N11*2000 -> 9384000
A92: Supplying softwares(library& registry) | B92: =N92/12 -> 166666.67 | C92: 166666.67 | D92: 166666.67 | E92: 166666.67 | F92: 166666.67 | G92: 166666.67 | H92: 166666.67 | I92: 166666.67 | J92: 166666.67 | K92: 166666.67 | L92: 166666.67 | M92: 166666.67 | N92: 2000000
A93: Subsription to online meeting software like webex, Ms team, Zoom | B93: =N93/12 -> 166666.67 | C93: 83333.333 | D93: 83333.333 | E93: 83333.333 | F93: 83333.333 | G93: 83333.333 | H93: 83333.333 | I93: 83333.333 | J93: 83333.333 | K93: 83333.333 | L93: 83333.333 | M93: 83333.333 | N93: 2000000
A94: Configuration of CUR Server room | B94: =N94/12 -> 250000 | C94: 250000 | D94: 250000 | E94: 250000 | F94: 250000 | G94: 250000 | H94: 250000 | I94: 250000 | J94: 250000 | K94: 250000 | L94: 250000 | M94: 250000 | N94: 3000000
A95: Annual Internet connection subscriptionn:(Taba and Save) | B95: 1274400 | C95: 1274400 | D95: 1890528 | E95: 1890528 | F95: 1890528 | G95: 1890528 | H95: 1890528 | I95: 1890528 | J95: 1890528 | K95: 1890528 | L95: 1890528 | M95: 1890528 | N95: =SUM(B95:M95) -> 21454080
A96: Total ICT COST | B96: =SUM(B87:B95) -> 3403345.8 | C96: =SUM(C87:C95) -> 3320012.5 | D96: =SUM(D87:D95) -> 3936140.5 | E96: =SUM(E87:E95) -> 3936140.5 | F96: =SUM(F87:F95) -> 3936140.5 | G96: =SUM(G87:G95) -> 3936140.5 | H96: =SUM(H87:H95) -> 3936140.5 | I96: =SUM(I87:I95) -> 3936140.5 | ... N96: =SUM(N87:N95) -> 50564780
A97: Finance Cost
A98: Cogebanque loan Interest | B98: =N98/12 -> 6131602.8 | C98: 6131602.8 | D98: 6131602.8 | E98: 6131602.8 | F98: 6131602.8 | G98: 6131602.8 | H98: 6131602.8 | I98: 6131602.8 | J98: 6131602.8 | K98: 6131602.8 | L98: 6131602.8 | M98: 6131602.8 | N98: 73579234
A99: Missio Invest Interest | B99: =N99/12 -> 6663195 | C99: 6663195 | D99: 6663195 | E99: 6663195 | F99: 6663195 | G99: 6663195 | H99: 6663195 | I99: 6663195 | J99: 6663195 | K99: 6663195 | L99: 6663195 | M99: 6663195 | N99: 79958340
A100: Total finance cost | B100: =B98+B99 -> 12794798 | C100: =C98+C99 -> 12794798 | D100: =D98+D99 -> 12794798 | E100: =E98+E99 -> 12794798 | F100: =F98+F99 -> 12794798 | G100: =G98+G99 -> 12794798 | H100: =H98+H99 -> 12794798 | I100: =I98+I99 -> 12794798 | ... N100: =N98+N99 -> 153537574
A101: TOTAL OPERATING EXPENSES(B) | B101: =B100+B96+B85+B76+B49 -> 1.214206e+08 | C101: =C100+C96+C85+C76+C49 -> 1.2133727e+08 | D101: =D100+D96+D85+D76+D49 -> 1.219534e+08 | E101: =E100+E96+E85+E76+E49 -> 1.219534e+08 | F101: =F100+F96+F85+F76+F49 -> 1.2814911e+08 | G101: =G100+G96+G85+G76+G49 -> 1.2814911e+08 | H101: =H100+H96+H85+H76+H49 -> 1.2814911e+08 | I101: =I100+I96+I85+I76+I49 -> 1.2814911e+08 | ... N101: =N100+N96+N85+N76+N49 -> 1.576849e+09
A102: SURPLUS /DEFICIT FOR PERIOD(A-B) | B102: =B41-B101 -> 49423297 | C102: =C41-C101 -> 49506630 | D102: =D41-D101 -> 48890502 | E102: =E41-E101 -> 48890502 | F102: =F41-F101 -> 61202748 | G102: =G41-G101 -> 61202748 | H102: =H41-H101 -> 61202748 | I102: =I41-I101 -> 61202748 | ... N102: =N41-N101 -> 7.2922441e+08
A103: CASH FLOW
A104: CAPITAL EXPENDITURE
A105: Other Equipment | B105: =N105/12 -> 833333.33 | C105: 833333.33 | D105: 833333.33 | E105: 833333.33 | F105: 833333.33 | G105: 833333.33 | H105: 833333.33 | I105: 833333.33 | J105: 833333.33 | K105: 833333.33 | L105: 833333.33 | M105: 833333.33 | N105: 10000000
A106: Purchase of Additional books (For Masters program,and other bachelor program) | B106: =N106/12 -> 1666666.7 | C106: 1666666.7 | D106: 1666666.7 | E106: 1666666.7 | F106: 1666666.7 | G106: 1666666.7 | H106: 1666666.7 | I106: 1666666.7 | J106: 1666666.7 | K106: 1666666.7 | L106: 1666666.7 | M106: 1666666.7 | N106: 20000000
A107: Building & Rehabilitation | B107: =N107/12 -> 4166666.7 | C107: 4166666.7 | D107: 4166666.7 | E107: 4166666.7 | F107: 4166666.7 | G107: 4166666.7 | H107: 4166666.7 | I107: 4166666.7 | J107: 4166666.7 | K107: 4166666.7 | L107: 4166666.7 | M107: 4166666.7 | N107: 50000000
A108: 20% Security for Chancen student | B108: =N108/12 -> 9805883.1 | C108: 9805883.1 | D108: 9805883.1 | E108: 9805883.1 | F108: 9805883.1 | G108: 9805883.1 | H108: 9805883.1 | I108: 9805883.1 | J108: 9805883.1 | K108: 9805883.1 | L108: 9805883.1 | M108: 9805883.1 | N108: =N25*20%+40091131 -> 1.176706e+08
...

Sheet presentation to Mgr
A1: BUDGET FOR ACADEMIC YEAR 2025-2026
N3: Number of students | O3: % Increase
A4: Number of student at start of 2025-2026 | N4: 3442
A5: Number of student Budgeted at end of 2025-2026 | N5: 4800
A6: Increase in number of student at year end | N6: =N5-N4 -> 1358 | O6: =N6/N4 -> 0.39453806
B8: Financial Budget for Academic year 2025-2026
B9: September | C9: October | D9: November | E9: December | F9: January | G9: February | H9: March | I9: April | J9: May | K9: June | L9: July | M9: August | N9: GENERAL TOTAL
B10: TOTAL | C10: TOTAL | D10: TOTAL | E10: TOTAL | F10: TOTAL | G10: TOTAL | H10: TOTAL | I10: TOTAL | J10: TOTAL | K10: TOTAL | L10: TOTAL | M10: TOTAL | N10: TOTAL
A11: Budgeted Number of Students | N11: 4800
A12: Revenue
A13: Tuition Fees
A14: Faculty of Catechesis and Religious Sciences | B14: =N14/12 -> 5208333.3 | C14: 5208333.3 | D14: 5208333.3 | E14: 5208333.3 | F14: 5208333.3 | G14: 5208333.3 | H14: 5208333.3 | I14: 5208333.3 | J14: 5208333.3 | K14: 5208333.3 | L14: 5208333.3 | M14: 5208333.3 | N14: ='INCOME DETAILS'!AB104 -> 62500000
A15: Faculty of Business studies | B15: =N15/12 -> 14843750 | C15: 17343750 | D15: 17343750 | E15: 17343750 | F15: 17343750 | G15: 17343750 | H15: 17343750 | I15: 17343750 | J15: 17343750 | K15: 17343750 | L15: 17343750 | M15: 17343750 | N15: 178125000
A16: Faculty of Education -under graduates | B16: =N16/12 -> 38207083 | C16: 46540417 | D16: 46540417 | E16: 46540417 | F16: 46540417 | G16: 46540417 | H16: 46540417 | I16: 46540417 | J16: 46540417 | K16: 46540417 | L16: 46540417 | M16: 46540417 | N16: 458485000
A17: Faculty of Education -PGD- Taba campus-Kibungo Learning Center | B17: =N17/12 -> 2482666.7 | C17: 2482666.7 | D17: 2482666.7 | E17: 2482666.7 | F17: 2482666.7 | G17: 2482666.7 | H17: 2482666.7 | I17: 2482666.7 | J17: 2482666.7 | K17: 2482666.7 | L17: 2482666.7 | M17: 2482666.7 | N17: ='INCOME DETAILS'!AB117 -> 29792000
A18: Faculty of Health Science | B18: =N18/12 -> 13090000 | C18: 17256667 | D18: 17256667 | E18: 17256667 | F18: 17256667 | G18: 17256667 | H18: 17256667 | I18: 17256667 | J18: 17256667 | K18: 17256667 | L18: 17256667 | M18: 17256667 | N18: 157080000
A19: Faculty of Science and Technology | B19: =N19/12 -> 7187500 | C19: 7187500 | D19: 7187500 | E19: 7187500 | F19: 7187500 | G19: 7187500 | H19: 7187500 | I19: 7187500 | J19: 7187500 | K19: 7187500 | L19: 7187500 | M19: 7187500 | N19: ='INCOME DETAILS'!AB21 -> 86250000
A20: Faculty of Social Work | B20: =N20/12 -> 4114583.3 | C20: 4114583.3 | D20: 4114583.3 | E20: 4114583.3 | F20: 4114583.3 | G20: 4114583.3 | H20: 4114583.3 | I20: 4114583.3 | J20: 4114583.3 | K20: 4114583.3 | L20: 4114583.3 | M20: 4114583.3 | N20: ='INCOME DETAILS'!AB29 -> 49375000
A21: Expected New Masters Program fees | K21: =N21/3 -> 5000000 | L21: 5000000 | M21: 5000000 | N21: ='INCOME DETAILS'!AB120 -> 15000000
A22: Ministry of health sponsored student
A23: Existing Sponsored | B23: =N23/12 -> 23065417 | C23: 23065417 | D23: 23065417 | E23: 23065417 | F23: 23065417 | G23: 23065417 | H23: 23065417 | I23: 23065417 | J23: 23065417 | K23: 23065417 | L23: 23065417 | M23: 23065417 | N23: 276785000
A24: Chancen Student Tuition fees | B24: =N24/12 -> 23991444 | C24: 32324778 | D24: 32324778 | E24: 32324778 | F24: 32324778 | G24: 32324778 | H24: 32324778 | I24: 32324778 | J24: 32324778 | K24: 32324778 | L24: 32324778 | M24: 32324778 | N24: 2.8789733e+08
A25: YWCA | F25: =N25/9 -> 6007962.2 | G25: 6007962.2 | H25: 6007962.2 | I25: 6007962.2 | J25: 6007962.2 | K25: 6007962.2 | L25: 6007962.2 | M25: 6007962.2 | N25: ='INCOME DETAILS'!E140 -> 54071660
A26: Total Tuition fees | B26: =SUM(B14:B25) -> 1.3219078e+08 | C26: =SUM(C14:C25) -> 1.5552411e+08 | D26: =SUM(D14:D25) -> 1.5552411e+08 | E26: =SUM(E14:E25) -> 1.5552411e+08 | F26: =SUM(F14:F25) -> 1.6153207e+08 | G26: =SUM(G14:G25) -> 1.6153207e+08 | H26: =SUM(H14:H25) -> 1.6153207e+08 | I26: =SUM(I14:I25) -> 1.6153207e+08 | ... N26: =SUM(N14:N25) -> 1.655361e+09
A27: Application fees | B27: =N27/12 -> 795833.33 | C27: 795833.33 | D27: 795833.33 | E27: 795833.33 | F27: 795833.33 | G27: 795833.33 | H27: 795833.33 | I27: 795833.33 | J27: 795833.33 | K27: 795833.33 | L27: 795833.33 | M27: 795833.33 | N27: ='INCOME DETAILS'!AD121 -> 9550000
A28: Internship fees | B28: =N28/12 -> 4840000 | C28: 2340000 | D28: 2340000 | E28: 2340000 | F28: 2340000 | G28: 2340000 | H28: 2340000 | I28: 2340000 | J28: 2340000 | K28: 2340000 | L28: 2340000 | M28: 2340000 | N28: 58080000
A29: Research supervision fees | B29: =N29/12 -> 2225000 | C29: 2225000 | D29: 2225000 | E29: 2225000 | F29: 2225000 | G29: 2225000 | H29: 2225000 | I29: 2225000 | J29: 2225000 | K29: 2225000 | L29: 2225000 | M29: 2225000 | N29: ='INCOME DETAILS'!AF121 -> 26700000
A30: Graduation fees | J30: =N30 -> 13000000 | N30: =260*50000 -> 13000000
A31: Fines | B31: =N31/12 -> 50820 | C31: 50820 | D31: 50820 | E31: 50820 | F31: 50820 | G31: 50820 | H31: 50820 | I31: 50820 | J31: 50820 | K31: 50820 | L31: 50820 | M31: 50820 | N31: 609840
A32: Retake fees | B32: =N32/12 -> 33333.333 | C32: 33333.333 | D32: 33333.333 | E32: 33333.333 | F32: 33333.333 | G32: 33333.333 | H32: 33333.333 | I32: 33333.333 | J32: 33333.333 | K32: 33333.333 | L32: 33333.333 | M32: 33333.333 | N32: 400000
A33: Academic documents fees | B33: =N33/12 -> 232466.67 | C33: 232466.67 | D33: 232466.67 | E33: 232466.67 | F33: 232466.67 | G33: 232466.67 | H33: 232466.67 | I33: 232466.67 | J33: 232466.67 | K33: 232466.67 | L33: 232466.67 | M33: 232466.67 | N33: 2789600
A34: Total academic cost | B34: =SUM(B26:B33) -> 1.4036823e+08 | C34: =SUM(C26:C33) -> 1.6120156e+08 | D34: =SUM(D26:D33) -> 1.6120156e+08 | E34: =SUM(E26:E33) -> 1.6120156e+08 | F34: =SUM(F26:F33) -> 1.6720953e+08 | G34: =SUM(G26:G33) -> 1.6720953e+08 | H34: =SUM(H26:H33) -> 1.6720953e+08 | I34: =SUM(I26:I33) -> 1.6720953e+08 | ... N34: =SUM(N26:N33) -> 1.7664904e+09
A35: Other Income
A36: Accomodation fee | B36: =N36/12 -> 7480000 | C36: 1309000 | D36: 1309000 | E36: 1309000 | F36: 1309000 | G36: 1309000 | H36: 1309000 | I36: 1309000 | J36: 1309000 | K36: 1309000 | L36: 1309000 | M36: 1309000 | N36: =187*40000*12 -> 89760000
A37: Income From research and Consultancy | N37: 100000000
A38: Income from Agricultural | N38: =1089876503.9/5 -> 2.179753e+08
A39: Other Income(Different IURA Projects) | F39: =N39/8 -> 25000000 | G39: 25000000 | H39: 25000000 | I39: 25000000 | J39: 25000000 | K39: 25000000 | L39: 25000000 | M39: 25000000 | N39: 200000000
A40: Total Income | B40: =B36+B39 -> 7480000 | C40: =C36+C39 -> 1309000 | D40: =D36+D39 -> 1309000 | E40: =E36+E39 -> 1309000 | F40: =F36+F39 -> 26309000 | G40: =G36+G39 -> 26309000 | H40: =H36+H39 -> 26309000 | I40: =I36+I39 -> 26309000 | ... M40: =M36+M39 -> 26309000 | N40: =N36+N39+N37+N38 -> 6.077353e+08
A41: TOTAL REVENUE(A) | B41: =B40+B34 -> 1.4784823e+08 | C41: =C40+C34 -> 1.6251056e+08 | D41: =D40+D34 -> 1.6251056e+08 | E41: =E40+E34 -> 1.6251056e+08 | F41: =F40+F34 -> 1.9351853e+08 | G41: =G40+G34 -> 1.9351853e+08 | H41: =H40+H34 -> 1.9351853e+08 | I41: =I40+I34 -> 1.9351853e+08 | ... N41: =N40+N34 -> 2.3742257e+09
A42: OPERATING EXPENSES
A43: Staff Cost
A44: Full timeTeaching staff | B44: =33807840.0605505*110% -> 37188624 | C44: =33807840.0605505*110% -> 37188624 | D44: =33807840.0605505*110% -> 37188624 | E44: =33807840.0605505*110% -> 37188624 | F44: =33807840.0605505*120% -> 40569408 | G44: =33807840.0605505*120% -> 40569408 | H44: =33807840.0605505*120% -> 40569408 | I44: =33807840.0605505*120% -> 40569408 | J44: =33807840.0605505*120% -> 40569408 | K44: =33807840.0605505*150% -> 50711760 | L44: =33807840.0605505*150% -> 50711760 | M44: =33807840.0605505*150% -> 50711760 | N44: =SUM(B44:M44) -> 5.0373682e+08
A45: Part time teaching staff | B45: =8392352.01821476*110% -> 9231587.2 | C45: =8392352.01821476*110% -> 9231587.2 | D45: =8392352.01821476*110% -> 9231587.2 | E45: =8392352.01821476*110% -> 9231587.2 | F45: =8392352.01821476*120% -> 10070822 | G45: =8392352.01821476*120% -> 10070822 | H45: =8392352.01821476*120% -> 10070822 | I45: =8392352.01821476*120% -> 10070822 | J45: =8392352.01821476*120% -> 10070822 | K45: =8392352.01821476*150% -> 12588528 | L45: =8392352.01821476*150% -> 12588528 | M45: =8392352.01821476*150% -> 12588528 | N45: =SUM(B45:M45) -> 1.2504605e+08
A46: Administrative + Support staff | B46: =15530409.8544533*110% -> 17083451 | C46: =15530409.8544533*110% -> 17083451 | D46: =15530409.8544533*110% -> 17083451 | E46: =15530409.8544533*110% -> 17083451 | F46: =15530409.8544533*120% -> 18636492 | G46: =15530409.8544533*120% -> 18636492 | H46: =15530409.8544533*120% -> 18636492 | I46: =15530409.8544533*120% -> 18636492 | J46: =15530409.8544533*120% -> 18636492 | K46: =15530409.8544533*150% -> 23295615 | L46: =15530409.8544533*150% -> 23295615 | M46: =15530409.8544533*150% -> 23295615 | N46: =SUM(B46:M46) -> 2.3140311e+08
A47: Other payment(Consultancy fees) | B47: =2974718.79640678*110% -> 3272190.7 | C47: =2974718.79640678*110% -> 3272190.7 | D47: =2974718.79640678*110% -> 3272190.7 | E47: =2974718.79640678*110% -> 3272190.7 | F47: =2974718.79640678*120% -> 3569662.6 | G47: =2974718.79640678*120% -> 3569662.6 | H47: =2974718.79640678*120% -> 3569662.6 | I47: =2974718.79640678*120% -> 3569662.6 | J47: =2974718.79640678*120% -> 3569662.6 | K47: =2974718.79640678*150% -> 4462078.2 | L47: =2974718.79640678*150% -> 4462078.2 | M47: =2974718.79640678*150% -> 4462078.2 | N47: =SUM(B47:M47) -> 44323310
A48: CPA staff | B48: =1251849.27037465*110% -> 1377034.2 | C48: =1251849.27037465*110% -> 1377034.2 | D48: =1251849.27037465*110% -> 1377034.2 | E48: =1251849.27037465*110% -> 1377034.2 | F48: =1251849.27037465*120% -> 1502219.1 | G48: =1251849.27037465*120% -> 1502219.1 | H48: =1251849.27037465*120% -> 1502219.1 | I48: =1251849.27037465*120% -> 1502219.1 | J48: =1251849.27037465*120% -> 1502219.1 | K48: =1251849.27037465*150% -> 1877773.9 | L48: =1251849.27037465*150% -> 1877773.9 | M48: =1251849.27037465*150% -> 1877773.9 | N48: =SUM(B48:M48) -> 18652554
A49: Total Staff Cost | B49: =SUM(B44:B48) -> 68152887 | C49: =SUM(C44:C48) -> 68152887 | D49: =SUM(D44:D48) -> 68152887 | E49: =SUM(E44:E48) -> 68152887 | F49: =SUM(F44:F48) -> 74348604 | G49: =SUM(G44:G48) -> 74348604 | H49: =SUM(H44:H48) -> 74348604 | I49: =SUM(I44:I48) -> 74348604 | ... N49: =SUM(N44:N48) -> 9.2316183e+08
A50: Administrative Cost
A51: Communication | B51: 210000 | C51: 210000 | D51: 210000 | E51: 210000 | F51: 210000 | G51: 210000 | H51: 210000 | I51: 210000 | J51: 210000 | K51: 210000 | L51: 210000 | M51: 210000 | N51: =SUM(B51:M51) -> 2520000
A52: Hygiene and sanitation | B52: 1579180 | C52: 1579180 | D52: 1579180 | E52: 1579180 | F52: 1579180 | G52: 1579180 | H52: 1579180 | I52: 1579180 | J52: 1579180 | K52: 1579180 | L52: 1579180 | M52: 1579180 | N52: =SUM(B52:M52) -> 18950160
A53: Security | B53: =720000+55000 -> 775000 | C53: =720000+55000 -> 775000 | D53: =720000+55000 -> 775000 | E53: =720000+55000 -> 775000 | F53: =720000+55000 -> 775000 | G53: =720000+55000 -> 775000 | H53: =720000+55000 -> 775000 | I53: =720000+55000 -> 775000 | ... M53: =720000+55000 -> 775000 | N53: =SUM(B53:M53) -> 9300000
A54: Water & Electricity | B54: 1342035 | C54: 1342035 | D54: 1342035 | E54: 1342035 | F54: 1342035 | G54: 1342035 | H54: 1342035 | I54: 1342035 | J54: 1342035 | K54: 1342035 | L54: 1342035 | M54: 1342035 | N54: =SUM(B54:M54) -> 16104420
A55: Medical insurance | B55: =N55/12 -> 1280603.4 | C55: 1280603.4 | D55: 1280603.4 | E55: 1280603.4 | F55: 1280603.4 | G55: 1280603.4 | H55: 1280603.4 | I55: 1280603.4 | J55: 1280603.4 | K55: 1280603.4 | L55: 1280603.4 | M55: 1280603.4 | N55: =(12234658+571376)*120% -> 15367241
A56: Rent ISR | B56: 800000 | C56: 800000 | D56: 800000 | E56: 800000 | F56: 800000 | G56: 800000 | H56: 800000 | I56: 800000 | J56: 800000 | K56: 800000 | L56: 800000 | M56: 800000 | N56: =SUM(B56:M56) -> 9600000
A57: Carburant/fuel | B57: 2020000 | C57: 2020000 | D57: 2020000 | E57: 2020000 | F57: 2020000 | G57: 2020000 | H57: 2020000 | I57: 2020000 | J57: 2020000 | K57: 2020000 | L57: 2020000 | M57: 2020000 | N57: =SUM(B57:M57) -> 24240000
A58: Supplies & office materials | B58: 3999855 | C58: 3999855 | D58: 3999855 | E58: 3999855 | F58: 3999855 | G58: 3999855 | H58: 3999855 | I58: 3999855 | J58: 3999855 | K58: 3999855 | L58: 3999855 | M58: 3999855 | N58: =SUM(B58:M58) -> 47998260
A59: Bank Charges | B59: =N59/12 -> 99705.6 | C59: 99705.6 | D59: 99705.6 | E59: 99705.6 | F59: 99705.6 | G59: 99705.6 | H59: 99705.6 | I59: 99705.6 | J59: 99705.6 | K59: 99705.6 | L59: 99705.6 | M59: 99705.6 | N59: =997056*120% -> 1196467.2
A60: Postal Charge | B60: =N60/12 -> 14640 | C60: 14640 | D60: 14640 | E60: 14640 | F60: 14640 | G60: 14640 | H60: 14640 | I60: 14640 | J60: 14640 | K60: 14640 | L60: 14640 | M60: 14640 | N60: =146400*120% -> 175680
A61: Internship Supervision fees | B61: 3294272.8 | C61: 3294272.8 | D61: 3294272.8 | E61: 3294272.8 | F61: 3294272.8 | G61: 3294272.8 | H61: 3294272.8 | I61: 3294272.8 | J61: 3294272.8 | K61: 3294272.8 | L61: 3294272.8 | M61: 3294272.8 | N61: 39531274
A62: Maintenaince and repair | B62: 1172273.3 | C62: 1172273.3 | D62: 1172273.3 | E62: 1172273.3 | F62: 1172273.3 | G62: 1172273.3 | H62: 1172273.3 | I62: 1172273.3 | J62: 1172273.3 | K62: 1172273.3 | L62: 1172273.3 | M62: 1172273.3 | N62: =SUM(B62:M62) -> 14067279
A63: Marketing and Publicity | B63: =500000+400000+50000 -> 950000 | C63: =500000+400000+50000 -> 950000 | D63: =500000+400000+50000 -> 950000 | E63: =500000+400000+50000 -> 950000 | F63: =500000+400000+50000 -> 950000 | G63: =500000+400000+50000 -> 950000 | H63: =500000+400000+50000 -> 950000 | I63: =500000+400000+50000 -> 950000 | ... M63: =500000+400000+50000 -> 950000 | N63: =SUM(B63:M63) -> 11400000
A64: Marketing Agents Expenses fee | B64: 1038333.3 | C64: 1038333.3 | D64: 1038333.3 | E64: 1038333.3 | F64: 1038333.3 | G64: 1038333.3 | H64: 1038333.3 | I64: 1038333.3 | J64: 1038333.3 | K64: 1038333.3 | L64: 1038333.3 | M64: 1038333.3 | N64: ='INCOME DETAILS'!X124 -> 17210000
A65: Graduation expenses | B65: =N65/12 -> 833333.33 | C65: 833333.33 | D65: 833333.33 | E65: 833333.33 | F65: 833333.33 | G65: 833333.33 | H65: 833333.33 | I65: 833333.33 | J65: 833333.33 | K65: 833333.33 | L65: 833333.33 | M65: 833333.33 | N65: 10000000
A66: Vehicle Insurance | B66: =N66/12 -> 229814.67 | C66: 229814.67 | D66: 229814.67 | E66: 229814.67 | F66: 229814.67 | G66: 229814.67 | H66: 229814.67 | I66: 229814.67 | J66: 229814.67 | K66: 229814.67 | L66: 229814.67 | M66: 229814.67 | N66: 2757776
A67: Building Insurance | B67: =N67/12 -> 195082.08 | C67: 195082.08 | D67: 195082.08 | E67: 195082.08 | F67: 195082.08 | G67: 195082.08 | H67: 195082.08 | I67: 195082.08 | J67: 195082.08 | K67: 195082.08 | L67: 195082.08 | M67: 195082.08 | N67: 2340985
A68: Employees Capacity Building | B68: =N68/12 -> 333333.33 | C68: 333333.33 | D68: 333333.33 | E68: 333333.33 | F68: 333333.33 | G68: 333333.33 | H68: 333333.33 | I68: 333333.33 | J68: 333333.33 | K68: 333333.33 | L68: 333333.33 | M68: 333333.33 | N68: 4000000
A69: Accueil et reception | B69: =N69/12 -> 410922.75 | C69: 410922.75 | D69: 410922.75 | E69: 410922.75 | F69: 410922.75 | G69: 410922.75 | H69: 410922.75 | I69: 410922.75 | J69: 410922.75 | K69: 410922.75 | L69: 410922.75 | M69: 410922.75 | N69: 4931073
A70: Mission Fees | B70: =N70/12 -> 486777.08 | C70: 486777.08 | D70: 486777.08 | E70: 486777.08 | F70: 486777.08 | G70: 486777.08 | H70: 486777.08 | I70: 486777.08 | J70: 486777.08 | K70: 486777.08 | L70: 486777.08 | M70: 486777.08 | N70: 5841325
A71: Contribution in other Organism | B71: =N71/12 -> 250000 | C71: 250000 | D71: 250000 | E71: 250000 | F71: 250000 | G71: 250000 | H71: 250000 | I71: 250000 | J71: 250000 | K71: 250000 | L71: 250000 | M71: 250000 | N71: 3000000
A72: External Audit fee | B72: =N72/12 -> 250000 | C72: 250000 | D72: 250000 | E72: 250000 | F72: 250000 | G72: 250000 | H72: 250000 | I72: 250000 | J72: 250000 | K72: 250000 | L72: 250000 | M72: 250000 | N72: 3000000
A73: Public Relation | B73: =N73/12 -> 416666.67 | C73: 416666.67 | D73: 416666.67 | E73: 416666.67 | F73: 416666.67 | G73: 416666.67 | H73: 416666.67 | I73: 416666.67 | J73: 416666.67 | K73: 416666.67 | L73: 416666.67 | M73: 416666.67 | N73: 5000000
A74: Kibungo L.Center rental cost. | B74: 400000 | C74: 400000 | D74: 400000 | E74: 400000 | F74: 400000 | G74: 400000 | H74: 400000 | I74: 400000 | J74: 400000 | K74: 400000 | L74: 400000 | M74: 400000 | N74: =SUM(B74:M74) -> 4800000
A75: Partnership fees | B75: 3024380 | C75: 3024380 | D75: 3024380 | E75: 3024380 | F75: 3024380 | G75: 3024380 | H75: 3024380 | I75: 3024380 | J75: 3024380 | K75: 3024380 | L75: 3024380 | M75: 3024380 | N75: =SUM(B75:M75) -> 36292560
A76: Unforseen expenses | B76: 5000000 | C76: 5000000 | D76: 5000000 | E76: 5000000 | F76: 5000000 | G76: 5000000 | H76: 5000000 | I76: 5000000 | J76: 5000000 | K76: 5000000 | L76: 5000000 | M76: 5000000 | N76: 200000000
A77: Expense Self Financing | N77: 117975301
A78: Total Administrative Cost | B78: =SUM(B51:B76) -> 30406208 | C78: =SUM(C51:C76) -> 30406208 | D78: =SUM(D51:D76) -> 30406208 | E78: =SUM(E51:E76) -> 30406208 | F78: =SUM(F51:F76) -> 30406208 | G78: =SUM(G51:G76) -> 30406208 | H78: =SUM(H51:H76) -> 30406208 | I78: =SUM(I51:I76) -> 30406208 | ... M78: =SUM(M51:M76) -> 30406208 | N78: =SUM(N51:N77) -> 6.275998e+08
A79: Academic cost
A80: Research | B80: 1250000 | C80: 1250000 | D80: 1250000 | E80: 1250000 | F80: 1250000 | G80: 1250000 | H80: 1250000 | I80: 1250000 | J80: 1250000 | K80: 1250000 | L80: 1250000 | M80: 1250000 | N80: 15000000
A81: Seminars and conferences | B81: 170000 | C81: 170000 | D81: 170000 | E81: 170000 | F81: 170000 | G81: 170000 | H81: 170000 | I81: 170000 | J81: 170000 | K81: 170000 | L81: 170000 | M81: 170000 | N81: =SUM(B81:M81) -> 2040000
A82: Laboratory Consumables | B82: 1080208.3 | C82: 1080208.3 | D82: 1080208.3 | E82: 1080208.3 | F82: 1080208.3 | G82: 1080208.3 | H82: 1080208.3 | I82: 1080208.3 | J82: 1080208.3 | K82: 1080208.3 | L82: 1080208.3 | M82: 1080208.3 | N82: 12962500
A83: Designing and launching new programs | B83: 1084000 | C83: 1084000 | D83: 1084000 | E83: 1084000 | F83: 1084000 | G83: 1084000 | H83: 1084000 | I83: 1084000 | J83: 1084000 | K83: 1084000 | L83: 1084000 | M83: 1084000 | N83: =SUM(B83:M83) -> 13008000
A84: Other academic activities (field visit,community services..) | B84: 300000 | C84: 300000 | D84: 300000 | E84: 300000 | F84: 300000 | G84: 300000 | H84: 300000 | I84: 300000 | J84: 300000 | K84: 300000 | L84: 300000 | M84: 300000 | N84: =SUM(B84:M84) -> 3600000
A85: Responsability allowance | B85: 3600000 | C85: 3600000 | D85: 3600000 | E85: 3600000 | F85: 3600000 | G85: 3600000 | H85: 3600000 | I85: 3600000 | J85: 3600000 | K85: 3600000 | L85: 3600000 | M85: 3600000 | N85: =SUM(B85:M85) -> 43200000
A86: Panel fees | B86: =N86/12 -> 758333.33 | C86: 758333.33 | D86: 758333.33 | E86: 758333.33 | F86: 758333.33 | G86: 758333.33 | H86: 758333.33 | I86: 758333.33 | J86: 758333.33 | K86: 758333.33 | L86: 758333.33 | M86: 758333.33 | N86: 9100000
A87: Total Academic Cost | B87: =SUM(B80:B86) -> 8242541.7 | C87: =SUM(C80:C86) -> 8242541.7 | D87: =SUM(D80:D86) -> 8242541.7 | E87: =SUM(E80:E86) -> 8242541.7 | F87: =SUM(F80:F86) -> 8242541.7 | G87: =SUM(G80:G86) -> 8242541.7 | H87: =SUM(H80:H86) -> 8242541.7 | I87: =SUM(I80:I86) -> 8242541.7 | ... N87: =SUM(N80:N86) -> 98910500
A88: ICT COST
A89: Subscription to anti plagiarism software | B89: =N89/12 -> 73333.333 | C89: 73333.333 | D89: 73333.333 | E89: 73333.333 | F89: 73333.333 | G89: 73333.333 | H89: 73333.333 | I89: 73333.333 | J89: 73333.333 | K89: 73333.333 | L89: 73333.333 | M89: 73333.333 | N89: 880000
A90: Kaspesky (Antivirus ) | B90: =N90/12 -> 125000 | C90: 125000 | D90: 125000 | E90: 125000 | F90: 125000 | G90: 125000 | H90: 125000 | I90: 125000 | J90: 125000 | K90: 125000 | L90: 125000 | M90: 125000 | N90: 1500000
A91: Maintenance of IT equipment | B91: 431112.5 | C91: 431112.5 | D91: 431112.5 | E91: 431112.5 | F91: 431112.5 | G91: 431112.5 | H91: 431112.5 | I91: 431112.5 | J91: 431112.5 | K91: 431112.5 | L91: 431112.5 | M91: 431112.5 | N91: 5173350
A92: Website hosting+Elearning platform hosting + MIS Hosting | B92: 250000 | C92: 250000 | D92: 250000 | E92: 250000 | F92: 250000 | G92: 250000 | H92: 250000 | I92: 250000 | J92: 250000 | K92: 250000 | L92: 250000 | M92: 250000 | N92: 5173350
A93: School gear fees | B93: 666166.67 | C93: 666166.67 | D93: 666166.67 | E93: 666166.67 | F93: 666166.67 | G93: 666166.67 | H93: 666166.67 | I93: 666166.67 | J93: 666166.67 | K93: 666166.67 | L93: 666166.67 | M93: 666166.67 | N93: =N11*2000 -> 9600000
A94: Supplying softwares(library& registry) | B94: =N94/12 -> 166666.67 | C94: 166666.67 | D94: 166666.67 | E94: 166666.67 | F94: 166666.67 | G94: 166666.67 | H94: 166666.67 | I94: 166666.67 | J94: 166666.67 | K94: 166666.67 | L94: 166666.67 | M94: 166666.67 | N94: 2000000
A95: Subsription to online meeting software like webex, Ms team, Zoom | B95: =N95/12 -> 166666.67 | C95: 83333.333 | D95: 83333.333 | E95: 83333.333 | F95: 83333.333 | G95: 83333.333 | H95: 83333.333 | I95: 83333.333 | J95: 83333.333 | K95: 83333.333 | L95: 83333.333 | M95: 83333.333 | N95: 2000000
A96: Configuration of CUR Server room | B96: =N96/12 -> 250000 | C96: 250000 | D96: 250000 | E96: 250000 | F96: 250000 | G96: 250000 | H96: 250000 | I96: 250000 | J96: 250000 | K96: 250000 | L96: 250000 | M96: 250000 | N96: 3000000
A97: Annual Internet connection subscriptionn:(Taba and Save) | B97: 1274400 | C97: 1274400 | D97: 1890528 | E97: 1890528 | F97: 1890528 | G97: 1890528 | H97: 1890528 | I97: 1890528 | J97: 1890528 | K97: 1890528 | L97: 1890528 | M97: 1890528 | N97: =SUM(B97:M97) -> 21454080
A98: Total ICT COST | B98: =SUM(B89:B97) -> 3403345.8 | C98: =SUM(C89:C97) -> 3320012.5 | D98: =SUM(D89:D97) -> 3936140.5 | E98: =SUM(E89:E97) -> 3936140.5 | F98: =SUM(F89:F97) -> 3936140.5 | G98: =SUM(G89:G97) -> 3936140.5 | H98: =SUM(H89:H97) -> 3936140.5 | I98: =SUM(I89:I97) -> 3936140.5 | ... N98: =SUM(N89:N97) -> 50780780
A99: Finance Cost
A100: Cogebanque loan Interest | B100: =N100/12 -> 6131602.8 | C100: 6131602.8 | D100: 6131602.8 | E100: 6131602.8 | F100: 6131602.8 | G100: 6131602.8 | H100: 6131602.8 | I100: 6131602.8 | J100: 6131602.8 | K100: 6131602.8 | L100: 6131602.8 | M100: 6131602.8 | N100: 73579234
A101: Missio Invest Interest | B101: =N101/12 -> 6663195 | C101: 6663195 | D101: 6663195 | E101: 6663195 | F101: 6663195 | G101: 6663195 | H101: 6663195 | I101: 6663195 | J101: 6663195 | K101: 6663195 | L101: 6663195 | M101: 6663195 | N101: 79958340
A102: Total finance cost | B102: =B100+B101 -> 12794798 | C102: =C100+C101 -> 12794798 | D102: =D100+D101 -> 12794798 | E102: =E100+E101 -> 12794798 | F102: =F100+F101 -> 12794798 | G102: =G100+G101 -> 12794798 | H102: =H100+H101 -> 12794798 | I102: =I100+I101 -> 12794798 | ... N102: =N100+N101 -> 153537574
...

Sheet INCOME DETAILS
C1: Current Student | G1: Projected New student
G2: September 2025 Intake | J2: March 2026 Intake | M2: June 2026 Intake
C3: Day program | D3: Weekend Program | E3: Holiday Program | F3: Total Existing | G3: Day program | H3: Weekend Program | I3: Holiday Program | J3: Day program | K3: Weekend Program | L3: Holiday Program | M3: Day program | N3: Weekend Program | O3: Holiday Program | P3: Total Projected | Q3: Total Student Budgeted 2024-2025 | R3: Sponsored Student | AB3: Tuition fees | AC3: Registration fees+Technology fees | AD3: Application fees | AE3: Internship fees | AF3: Final project fees | AG3: Total
R4: Minisante | T4: Chancen | V4: YWCA | W4: Private student | X4: Existing private student | Y4: Projected Private
R5: Existing | S5: Projected | T5: Existing | U5: Projected | V5: Projected | Y5: Sept int | Z5: March In | AA5: June int
B6: 1.Faculty of science and technology
B7: 1.1 Department of computer science
B8: L8 S1&2 | C8: 60 | D8: 17 | F8: =SUM(C8:E8) -> 77 | G8: 10 | H8: 20 | I8: 0 | L8: 0 | O8: 0 | P8: =SUM(G8:O8) -> 30 | Q8: =F8+P8 -> 107 | T8: =21 -> 21 | U8: 50 | V8: 40 | W8: =Q8-SUM(R8:V8) -> -4 | X8: =F8-R8-T8 -> 56 | Z8: 10 | AB8: =((X8*375000)+(Y8*375000)+(Z8*250000)+(AA8*125000)) -> 23500000 | AC8: =W8*33000 -> -132000 | AD8: =W8*5000 -> -20000 | AG8: =SUM(AB8:AD8) -> 23348000
B9: L8 S3&4 | C9: 45 | D9: 23 | F9: =SUM(C9:E9) -> 68 | G9: 0 | H9: 0 | I9: 0 | J9: 0 | K9: 0 | L9: 0 | M9: 0 | N9: 0 | O9: 0 | P9: =SUM(G9:O9) -> 0 | Q9: =F9+P9 -> 68 | T9: 66 | W9: =Q9-SUM(R9:V9) -> 2 | X9: =F9-R9-T9 -> 2 | AG9: =SUM(AB9:AD9) -> 0
B10: L8 S5&6 | C10: 58 | D10: 9 | F10: =SUM(C10:E10) -> 67 | G10: 0 | H10: 10 | I10: 0 | J10: 0 | L10: 0 | M10: 0 | N10: 10 | O10: 0 | P10: =SUM(G10:O10) -> 20 | Q10: =F10+P10 -> 87 | W10: =Q10-SUM(R10:V10) -> 87 | X10: =F10-R10-T10 -> 67 | Z10: 10 | AA10: 10 | AB10: =((X10*375000)+(Y10*375000)+(Z10*250000)+(AA10*125000)) -> 28875000 | AC10: =W10*33000 -> 2871000 | AG10: =SUM(AB10:AD10) -> 31746000
B11: L8 S7&8 | C11: 6 | D11: 13 | F11: =SUM(C11:E11) -> 19 | G11: 0 | H11: 0 | I11: 0 | J11: 0 | K11: 0 | L11: 0 | M11: 0 | N11: 0 | O11: 0 | P11: =SUM(G11:O11) -> 0 | Q11: =F11+P11 -> 19 | W11: =Q11-SUM(R11:V11) -> 19 | X11: =F11-R11-T11 -> 19 | AB11: =((X11*375000)+(Y11*375000)+(Z11*250000)+(AA11*125000)) -> 7125000 | AC11: =W11*33000 -> 627000 | AE11: =W11*30000 -> 570000 | AF11: =W11*150000 -> 2850000 | AG11: =SUM(AB11:AD11) -> 7752000
B12: Graduands | F12: =SUM(C12:E12) -> 0 | G12: 0 | H12: 0 | I12: 0 | J12: 0 | K12: 0 | L12: 0 | M12: 0 | N12: 0 | O12: 0 | P12: =SUM(G12:O12) -> 0 | Q12: =F12+P12 -> 0 | X12: =F12-R12-T12 -> 0 | AB12: =((X12*375000)+(Y12*375000)+(Z12*250000)+(AA12*125000)) -> 0 | AC12: =W12*33000 -> 0
B13: Total Students in CS | C13: =SUM(C8:C12) -> 169 | D13: =SUM(D8:D12) -> 62 | F13: =SUM(F8:F12) -> 231 | G13: =SUM(G8:G12) -> 10 | H13: =SUM(H8:H12) -> 30 | I13: =SUM(I8:I12) -> 0 | J13: =SUM(J8:J12) -> 0 | K13: =SUM(K8:K12) -> 0 | L13: =SUM(L8:L12) -> 0 | M13: =SUM(M8:M12) -> 0 | ... AG13: =SUM(AG8:AG12) -> 62846000
B14: 1.2 Food processing Department
B15: L8 S1&2 | C15: 48 | D15: 0 | E15: 0 | F15: =SUM(C15:E15) -> 48 | G15: 40 | H15: 20 | I15: 0 | J15: 20 | K15: 20 | L15: 0 | P15: =SUM(G15:O15) -> 100 | Q15: =F15+P15 -> 148 | W15: =Q15-SUM(R15:V15) -> 148 | X15: =F15-R15-T15 -> 48 | AA15: 70 | AB15: =((X15*375000)+(Y15*375000)+(Z15*250000)+(AA15*125000)) -> 26750000 | AC15: =W15*33000 -> 4884000 | AD15: =W15*5000 -> 740000 | AG15: =SUM(AB15:AD15) -> 32374000
B16: L8 S3&4 | C16: 0 | D16: 0 | E16: 0 | F16: =SUM(C16:E16) -> 0 | G16: 0 | H16: 0 | I16: 0 | J16: 0 | K16: 0 | L16: 0 | M16: 0 | N16: 0 | O16: 0 | P16: =SUM(G16:O16) -> 0 | Q16: =F16+P16 -> 0 | W16: =Q16-SUM(R16:V16) -> 0 | X16: =F16-R16-T16 -> 0 | AC16: =W16*33000 -> 0 | AD16: =W16*5000 -> 0 | AE16: 0 | AF16: 0 | AG16: =SUM(AB16:AD16) -> 0
B17: L8 S5&6 | C17: 0 | D17: 0 | E17: 0 | F17: =SUM(C17:E17) -> 0 | G17: 0 | H17: 0 | I17: 0 | J17: 0 | K17: 0 | L17: 0 | M17: 0 | N17: 0 | O17: 0 | P17: =SUM(G17:O17) -> 0 | Q17: =F17+P17 -> 0 | W17: =Q17-SUM(R17:V17) -> 0 | X17: =F17-R17-T17 -> 0 | AC17: =W17*33000 -> 0 | AD17: =W17*5000 -> 0 | AE17: 0 | AF17: 0 | AG17: =SUM(AB17:AD17) -> 0
B18: L8 S7&8 | C18: 0 | D18: 0 | E18: 0 | F18: =SUM(C18:E18) -> 0 | G18: 0 | H18: 0 | I18: 0 | J18: 0 | K18: 0 | L18: 0 | M18: 0 | N18: 0 | O18: 0 | P18: =SUM(G18:O18) -> 0 | Q18: =F18+P18 -> 0 | W18: =Q18-SUM(R18:V18) -> 0 | X18: =F18-R18-T18 -> 0 | AC18: =W18*33000 -> 0 | AD18: =W18*5000 -> 0 | AE18: 0 | AF18: 0 | AG18: =SUM(AB18:AD18) -> 0
B19: Graduands | C19: 0 | D19: 0 | E19: 0 | F19: =SUM(C19:E19) -> 0 | G19: 0 | H19: 0 | I19: 0 | J19: 0 | K19: 0 | L19: 0 | M19: 0 | N19: 0 | O19: 0 | P19: =SUM(G19:O19) -> 0 | Q19: =F19+P19 -> 0 | W19: =Q19-SUM(R19:V19) -> 0 | X19: =F19-R19-T19 -> 0 | AC19: =W19*33000 -> 0 | AD19: =W19*5000 -> 0 | AE19: 0 | AF19: 0 | AG19: =SUM(AB19:AD19) -> 0
B20: Total Students in FP | C20: =SUM(C15:C19) -> 48 | D20: =SUM(D15:D19) -> 0 | E20: =SUM(E15:E19) -> 0 | F20: =SUM(F15:F19) -> 48 | G20: =SUM(G15:G19) -> 40 | H20: =SUM(H15:H19) -> 20 | I20: =SUM(I15:I19) -> 0 | J20: =SUM(J15:J19) -> 20 | ... AG20: =SUM(AG15:AG19) -> 32374000
B21: 1.Total Students in faculty of Science and technology | F21: =F13+F20 -> 279 | G21: =G13+G20 -> 50 | H21: =H13+H20 -> 50 | I21: =I13+I20 -> 0 | J21: =J13+J20 -> 20 | K21: =K13+K20 -> 20 | L21: =L13+L20 -> 0 | M21: =M13+M20 -> 0 | ... AG21: =AG13+AG20 -> 95220000
B22: 2.Faculty of social work | P22: =SUM(G22:O22) -> 0 | X22: =F22-R22-T22 -> 0
B23: L8 S1&2 | C23: 0 | F23: =SUM(C23:E23) -> 0 | H23: 10 | K23: 20 | N23: 10 | P23: =SUM(G23:O23) -> 40 | Q23: =F23+P23 -> 40 | W23: =Q23-SUM(R23:V23) -> 40 | X23: =F23-R23-T23 -> 0 | Y23: 10 | Z23: 20 | AA23: 10 | AB23: =((X23*375000)+(Y23*375000)+(Z23*250000)+(AA23*125000)) -> 10000000 | AC23: =W23*33000 -> 1320000 | AD23: =W23*5000 -> 200000 | AG23: =SUM(AB23:AD23) -> 11520000
B24: L8 S3&4 | C24: 0 | D24: 53 | E24: 0 | F24: =SUM(C24:E24) -> 53 | P24: =SUM(G24:O24) -> 0 | Q24: =F24+P24 -> 53 | W24: =Q24-SUM(R24:V24) -> 53 | X24: =F24-R24-T24 -> 53 | AB24: =((X24*375000)+(Y24*375000)+(Z24*250000)+(AA24*125000)) -> 19875000 | AC24: =W24*33000 -> 1749000 | AG24: =SUM(AB24:AD24) -> 21624000
B25: L8 S5&6 | C25: 0 | D25: 17 | E25: 0 | F25: =SUM(C25:E25) -> 17 | P25: =SUM(G25:O25) -> 0 | Q25: =F25+P25 -> 17 | W25: =Q25-SUM(R25:V25) -> 17 | X25: =F25-R25-T25 -> 17 | AB25: =((X25*375000)+(Y25*375000)+(Z25*250000)+(AA25*125000)) -> 6375000 | AC25: =W25*33000 -> 561000 | AG25: =SUM(AB25:AD25) -> 6936000
B26: L8 S7&8 | C26: 0 | D26: 21 | E26: 0 | F26: =SUM(C26:E26) -> 21 | P26: =SUM(G26:O26) -> 0 | Q26: =F26+P26 -> 21 | W26: =Q26-SUM(R26:V26) -> 21 | X26: =F26-R26-T26 -> 21 | AB26: =((X26*375000)+(Y26*375000)+(Z26*250000)+(AA26*125000)) -> 7875000 | AC26: =W26*33000 -> 693000 | AE26: =W26*30000 -> 630000 | AF26: =W26*150000 -> 3150000 | AG26: =SUM(AB26:AD26) -> 8568000
B27: Graduands | D27: 14 | E27: 0 | F27: =SUM(C27:E27) -> 14 | P27: =SUM(G27:O27) -> 0 | Q27: =F27+P27 -> 14 | W27: =Q27-SUM(R27:V27) -> 14 | X27: =F27-R27-T27 -> 14 | AB27: =((X27*375000)+(Y27*375000)+(Z27*250000)+(AA27*125000)) -> 5250000 | AC27: =W27*33000 -> 462000 | AG27: =SUM(AB27:AD27) -> 5712000
B28: Partime | C28: 0 | D28: 0 | E28: 0 | F28: =SUM(C28:E28) -> 0 | P28: =SUM(G28:O28) -> 0 | Q28: =F28+P28 -> 0 | W28: =Q28-SUM(R28:V28) -> 0 | X28: =F28-R28-T28 -> 0 | AB28: =((X28*375000)+(Y28*375000)+(Z28*250000)+(AA28*125000)) -> 0 | AC28: =W28*33000 -> 0 | AG28: =SUM(AB28:AD28) -> 0
B29: 2.Total students Faculty of social work | C29: 0 | D29: =SUM(D23:D28) -> 105 | F29: =SUM(F23:F28) -> 105 | G29: =SUM(G23:G28) -> 0 | H29: =SUM(H23:H28) -> 10 | I29: =SUM(I23:I28) -> 0 | J29: =SUM(J23:J28) -> 0 | K29: =SUM(K23:K28) -> 20 | L29: =SUM(L23:L28) -> 0 | M29: =SUM(M23:M28) -> 0 | ... AG29: =SUM(AG23:AG28) -> 54360000
B30: 3.Faculty of Education
B31: 3.1 Educational Management and planning | P31: =SUM(G31:O31) -> 0 | Q31: =F31+P31 -> 0 | X31: =F31-R31-T31 -> 0
B32: L8 S1&2 | C32: 1 | D32: 0 | F32: =SUM(C32:E32) -> 1 | P32: =SUM(G32:O32) -> 0 | Q32: =F32+P32 -> 1 | W32: =Q32-SUM(R32:V32) -> 1 | X32: =F32-R32-T32 -> 1 | AB32: =((X32*375000)+(Y32*375000)+(Z32*250000)+(AA32*125000)) -> 375000 | AC32: =W32*33000 -> 33000 | AD32: =W32*5000 -> 5000 | AG32: =SUM(AB32:AD32) -> 413000
B33: L8 S3&4 | C33: 0 | D33: 0 | F33: =SUM(C33:E33) -> 0 | P33: =SUM(G33:O33) -> 0 | Q33: =F33+P33 -> 0 | W33: =Q33-SUM(R33:V33) -> 0 | X33: =F33-R33-T33 -> 0 | AB33: =((X33*375000)+(Y33*375000)+(Z33*250000)+(AA33*125000)) -> 0 | AC33: =W33*33000 -> 0 | AG33: =SUM(AB33:AD33) -> 0
B34: L8 S5&6 | C34: 0 | D34: 0 | F34: =SUM(C34:E34) -> 0 | P34: =SUM(G34:O34) -> 0 | Q34: =F34+P34 -> 0 | W34: =Q34-SUM(R34:V34) -> 0 | X34: =F34-R34-T34 -> 0 | AB34: =((X34*375000)+(Y34*375000)+(Z34*250000)+(AA34*125000)) -> 0 | AC34: =W34*33000 -> 0 | AG34: =SUM(AB34:AD34) -> 0
B35: L8 S7&8 | C35: 0 | D35: 0 | F35: =SUM(C35:E35) -> 0 | P35: =SUM(G35:O35) -> 0 | Q35: =F35+P35 -> 0 | W35: =Q35-SUM(R35:V35) -> 0 | X35: =F35-R35-T35 -> 0 | AB35: =((X35*375000)+(Y35*375000)+(Z35*250000)+(AA35*125000)) -> 0 | AC35: =W35*33000 -> 0 | AE35: =W35*30000 -> 0 | AF35: =W35*150000 -> 0 | AG35: =SUM(AB35:AD35) -> 0
B36: Graduands | C36: 0 | D36: 0 | F36: =SUM(C36:E36) -> 0 | P36: =SUM(G36:O36) -> 0 | Q36: =F36+P36 -> 0 | W36: =Q36-SUM(R36:V36) -> 0 | X36: =F36-R36-T36 -> 0 | AB36: =((X36*375000)+(Y36*375000)+(Z36*250000)+(AA36*125000)) -> 0 | AC36: =W36*33000 -> 0 | AG36: =SUM(AB36:AD36) -> 0
B37: Partime | C37: 0 | D37: 0 | F37: =SUM(C37:E37) -> 0 | P37: =SUM(G37:O37) -> 0 | Q37: =F37+P37 -> 0 | W37: =Q37-SUM(R37:V37) -> 0 | X37: =F37-R37-T37 -> 0 | AB37: =((X37*375000)+(Y37*375000)+(Z37*250000)+(AA37*125000)) -> 0 | AC37: =W37*33000 -> 0 | AG37: =SUM(AB37:AD37) -> 0
B38: Total students | F38: =SUM(F32:F37) -> 1 | G38: =SUM(G32:G37) -> 0 | H38: =SUM(H32:H37) -> 0 | I38: =SUM(I32:I37) -> 0 | J38: =SUM(J32:J37) -> 0 | K38: =SUM(K32:K37) -> 0 | L38: =SUM(L32:L37) -> 0 | M38: =SUM(M32:M37) -> 0 | ... AG38: =SUM(AG32:AG37) -> 413000
B39: 3.2 Department of art and social science
B40: L8 S1&2 | C40: 94 | D40: 53 | E40: 86 | F40: =SUM(C40:E40) -> 233 | G40: 10 | H40: 20 | I40: 20 | J40: 10 | M40: 10 | N40: 20 | O40: 20 | P40: =SUM(G40:O40) -> 110 | Q40: =F40+P40 -> 343 | T40: 25 | W40: =Q40-SUM(R40:V40) -> 318 | X40: =F40-R40-T40 -> 208 | Y40: 90 | Z40: 70 | AA40: 90 | AB40: =(((E40*330000)+(I40*330000)+(L40*220000)+(O40*110000))+((C40-T40)*500000)+(D40*375000)+(G40*500000)+(H40*375000)+((J40-U40)*375000)+(K40*250000)+(M40*250000)+(N40*125000)) -> 112805000 | AC40: =W40*33000 -> 10494000 | AD40: =W40*5000 -> 1590000 | AG40: =SUM(AB40:AD40) -> 124889000
B41: L8 S3&4 | C41: 75 | D41: 39 | E41: 65 | F41: =SUM(C41:E41) -> 179 | G41: 0 | H41: 0 | I41: 0 | J41: 0 | K41: 0 | L41: 0 | M41: 0 | N41: 0 | O41: 0 | P41: =SUM(G41:O41) -> 0 | Q41: =F41+P41 -> 179 | W41: =Q41-SUM(R41:V41) -> 179 | X41: =F41-R41-T41 -> 179 | Y41: =W41-X41 -> 0 | AB41: =(((E41*330000)+(I41*330000)+(L41*220000)+(O41*110000))+((C41-T41)*500000)+(D41*375000)+(G41*500000)+(H41*375000)+((J41-U41)*375000)+(K41*250000)+(M41*250000)+(N41*125000)) -> 73575000 | AC41: =W41*33000 -> 5907000 | AG41: =SUM(AB41:AD41) -> 79482000
B42: L8 S5&6 | C42: 39 | D42: 12 | E42: 21 | F42: =SUM(C42:E42) -> 72 | G42: 0 | H42: 10 | I42: 20 | J42: 0 | K42: 10 | L42: 20 | M42: 0 | O42: 20 | P42: =SUM(G42:O42) -> 80 | Q42: =F42+P42 -> 152 | W42: =Q42-SUM(R42:V42) -> 152 | X42: =F42-R42-T42 -> 72 | Y42: 30 | Z42: 30 | AA42: 30 | AB42: =(((E42*330000)+(I42*330000)+(L42*220000)+(O42*110000))+((C42-T42)*500000)+(D42*375000)+(G42*500000)+(H42*375000)+((J42-U42)*375000)+(K42*250000)+(M42*250000)+(N42*125000)) -> 50380000 | AC42: =W42*33000 -> 5016000 | AD42: =(Y42+Z42+AA42)*5000 -> 450000 | AG42: =SUM(AB42:AD42) -> 55846000
B43: L8 S7&8 | D43: 16 | E43: 12 | F43: =SUM(C43:E43) -> 28 | G43: 0 | H43: 0 | I43: 0 | J43: 0 | K43: 0 | L43: 0 | M43: 0 | N43: 0 | O43: 0 | P43: =SUM(G43:O43) -> 0 | Q43: =F43+P43 -> 28 | W43: =Q43-SUM(R43:V43) -> 28 | X43: =F43-R43-T43 -> 28 | AB43: =(((E43*330000)+(I43*330000)+(L43*220000)+(O43*110000))+((C43-T43)*500000)+(D43*375000)+(G43*500000)+(H43*375000)+((J43-U43)*375000)+(K43*250000)+(M43*250000)+(N43*125000)) -> 9960000 | AC43: =W43*33000 -> 924000 | AE43: =W43*30000 -> 840000 | AG43: =SUM(AB43:AD43) -> 10884000
B44: Graduands | F44: =SUM(C44:E44) -> 0 | G44: 0 | H44: 0 | I44: 0 | J44: 0 | K44: 0 | L44: 0 | M44: 0 | N44: 0 | O44: 0 | P44: =SUM(G44:O44) -> 0 | Q44: =F44+P44 -> 0 | W44: =Q44-SUM(R44:V44) -> 0 | X44: =F44-R44-T44 -> 0 | AB44: =(((E44*330000)+(I44*330000)+(L44*220000)+(O44*110000))+((C44-T44)*500000)+(D44*375000)+(G44*500000)+(H44*375000)+((J44-U44)*375000)+(K44*250000)+(M44*250000)+(N44*125000)) -> 0 | AC44: =W44*33000 -> 0 | AF44: =W44*150000 -> 0 | AG44: =SUM(AB44:AD44) -> 0
B45: Partime | F45: =SUM(C45:E45) -> 0 | G45: 0 | H45: 0 | I45: 0 | J45: 0 | K45: 0 | L45: 0 | M45: 0 | N45: 0 | O45: 0 | P45: =SUM(G45:O45) -> 0 | Q45: =F45+P45 -> 0 | W45: =Q45-SUM(R45:V45) -> 0 | X45: =F45-R45-T45 -> 0 | AB45: =(((E45*330000)+(I45*330000)+(L45*220000)+(O45*110000))+((C45-T45)*500000)+(D45*375000)+(G45*500000)+(H45*375000)+((J45-U45)*375000)+(K45*250000)+(M45*250000)+(N45*125000)) -> 0 | AC45: =W45*33000 -> 0 | AG45: =SUM(AB45:AD45) -> 0
B46: Total students | C46: 136 | D46: 120 | F46: =SUM(F40:F45) -> 512 | G46: =SUM(G40:G45) -> 10 | H46: =SUM(H40:H45) -> 30 | I46: =SUM(I40:I45) -> 40 | J46: =SUM(J40:J45) -> 10 | K46: =SUM(K40:K45) -> 10 | L46: =SUM(L40:L45) -> 20 | M46: =SUM(M40:M45) -> 10 | ... AG46: =SUM(AG40:AG45) -> 271101000
B47: 3.3 Department of Science | X47: =F47-R47-T47 -> 0
B48: L8 S1&2 | C48: 189 | D48: 62 | E48: 211 | F48: =SUM(C48:E48) -> 462 | H48: 20 | I48: 40 | K48: 10 | N48: 20 | O48: 40 | P48: =SUM(G48:O48) -> 130 | Q48: =F48+P48 -> 592 | W48: =Q48-SUM(R48:V48) -> 592 | X48: =F48-R48-T48 -> 462 | Y48: 60 | Z48: 60 | AA48: 60 | AB48: =(((E48*330000)+(I48*330000)+(L48*220000)+(O48*110000))+((C48-T48)*500000)+(D48*375000)+(G48*500000)+(H48*375000)+((J48-U48)*375000)+(K48*250000)+(M48*250000)+(N48*125000)) -> 217480000 | AC48: =W48*33000 -> 19536000 | AD48: =W48*5000 -> 2960000 | AG48: =SUM(AB48:AD48) -> 239976000
B49: L8 S3&4 | C49: 139 | D49: 32 | E49: 128 | F49: =SUM(C49:E49) -> 299 | P49: =SUM(G49:O49) -> 0 | Q49: =F49+P49 -> 299 | T49: 112 | W49: =Q49-SUM(R49:V49) -> 187 | X49: =F49-R49-T49 -> 187 | AB49: =(((E49*330000)+(I49*330000)+(L49*220000)+(O49*110000))+((C49-T49)*500000)+(D49*375000)+(G49*500000)+(H49*375000)+((J49-U49)*375000)+(K49*250000)+(M49*250000)+(N49*125000)) -> 67740000 | AC49: =W49*33000 -> 6171000 | AG49: =SUM(AB49:AD49) -> 73911000
B50: L8 S5&6 | C50: 74 | D50: 27 | E50: 36 | F50: =SUM(C50:E50) -> 137 | H50: 10 | I50: 20 | K50: 15 | L50: 20 | N50: 20 | O50: 20 | P50: =SUM(G50:O50) -> 105 | Q50: =F50+P50 -> 242 | W50: =Q50-SUM(R50:V50) -> 242 | X50: =F50-R50-T50 -> 137 | Y50: 30 | Z50: 35 | AA50: 40 | AB50: =(((E50*330000)+(I50*330000)+(L50*220000)+(O50*110000))+((C50-T50)*500000)+(D50*375000)+(G50*500000)+(H50*375000)+((J50-U50)*375000)+(K50*250000)+(M50*250000)+(N50*125000)) -> 82205000 | AC50: =W50*33000 -> 7986000 | AD50: =(Y50+Z50+AA50)*5000 -> 525000 | AG50: =SUM(AB50:AD50) -> 90716000
B51: L8 S7&8 | C51: 3 | D51: 49 | E51: 73 | F51: =SUM(C51:E51) -> 125 | P51: =SUM(G51:O51) -> 0 | Q51: =F51+P51 -> 125 | W51: =Q51-SUM(R51:V51) -> 125 | X51: =F51-R51-T51 -> 125 | AB51: =(((E51*330000)+(I51*330000)+(L51*220000)+(O51*110000))+((C51-T51)*500000)+(D51*375000)+(G51*500000)+(H51*375000)+((J51-U51)*375000)+(K51*250000)+(M51*250000)+(N51*125000)) -> 43965000 | AC51: =W51*33000 -> 4125000 | AE51: =W51*30000 -> 3750000 | AG51: =SUM(AB51:AD51) -> 48090000
B52: Graduands | P52: =SUM(G52:O52) -> 0 | Q52: =F52+P52 -> 0 | W52: =Q52-SUM(R52:V52) -> 0 | X52: =F52-R52-T52 -> 0 | AB52: =(((E52*330000)+(I52*330000)+(L52*220000)+(O52*110000))+((C52-T52)*500000)+(D52*375000)+(G52*500000)+(H52*375000)+((J52-U52)*375000)+(K52*250000)+(M52*250000)+(N52*125000)) -> 0 | AC52: =W52*33000 -> 0 | AF52: =W52*150000 -> 0 | AG52: =SUM(AB52:AD52) -> 0
B53: Partime | F53: =SUM(C53:E53) -> 0 | P53: =SUM(G53:O53) -> 0 | Q53: =F53+P53 -> 0 | W53: =Q53-SUM(R53:V53) -> 0 | X53: =F53-R53-T53 -> 0 | AB53: =(((E53*330000)+(I53*330000)+(L53*220000)+(O53*110000))+((C53-T53)*500000)+(D53*375000)+(G53*500000)+(H53*375000)+((J53-U53)*375000)+(K53*250000)+(M53*250000)+(N53*125000)) -> 0 | AC53: =W53*33000 -> 0
B54: Total students | C54: 167 | D54: 186 | F54: =SUM(F48:F53) -> 1023 | G54: =SUM(G48:G53) -> 0 | H54: =SUM(H48:H53) -> 30 | I54: =SUM(I48:I53) -> 60 | J54: =SUM(J48:J53) -> 0 | K54: =SUM(K48:K53) -> 25 | L54: =SUM(L48:L53) -> 20 | M54: =SUM(M48:M53) -> 0 | ... AG54: =SUM(AG48:AG53) -> 452693000
B55: 3. Total students in faculty of Education | C55: =C54+C46+C38 -> 303 | D55: =D54+D46+D38 -> 306 | E55: =E54+E46+E38 -> 0 | F55: =F54+F46+F38 -> 1536 | G55: =G54+G46+G38 -> 10 | H55: =H54+H46+H38 -> 60 | I55: =I54+I46+I38 -> 100 | J55: =J54+J46+J38 -> 10 | ... AG55: =AG54+AG46+AG38 -> 724207000
B56: 4.Faculty of Health studies | X56: =W55-X55 -> 425
B57: 4.1 Department Biomedical Laboratory science
B58: L8 S1&2 | C58: 9 | D58: 0 | E58: 0 | F58: =SUM(C58:E58) -> 9 | H58: 0 | I58: 0 | J58: 15 | K58: 0 | L58: 0 | N58: 0 | O58: 0 | P58: =SUM(G58:O58) -> 15 | Q58: =F58+P58 -> 24 | R58: 14 | U58: 10 | V58: 5 | W58: =Q58-SUM(R58:V58) -> -5 | X58: =F58-R58-T58 -> -5 | AB58: =((X58*600000)+(Y58*600000)+(Z58*450000)+(AA58*300000)) -> -3000000 | AC58: =W58*33000 -> -165000 | AD58: =W58*5000 -> -25000 | AG58: =SUM(AB58:AD58) -> -3190000
B59: L8 S3&4 | C59: 21 | D59: 0 | E59: 0 | F59: =SUM(C59:E59) -> 21 | G59: 0 | H59: 0 | I59: 0 | J59: 0 | K59: 0 | L59: 0 | M59: 0 | N59: 0 | O59: 0 | P59: =SUM(G59:O59) -> 0 | Q59: =F59+P59 -> 21 | R59: 0 | W59: =Q59-SUM(R59:V59) -> 21 | X59: =F59-R59-T59 -> 21 | AB59: =((X59*600000)+(Y59*600000)+(Z59*450000)+(AA59*300000)) -> 12600000 | AC59: =W59*33000 -> 693000 | AE59: =(X59-Y59-Z59-AA59)*160000 -> 3360000 | AG59: =SUM(AB59:AD59) -> 13293000
B60: L8 S5&6 | C60: 9 | D60: 54 | E60: 0 | F60: =SUM(C60:E60) -> 63 | G60: 10 | H60: 0 | I60: 0 | K60: 0 | L60: 0 | M60: 20 | N60: 0 | O60: 0 | P60: =SUM(G60:O60) -> 30 | Q60: =F60+P60 -> 93 | R60: 0 | U60: 30 | W60: =Q60-SUM(R60:V60) -> 63 | X60: =F60-R60-T60 -> 63 | Y60: 0 | AA60: 0 | AB60: =((X60*600000)+(Y60*600000)+(Z60*450000)+(AA60*300000)) -> 37800000 | AC60: =W60*33000 -> 2079000 | AE60: =(X60-Y60-Z60-AA60)*160000 -> 10080000 | AG60: =SUM(AB60:AD60) -> 39879000
B61: L8 S7&8 | C61: 0 | D61: 0 | E61: 0 | F61: =SUM(C61:E61) -> 0 | G61: 0 | H61: 0 | I61: 0 | J61: 0 | K61: 0 | L61: 0 | M61: 0 | N61: 0 | O61: 0 | P61: =SUM(G61:O61) -> 0 | Q61: =F61+P61 -> 0 | R61: 0 | W61: =Q61-SUM(R61:V61) -> 0 | X61: =F61-R61-T61 -> 0 | AB61: =((X61*600000)+(Y61*600000)+(Z61*450000)+(AA61*300000)) -> 0 | AC61: =W61*33000 -> 0 | AE61: =(X61-Y61-Z61-AA61)*160000 -> 0 | AG61: =SUM(AB61:AD61) -> 0
B62: Graduands | D62: 70 | E62: 0 | F62: =SUM(C62:E62) -> 70 | G62: 0 | H62: 0 | I62: 0 | J62: 0 | K62: 0 | L62: 0 | M62: 0 | N62: 0 | O62: 0 | P62: =SUM(G62:O62) -> 0 | Q62: =F62+P62 -> 70 | X62: =F62-R62-T62 -> 70
B63: Total students in BLS | F63: =SUM(F58:F62) -> 163 | G63: =SUM(G58:G62) -> 10 | H63: =SUM(H58:H62) -> 0 | I63: =SUM(I58:I62) -> 0 | J63: =SUM(J58:J62) -> 15 | K63: =SUM(K58:K62) -> 0 | L63: =SUM(L58:L62) -> 0 | M63: =SUM(M58:M62) -> 20 | ... AG63: =SUM(AG58:AG62) -> 49982000
B64: 4.2 Public Health | P64: =SUM(G64:O64) -> 0 | Q64: =F64+P64 -> 0
B65: L8 S1&2 | D65: 8 | F65: =SUM(C65:E65) -> 8 | M65: 10 | P65: =SUM(G65:O65) -> 10 | Q65: =F65+P65 -> 18 | W65: =Q65-SUM(R65:V65) -> 18 | X65: =F65-R65-T65 -> 8 | Z65: 10 | AA65: 5 | AB65: =((X65*440000)+(Y65*440000)+(Z65*295000)+(AA65*150000)) -> 7220000 | AC65: =W65*33000 -> 594000 | AD65: =W65*5000 -> 90000 | AG65: =SUM(AB65:AD65) -> 7904000
B66: L8 S3&4 | F66: =SUM(C66:E66) -> 0 | P66: =SUM(G66:O66) -> 0 | Q66: =F66+P66 -> 0 | W66: =Q66-SUM(R66:V66) -> 0 | X66: =F66-R66-T66 -> 0 | AB66: =((X66*440000)+(Y66*440000)+(Z66*295000)+(AA66*150000)) -> 0 | AC66: =W66*33000 -> 0 | AG66: =SUM(AB66:AD66) -> 0
B67: L8 S5&6 | D67: 27 | F67: =SUM(C67:E67) -> 27 | J67: 20 | M67: 30 | P67: =SUM(G67:O67) -> 50 | Q67: =F67+P67 -> 77 | U67: 50 | W67: =Q67-SUM(R67:V67) -> 27 | X67: =F67-R67-T67 -> 27 | Z67: 0 | AA67: 0 | AB67: =((X67*440000)+(Y67*440000)+(Z67*295000)+(AA67*150000)) -> 11880000 | AC67: =W67*33000 -> 891000 | AD67: =(Y67+Z67+AA67)*5000 -> 0 | AG67: =SUM(AB67:AD67) -> 12771000
B68: L8 S7&8 | D68: 21 | F68: =SUM(C68:E68) -> 21 | P68: =SUM(G68:O68) -> 0 | Q68: =F68+P68 -> 21 | W68: =Q68-SUM(R68:V68) -> 21 | X68: =F68-R68-T68 -> 21 | AB68: =((X68*440000)+(Y68*440000)+(Z68*295000)+(AA68*150000)) -> 9240000 | AC68: =W68*33000 -> 693000 | AE68: =W68*30000 -> 630000 | AF68: =W68*150000 -> 3150000 | AG68: =SUM(AB68:AD68) -> 9933000
B69: Graduands | F69: =SUM(C69:E69) -> 0 | P69: =SUM(G69:O69) -> 0 | Q69: =F69+P69 -> 0 | W69: =Q69-SUM(R69:V69) -> 0 | X69: =F69-R69-T69 -> 0 | AB69: =((X69*440000)+(Y69*440000)+(Z69*295000)+(AA69*150000)) -> 0 | AC69: =W69*33000 -> 0 | AE69: =W69*30000 -> 0 | AF69: =W69*150000 -> 0 | AG69: =SUM(AB69:AD69) -> 0
B70: Partime | F70: =SUM(C70:E70) -> 0 | P70: =SUM(G70:O70) -> 0 | Q70: =F70+P70 -> 0 | W70: =Q70-SUM(R70:V70) -> 0 | X70: =F70-R70-T70 -> 0 | AB70: =((X70*440000)+(Y70*440000)+(Z70*295000)+(AA70*150000)) -> 0
B71: Total students | C71: =SUM(C65:C70) -> 0 | D71: =SUM(D65:D70) -> 56 | F71: =SUM(F65:F70) -> 56 | G71: =SUM(G65:G70) -> 0 | H71: =SUM(H65:H70) -> 0 | I71: =SUM(I65:I70) -> 0 | J71: =SUM(J65:J70) -> 20 | K71: =SUM(K65:K70) -> 0 | L71: =SUM(L65:L70) -> 0 | M71: =SUM(M65:M70) -> 40 | ... AG71: =SUM(AG65:AG70) -> 30608000
B72: 4.3 Human Nutrition | X72: =F72-R72-T72 -> 0
B73: L8 S1&2 | F73: =SUM(C73:E73) -> 0 | M73: 10 | P73: =SUM(G73:O73) -> 10 | Q73: =F73+P73 -> 10 | U73: 10 | V73: 0 | W73: =Q73-SUM(R73:V73) -> 0 | X73: =F73-R73-T73 -> 0 | AA73: 0 | AB73: =((X73*500000)+(Y73*500000)+(Z73*340000)+(AA73*170000)) -> 0 | AC73: =W73*33000 -> 0 | AD73: =W73*5000 -> 0 | AG73: =SUM(AB73:AD73) -> 0
B74: L8 S3&4 | F74: =SUM(C74:E74) -> 0 | P74: =SUM(G74:O74) -> 0 | Q74: =F74+P74 -> 0 | R74: 5 | W74: =Q74-SUM(R74:V74) -> -5 | X74: =F74-R74-T74 -> -5 | AB74: =((X74*500000)+(Y74*500000)+(Z74*340000)+(AA74*170000)) -> -2500000 | AC74: =W74*33000 -> -165000 | AG74: =SUM(AB74:AD74) -> -2665000
B75: L8 S5&6 | C75: 5 | D75: 9 | F75: =SUM(C75:E75) -> 14 | M75: 0 | P75: =SUM(G75:O75) -> 0 | Q75: =F75+P75 -> 14 | U75: 20 | W75: =Q75-SUM(R75:V75) -> -6 | X75: =F75-R75-T75 -> 14 | AA75: 0 | AB75: =((X75*500000)+(Y75*500000)+(Z75*340000)+(AA75*170000)) -> 7000000 | AC75: =W75*33000 -> -198000 | AD75: =(Y75+Z75+AA75)*5000 -> 0 | AG75: =SUM(AB75:AD75) -> 6802000
B76: L8 S7&8 | F76: =SUM(C76:E76) -> 0 | P76: =SUM(G76:O76) -> 0 | Q76: =F76+P76 -> 0 | W76: =Q76-SUM(R76:V76) -> 0 | X76: =F76-R76-T76 -> 0 | AB76: =((X76*500000)+(Y76*500000)+(Z76*340000)+(AA76*170000)) -> 0 | AC76: =W76*33000 -> 0 | AE76: =W76*30000 -> 0 | AF76: =W76*150000 -> 0 | AG76: =SUM(AB76:AD76) -> 0
B77: Graduands | F77: =SUM(C77:E77) -> 0 | P77: =SUM(G77:O77) -> 0 | Q77: =F77+P77 -> 0 | W77: =Q77-SUM(R77:V77) -> 0 | X77: =F77-R77-T77 -> 0 | AB77: =((X77*500000)+(Y77*500000)+(Z77*340000)+(AA77*170000)) -> 0 | AC77: =W77*33000 -> 0 | AG77: =SUM(AB77:AD77) -> 0
B78: Partime | F78: =SUM(C78:E78) -> 0 | P78: =SUM(G78:O78) -> 0 | Q78: =F78+P78 -> 0 | W78: =Q78-SUM(R78:V78) -> 0 | X78: =F78-R78-T78 -> 0
B79: Total students | C79: =SUM(C73:C78) -> 5 | D79: =SUM(D73:D78) -> 9 | F79: =SUM(F73:F78) -> 14 | G79: =SUM(G73:G78) -> 0 | H79: =SUM(H73:H78) -> 0 | I79: =SUM(I73:I78) -> 0 | J79: =SUM(J73:J78) -> 0 | K79: =SUM(K73:K78) -> 0 | L79: =SUM(L73:L78) -> 0 | M79: =SUM(M73:M78) -> 10 | ... AG79: =SUM(AG73:AG78) -> 4137000
B80: 4.4 Nursing
B81: L8 S1&2 | C81: =8+44+4 -> 56 | F81: =SUM(C81:E81) -> 56 | J81: 60 | M81: 30 | P81: =SUM(G81:O81) -> 90 | Q81: =F81+P81 -> 146 | R81: 81 | S81: 50 | U81: 20 | W81: =Q81-SUM(R81:V81) -> -5 | X81: =F81-R81-T81 -> -25 | AA81: 0 | AB81: =((X81*800000)+(Y81*800000)+(Z81*600000)+(AA81*400000)) -> -20000000 | AC81: =W81*33000 -> -165000 | AD81: =W81*5000 -> -25000 | AG81: =SUM(AB81:AD81) -> -20190000
B82: L8 S3&4 | C82: =2+40+2+41 -> 85 | F82: =SUM(C82:E82) -> 85 | P82: =SUM(G82:O82) -> 0 | Q82: =F82+P82 -> 85 | W82: =Q82-SUM(R82:V82) -> 85 | X82: =F82-R82-T82 -> 85 | AB82: =((X82*800000)+(Y82*800000)+(Z82*600000)+(AA82*400000)) -> 68000000 | AC82: =W82*33000 -> 2805000 | AD82: =W82*5000 -> 425000 | AG82: =SUM(AB82:AD82) -> 71230000
B83: L8 S5&6 | F83: =SUM(C83:E83) -> 0 | P83: =SUM(G83:O83) -> 0 | Q83: =F83+P83 -> 0 | W83: =Q83-SUM(R83:V83) -> 0 | X83: =F83-R83-T83 -> 0 | AB83: =((X83*800000)+(Y83*800000)+(Z83*600000)+(AA83*400000)) -> 0 | AC83: =W83*33000 -> 0 | AD83: =(Y83+Z83+AA83)*5000 -> 0 | AG83: =SUM(AB83:AD83) -> 0
B84: L8 S7&8 | F84: =SUM(C84:E84) -> 0 | P84: =SUM(G84:O84) -> 0 | Q84: =F84+P84 -> 0 | W84: =Q84-SUM(R84:V84) -> 0 | X84: =F84-R84-T84 -> 0 | AB84: =((X84*800000)+(Y84*800000)+(Z84*600000)+(AA84*400000)) -> 0 | AC84: =W84*33000 -> 0 | AG84: =SUM(AB84:AD84) -> 0
B85: Graduands | F85: =SUM(C85:E85) -> 0 | P85: =SUM(G85:O85) -> 0 | Q85: =F85+P85 -> 0 | W85: =Q85-SUM(R85:V85) -> 0 | X85: =F85-R85-T85 -> 0 | AB85: =((X85*800000)+(Y85*800000)+(Z85*600000)+(AA85*400000)) -> 0 | AC85: =W85*33000 -> 0 | AE85: =W85*30000 -> 0 | AF85: =W85*150000 -> 0 | AG85: =SUM(AB85:AD85) -> 0
B86: Partime | F86: =SUM(C86:E86) -> 0 | P86: =SUM(G86:O86) -> 0 | Q86: =F86+P86 -> 0 | W86: =Q86-SUM(R86:V86) -> 0 | X86: =F86-R86-T86 -> 0
B87: Total students | C87: =SUM(C81:C86) -> 141 | D87: =SUM(D81:D86) -> 0 | F87: =SUM(F81:F86) -> 141 | G87: =SUM(G81:G86) -> 0 | H87: =SUM(H81:H86) -> 0 | I87: =SUM(I81:I86) -> 0 | J87: =SUM(J81:J86) -> 60 | K87: =SUM(K81:K86) -> 0 | L87: =SUM(L81:L86) -> 0 | M87: =SUM(M81:M86) -> 30 | ... AG87: =SUM(AG81:AG86) -> 51040000
B88: 4.5 Midwifery
B89: L8 S1&2 | C89: 98 | F89: =SUM(C89:E89) -> 98 | J89: =60+10 -> 70 | M89: 20 | P89: =SUM(G89:O89) -> 90 | Q89: =F89+P89 -> 188 | R89: 200 | S89: 100 | U89: 40 | W89: =Q89-SUM(R89:V89) -> -152 | X89: =F89-R89-T89 -> -102 | AB89: =((X89*720000)+(Y89*720000)+(Z89*540000)+(AA89*360000)) -> -73440000 | AC89: =W89*33000 -> -5016000 | AG89: =SUM(AB89:AD89) -> -78456000
B90: L8 S3&4 | C90: =99+100 -> 199 | F90: =SUM(C90:E90) -> 199 | P90: =SUM(G90:O90) -> 0 | Q90: =F90+P90 -> 199 | W90: =Q90-SUM(R90:V90) -> 199 | X90: =F90-R90-T90 -> 199 | AB90: =((X90*720000)+(Y90*720000)+(Z90*540000)+(AA90*360000)) -> 143280000 | AC90: =W90*33000 -> 6567000 | AG90: =SUM(AB90:AD90) -> 149847000
B91: L8 S5&6 | F91: =SUM(C91:E91) -> 0 | P91: =SUM(G91:O91) -> 0 | Q91: =F91+P91 -> 0 | W91: =Q91-SUM(R91:V91) -> 0 | X91: =F91-R91-T91 -> 0 | Z91: 10 | AA91: 10 | AB91: =((X91*720000)+(Y91*720000)+(Z91*540000)+(AA91*360000)) -> 9000000 | AC91: =W91*33000 -> 0 | AD91: =(Y91+Z91+AA91)*5000 -> 100000 | AG91: =SUM(AB91:AD91) -> 9100000
B92: L8 S7&8 | F92: =SUM(C92:E92) -> 0 | P92: =SUM(G92:O92) -> 0 | Q92: =F92+P92 -> 0 | W92: =Q92-SUM(R92:V92) -> 0 | X92: =F92-R92-T92 -> 0 | AB92: =((X92*720000)+(Y92*720000)+(Z92*540000)+(AA92*360000)) -> 0 | AC92: =W92*33000 -> 0 | AG92: =SUM(AB92:AD92) -> 0
B93: Graduands | F93: =SUM(C93:E93) -> 0 | P93: =SUM(G93:O93) -> 0 | Q93: =F93+P93 -> 0 | W93: =Q93-SUM(R93:V93) -> 0 | X93: =F93-R93-T93 -> 0 | AB93: =((X93*720000)+(Y93*720000)+(Z93*540000)+(AA93*360000)) -> 0 | AC93: =W93*33000 -> 0 | AE93: =W93*30000 -> 0 | AF93: =W93*150000 -> 0 | AG93: =SUM(AB93:AD93) -> 0
B94: Partime | F94: =SUM(C94:E94) -> 0 | P94: =SUM(G94:O94) -> 0 | Q94: =F94+P94 -> 0 | W94: =Q94-SUM(R94:V94) -> 0 | X94: =F94-R94-T94 -> 0 | AB94: =((X94*720000)+(Y94*720000)+(Z94*540000)+(AA94*360000)) -> 0 | AC94: =W94*33000 -> 0 | AG94: =SUM(AB94:AD94) -> 0
B95: Total students | C95: =SUM(C89:C94) -> 297 | D95: =SUM(D89:D94) -> 0 | F95: =SUM(F89:F94) -> 297 | G95: =SUM(G89:G94) -> 0 | H95: =SUM(H89:H94) -> 0 | I95: =SUM(I89:I94) -> 0 | J95: =SUM(J89:J94) -> 70 | K95: =SUM(K89:K94) -> 0 | L95: =SUM(L89:L94) -> 0 | M95: =SUM(M89:M94) -> 20 | ... AG95: =SUM(AG89:AG94) -> 80491000
B96: 4. Total Student in faculty of Health sciences | F96: =F95+F87+F79+F71+F63 -> 671 | G96: =G95+G87+G79+G71+G63 -> 10 | H96: =H95+H87+H79+H71+H63 -> 0 | I96: =I95+I87+I79+I71+I63 -> 0 | J96: =J95+J87+J79+J71+J63 -> 165 | K96: =K95+K87+K79+K71+K63 -> 0 | L96: =L95+L87+L79+L71+L63 -> 0 | M96: =M95+M87+M79+M71+M63 -> 120 | ... AG96: =AG95+AG87+AG79+AG71+AG63 -> 216258000
B97: 5. Faculty of Catechesis | X97: =F97-R97-T97 -> 0
B98: L8 S1&2 | D98: 0 | F98: =SUM(C98:E98) -> 0 | J98: 20 | M98: 20 | P98: =SUM(G98:O98) -> 40 | Q98: =F98+P98 -> 40 | W98: =Q98-SUM(R98:V98) -> 40 | X98: =F98-R98-T98 -> 0 | Z98: 20 | AA98: 20 | AB98: =((X98*500000)+(Y98*500000)+(Z98*375000)+(AA98*250000)) -> 12500000 | AC98: =W98*33000 -> 1320000 | AD98: =W98*5000 -> 200000 | AG98: =SUM(AB98:AD98) -> 14020000
B99: L8 S3&4 | C99: =56+14 -> 70 | D99: 0 | F99: =SUM(C99:E99) -> 70 | P99: =SUM(G99:O99) -> 0 | Q99: =F99+P99 -> 70 | W99: =Q99-SUM(R99:V99) -> 70 | X99: =F99-R99-T99 -> 70 | AB99: =((X99*500000)+(Y99*500000)+(Z99*375000)+(AA99*250000)) -> 35000000 | AC99: =W99*33000 -> 2310000 | AG99: =SUM(AB99:AD99) -> 37310000
B100: L8 S5&6 | D100: 0 | F100: =SUM(C100:E100) -> 0 | P100: =SUM(G100:O100) -> 0 | Q100: =F100+P100 -> 0 | W100: =Q100-SUM(R100:V100) -> 0 | X100: =F100-R100-T100 -> 0 | AB100: =((X100*500000)+(Y100*500000)+(Z100*375000)+(AA100*250000)) -> 0 | AC100: =W100*33000 -> 0 | AD100: =(Y100+Z100+AA100)*5000 -> 0 | AG100: =SUM(AB100:AD100) -> 0
...

Sheet Sheet2
A1: FHS | B1: 1300
A2: FED | B2: 2500
A3: FST | B3: 440
A4: FCRS | B4: 150
A5: FSW | B5: 160
A6: FBS | B6: 1100
A7: Post graduate studies | B7: 100
B8: =SUM(B1:B7) -> 5750
B9: 3442 | C9: =B8-B9 -> 2308 | D9: 819 | E9: =D9/C9 -> 0.35485269

Sheet DETAILED Number of students
C2: L8 S1&2 | D2: L8 S3&4 | E2: L8 S5&6 | F2: L8 S7&8 | G2: L9 | H2: Graduands | I2: Partime | J2: Total students
A3: 1.Faculty of science and technology
A5: Department Biomedical Laboratory science | B5: Day program | C5: 22 | D5: 26 | E5: 76 | F5: 18 | I5: 0 | J5: =SUM(C5:I5) -> 142
B6: Weekend Program | C6: 0 | D6: 0 | E6: 0 | F6: 0 | I6: 0 | J6: =SUM(C6:I6) -> 0
A7: Department of computer science | B7: Day program | C7: =35+4 -> 39 | D7: 63 | E7: 8 | F7: 17 | J7: =SUM(C7:I7) -> 127
B8: Weekend Program | C8: 23 | E8: 20 | F8: 19 | J8: =SUM(C8:I8) -> 62
J9: =SUM(J5:J8) -> 331
A10: 2.Faculty of social work | B10: Day program | C10: 0 | D10: 0 | E10: 0 | F10: 0 | I10: 0 | J10: 0
B11: Weekend Program | C11: 34 | D11: 0 | E11: 14 | F11: 14 | I11: 0 | J11: =SUM(C11:I11) -> 62 | K11: =J11-'INCOME DETAILS'!#REF! -> #REF!
J12: =SUM(J10:J11) -> 62
A13: 3.Faculty of Education
A14: Educational Management and planning | B14: Day program | C14: 0 | D14: 0 | E14: 0 | F14: 0 | G14: 0 | H14: 0 | I14: 0
B15: Weekend Program | C15: 0 | D15: 0 | E15: 0 | F15: 0 | G15: 0 | H15: 0 | I15: 0
B16: Holiday program | C16: 0 | D16: 0 | E16: 0 | F16: 0 | G16: 0 | H16: 0 | I16: 0
A17: Department of art and social science | B17: Day program | C17: 38 | D17: 98 | J17: 136
B18: Weekend Program | C18: 63 | D18: 17 | E18: 16 | F18: 12 | H18: 12 | J18: 120
B19: Holiday program | C19: 140 | E19: 5 | F19: 8 | H19: 8 | J19: 161 | K19: 137
A20: Department of Science | B20: Day program | C20: 54 | D20: 113 | J20: 167 | K20: =J17+J20 -> 303
B21: Weekend Program | C21: 16 | D21: 48 | E21: 56 | F21: 33 | H21: 33 | J21: 186 | K21: =K20-K19 -> 166
B22: Holiday program | C22: 137 | E22: 69 | F22: 47 | H22: 47 | J22: 300
A23: 4.Faculty of public health and Human Nutrition | J23: =SUM(J14:J22) -> 1070
A24: Public Health | B24: Day program | E24: 16 | F24: 45 | J24: =SUM(C24:I24) -> 61
B25: Weekend Program | J25: =SUM(C25:I25) -> 0
A26: Human Nutrition | B26: Day program | D26: 5 | J26: =SUM(C26:I26) -> 5
B27: Weekend Program | J27: =SUM(C27:I27) -> 0
A28: Nursing | B28: Day program | C28: =43+40 -> 83 | J28: =SUM(C28:I28) -> 83
B29: Weekend Program | J29: =SUM(C29:I29) -> 0
A30: Midwifery | B30: Day program | C30: =100+100 -> 200 | J30: =SUM(C30:I30) -> 200
B31: Weekend Program | J31: =SUM(C31:I31) -> 0
J32: =SUM(J24:J31) -> 349
A33: 5. Faculty of Catechesis | B33: Day program | C33: 57 | D33: 0 | E33: 30 | F33: 32 | I33: 1 | J33: =SUM(C33:I33) -> 120
B34: Weekend Program | C34: 0 | D34: 0 | E34: 0 | F34: 0 | J34: =SUM(C34:I34) -> 0
J35: =SUM(J33:J34) -> 120
A36: 6.Faculty of commerce | B36: Day program | C36: 40 | D36: 113 | H36: 18 | J36: =SUM(C36:I36) -> 171
B37: Weekend Program | C37: 27 | D37: 101 | E37: 48 | F37: 74 | H37: 62 | J37: =SUM(C37:I37) -> 312
J38: =SUM(J36:J37) -> 483
A39: 7.Postgraduate students
B40: Huye campus | G40: 70 | J40: =SUM(G40:I40) -> 70
B41: Ngoma Learning center | G41: 7 | J41: =SUM(G41:I41) -> 7
J42: =SUM(J40:J41) -> 77
A43: Grand total number of students | H43: =SUM(H14:H42) -> 180 | I43: =I9+I12+I23+I32+I35+I38+I42 -> 0 | J43: =J9+J12+J23+J32+J35+J38+J42 -> 2492

Sheet Sheet1
C2: L8 S1&2 | D2: L8 S3&4 | E2: L8 S5&6 | F2: L8 S7&8 | G2: L9 | H2: Graduands | I2: Partime | J2: Total students
A3: 3.Faculty of Education
A4: Educational Management and planning | B4: Day program | C4: 0 | D4: 0 | E4: 0 | F4: 0 | G4: 0 | H4: 0 | I4: 0
B5: Weekend Program | C5: 0 | D5: 0 | E5: 0 | F5: 0 | G5: 0 | H5: 0 | I5: 0
B6: Holiday program | C6: 0 | D6: 0 | E6: 0 | F6: 0 | G6: 0 | H6: 0 | I6: 0
A7: Department of art and social science | B7: Day program | C7: 38 | D7: 98 | J7: 136
B8: Weekend Program | C8: 63 | D8: 17 | E8: 16 | F8: 12 | H8: 12 | J8: 120
B9: Holiday program | C9: 140 | E9: 5 | F9: 8 | H9: 8 | J9: 161
A10: Department of Science | B10: Day program | C10: 54 | D10: 113 | J10: 167
B11: Weekend Program | C11: 16 | D11: 48 | E11: 56 | F11: 33 | H11: 33 | J11: 186
B12: Holiday program | C12: 137 | E12: 69 | F12: 47 | H12: 47 | J12: 300
D16: 3.Faculty of Education | E16: Educational Management and planning | H16: Department of art and social science | K16: Department of Science
E17: Day program | F17: Weekend Program | G17: Holiday program | H17: Day program | I17: Weekend Program | J17: Holiday program | K17: Day program | L17: Weekend Program | M17: Holiday program
C18: L8 S1&2 | E18: 0 | F18: 0 | G18: 0 | H18: 38 | I18: 63 | J18: 140 | K18: 54 | L18: 16 | M18: 137
C19: L8 S3&4 | E19: 0 | F19: 0 | G19: 0 | H19: 98 | I19: 17 | K19: 113 | L19: 48
C20: L8 S5&6 | E20: 0 | F20: 0 | G20: 0 | I20: 16 | J20: 5 | L20: 56 | M20: 69
C21: L8 S7&8 | E21: 0 | F21: 0 | G21: 0 | I21: 12 | J21: 8 | L21: 33 | M21: 47
C22: L9 | E22: 0 | F22: 0 | G22: 0
C23: Graduands | E23: 0 | F23: 0 | G23: 0 | I23: 12 | J23: 8 | L23: 33 | M23: 47
C24: Partime | E24: 0 | F24: 0 | G24: 0
C25: Total students | H25: 136 | I25: 120 | J25: 161 | K25: 167 | L25: 186 | M25: 300

Sheet Communication fees
A1: Communication fee Policy
A2: Rector | B2: =20000*2 -> 40000
A3: Vice-Rector | B3: 20000
A4: DAF | B4: 20000
A5: DOQ | B5: 15000
A6: Dean of FCRS | B6: 10000
A7: Dean of FED | B7: 10000
A8: Dean of FST | B8: 10000
A9: Dean of FCOM | B9: 10000
A10: Dean of FSW | B10: 10000
A11: Dean of FPHHN | B11: 10000
A12: Dean of students | B12: 10000
A13: Academic Registrar | B13: 10000
A14: Academic secretaries FCRS | B14: 10000
... A46: Driver 2 | B46: 3000
B47: =SUM(B2:B46) -> 466000

Sheet Responsability allowance
A1: Responsibility allowance
A2: Dean of FCRS | B2: 200000
A3: Dean of FED | B3: 200000
A4: Dean of FST | B4: 200000
A5: Dean of FCOM | B5: 200000
A6: Dean of FSW | B6: 200000
A7: Dean of FPHHN | B7: 200000
A8: Academic secretaries FCRS | B8: 150000
A9: Academic secretaries FED | B9: 150000
A10: Academic secretaries FST | B10: 150000
A11: Academic secretaries FCOM | B11: 150000
A12: Academic secretaries FSW | B12: 150000
A13: Academic secretaries FPHHN | B13: 150000
... A23: HOD HN&PH | B23: 150000
B24: =SUM(B2:B23) -> 3600000

Sheet Sheet5
A1: Panel fees
C2: Supervisor | D2: Panel members
A3: Number of graduates | B3: 260 | C3: =B3*15000 -> 3900000 | D3: =B3*2*10000 -> 5200000 | E3: =C3+D3 -> 9100000

Sheet Part-time staff cost
B4: Part-time
A5: FCRS | B5: 3574075
A6: FSW | B6: 3522960
A7: FST | B7: 2253360
A8: FPHHN | B8: 2419200
A9: FCOM | B9: 4094880
A10: FED | B10: 73274100
B11: 89138575
A12: 0.083 | B12: =B11*A12 -> 7398501.7
B13: =B11+B12 -> 96537077

Sheet STAFF COST DETAILS
A1: Proposed Salary structure | B1: Proposed new structure | C1: Existing structure | D1: Difference
A2: Senior Lecturer | B2: 1081433.7 | C2: 1029936.9 | D2: =B2-C2 -> 51496.843
A3: Lecturer | B3: 772600.95 | C3: 735810.43 | D3: =B3-C3 -> 36790.521
A4: Ass Lecturer | B4: 617402.25 | C4: 588002.14 | D4: =B4-C4 -> 29400.107
A5: Tutorial Ass | B5: 517495.5 | C5: 492853 | D5: =B5-C5 -> 24642.5
A7: This change of increase of 5% of basic salary will have overall impact which the following:
A8: Total staff cost will increase Monthly by:
A9: Academic staff | B9: =--893988.285714287 -> 893988.29
A10: Administratif staff | B10: 653976.13
A11: Total Monthly Increase | B11: =SUM(B9:B10) -> 1547964.4 | C11: 1547964.4
A12: Total annual increase in staff | B12: =B11*12 -> 18575573 | C12: 18575573
